Workbook
Name _aff306: '[1]BALANCE BFI INTERNAIONAL AU 30 '!$G$1:$G$65536
Name _DTF1: [2]Paramètres!$B$6
Name _sol306: '[1]BALANCE BFI INTERNAIONAL AU 30 '!$F$1:$F$65536
Name acc: [3]N_ACCTUN!$A$12:$C$629
Name ACLARACIONES_AYUDA: #REF!
Name AFEC: '[4]BALANCE AU 30.06.01'!$F$1:$F$65536
Name AFF: '[4]BALANCE AU 30.06.01'!$F$1:$F$65536
Name Affect: '[5]Balance comparative (2)'!$J$1:$J$65536
Name affect1: #REF!
Name affectation: [6]Bilan!$D$3:$D$239
Name AFFRT: [7]sum_ert!$A$1:$A$65536
Name am: [8]!am
Name AYUDA_PLAZO_ENTREGA: #REF!
Name az: [8]!az
Name Bal_CodeGroupeAnalyse: #REF!
Name Bal_CompteDebut: #REF!
Name Bal_CompteFin: #REF!
Name Bal_DateDebut: #REF!
Name Bal_DateFin: #REF!
Name Bal_NomGroupeAnalyse: #REF!
Name Bal_TypeEcriture: #REF!
Name BALANCE000999: #REF!
Name Balx_CodeGroupeAnalyse: [9]BALANCEAUX!$B$2
Name Balx_Compte: [9]BALANCEAUX!$D$2
Name Balx_DateDebut: [9]BALANCEAUX!$A$5
Name Balx_DateFin: [9]BALANCEAUX!$B$5
Name Balx_LibelleCompte: [9]BALANCEAUX!$D$3
Name Balx_NbLignes: [9]BALANCEAUX!#REF!
Name Balx_NomGroupeAnalyse: [9]BALANCEAUX!$B$3
Name Balx_TypeEcriture: [9]BALANCEAUX!$A$3
Name Beginning_Balance: #N/A
Name Beginning_Balance: #N/A
Name Beginning_Balance: #N/A
Name Beginning_Balance: #N/A
Name Beginning_Balance: #N/A
Name BIL_1: [10]BILAN!$P$3:$P$28,[10]BILAN!$G$3:$G$60
Name BIL_2: [10]BILAN!$Q$3:$Q$28,[10]BILAN!$H$3:$H$60
Name bilan: [8]!bilan
Name C_CLAVE_AYUDA: #REF!
Name Caseàcocher10_QuandClic: [8]!Caseàcocher10_QuandClic
Name Caseàcocher42_QuandClic: [8]!Caseàcocher42_QuandClic
Name CATE: [11]codes!$J$11:$J$14
Name CATE_NR.: [11]codes!$J$6
Name CDGR: [2]Paramètres!$A$1
Name CFA: #REF!
Name Charges: [8]!Charges
Name Choix_Imprimantes: [8]!Choix_Imprimantes
Name CODE_SEG: [12]Base.!$C$1:$C$65536
Name COM_BEB_AYUDA: #REF!
Name commentaires: [8]!commentaires
Name COMPARATIVO_AYUDA: #REF!
Name Contactos_AYUDA: #REF!
Name CURR: [11]codes!$F$5:$F$88
Name d: [8]!d
Name DATE: [13]Tréso!$B$5
Name Date_Paie: #REF!
Name Date_Paiement: DATE(YEAR(Début_Prêt),MONTH(Début_Prêt)+[0]!Payment_Number,DAY(Début_Prêt))
Name DATOS_AYUDA: #REF!
Name DC_AVW: #REF!
Name Début_Prêt: #REF!

Sheet Données
A1: Capacité nominale du système de production
A2: Désignation | B2: Nombre de sachet de 100 g/min | C2: Nombre de minute/jours | D2: Production moyenne journalière | E2: Capacité nominale mensuelle
A3: Capacité de Production moyenne forme coussin | B3: 68 | C3: =60*6 -> 360 | D3: =+B3*C3 -> 24480 | E3: =+D3*26 -> 636480
A4: Capacité de Production moyenne forme carré | B4: 43 | C4: =60*6 -> 360 | D4: =+B4*C4 -> 15480 | E4: =+D4*26 -> 402480
E6: =SUM(E3:E5) -> 1038960
A8: Rubrique | B8: Délai
A9: Délai de règlement Créances Clients | B9: 30 jours
A10: Délai de règlement dettes fournisseurs | B10: 30 jours
A11: Délai de démarrage | B11: 90 jours
A12: Nombre de jours / année | B12: 310 jours
A15: 1 kg Cacahuète necessite 60g/arome
A16: Une tonne de MP Nécessite 300 Dinars d'arome
A17: Prix d'achat emballage = 8,9 TND HT /Kg | B17: 11 | C17: =(8900/1000)*4 -> 35.6
A18: un sachet consomme 4 ou 5 gramme d'emballage(à 8 dinars le kg d'emballage , l'emballage de 100 gramme coute 32 millimes)
A19: Chaque carton comporte 36 Pièces de 100g
A20: le carton coute 0,600 TND | B20: 0.6
A22: Politique de vente c'est le porte à porte et se concentre essentiellement sur les grandes villes à savoir Tunis; Sousse et Sfax,
A23: Les achats MP emballage sont éffectués sur le marché local
A24: Les produits qui seront réalisés sont les produits salés
A25: le taux de déchet max 1%
A26: Prix d'achat MP
A27: Désignation de la rubrique | B27: P unitaire/Kg
A28: Mais | B28: 2.8
A29: Cacahuète | B29: 5.1
A30: Pois chiche | B30: 3.8
A31: Amande | B31: 25
A32: Acajou | B32: 22
A33: Pistache | B33: 24
A34: Noisette | B34: 24
A35: Aromes | B35: =10*2.2183 -> 22.183
A38: Poids
A39: Poid Brut en g | B39: Poid Net en g
A40: 100 | B40: 95
A41: 50 | B41: 45
A42: 400 | B42: 380
A45: Désignation de la rubrique | B45: QT produites mensuelle en Kg | C45: QT - sachet de 100 g | D45: PX UNIT | E45: Sachet de 100 g | F45: Prix de Vte unitaire
A46: PF Mais | B46: 3000 | C46: =+B46*10 -> 30000 | D46: 1 | E46: PF Mais | F46: 1
A47: PF Cacahuète | B47: 3000 | C47: =+B47*10 -> 30000 | D47: 1.4 | E47: PF Cacahuète | F47: 1.4
A48: PF Pois chiche | B48: 3000 | C48: =+B48*10 -> 30000 | D48: 1.2 | E48: PF Pois chiche | F48: 1.2
A49: PF Autres (noisette , pistche , acajou , amande) | B49: 1400 | C49: =+B49*10 -> 14000 | D49: 3.5 | E49: PF Autres (noisette , pistche , acajou , amande) | F49: 5
B51: =SUM(B46:B50) -> 10400 | C51: =SUM(C46:C50) -> 104000
A53: Simulation
A54: Vente | B54: 100000
A56: Production | B56: =+B54+(B54/288*10) -> 103472.22 | C56: Hypothèse : St de PF égal à 10J de CA
A58: Achats MP | B58: =+B56*1.08333333333333 -> 112094.91 | C58: Hypothèse : St de MP égal à 1 mois d'achats
A59: Achats Aromes | B59: =+(B56*60/1000)*13/12 -> 6725.6944 | C59: Hypothèse : St de Aromes égal à 1 mois d'achats
A60: Achats Emb | B60: =+(B56*50/1000)*13/12 -> 5604.7454 | C60: Hypothèse : St Emb égal à 1 mois d'achats
A61: Gaz
A62: Electricité
A63: Eau
A67: Stock PF | B67: =+B56-B54 -> 3472.2222 | C67: 10j de CA
A68: Stock MP | B68: =+B58-B56 -> 8622.6852 | C68: 1 mois d'achats
A69: Stock Aromes | B69: =+B59/13 -> 517.36111 | C69: 1 mois d'achats
A70: Stock Emb | B70: =+B60/13 -> 431.13426 | C70: 1 mois d'achats

Sheet Hypothèse
A2: Régime de TVA
A3: Mais : TVA 6% sur achat/P°/Vente (tableau B paragraphe I.11 du code de TVA)
A4: Autres fruits secs : 6% au niveau du transformation ; Tableau B paragraphe III .11
A5: Autres fruits secs sont soumis au taux de 18%
A7: Les importations des équipements sont soumis au taux de TVA de 6% Tableau B bis paragraphe I.3.a voir note commune N° 21/2014
A9: Le taux de ristourne est de 10% du chiffre d'affaire
A10: Production =320/310 jours vente | D10: =320/310 -> 1.0322581
A11: consommation= 101% prod
A12: Achat = (consommation-SI)*13/12
A13: stock MP = Achat/13

Sheet Schémas fin
A3: Source de financement | B3: Valeur | C3: %
A4: Fonds propres | B4: 180000 | C4: =+B4/$B$6 -> 0.3
A5: Crédit à Moyen Terme | B5: 420000 | C5: =+B5/$B$6 -> 0.7
A6: Total | B6: =SUM(B4:B5) -> 600000
B7: =+B6-Investissements!C32 -> -0.064428897

Sheet Investissements
A3: Investissements | B3: Valeur en DT | C3: Taux | F3: 2016 | G3: 2017 | H3: 2018 | I3: 2019 | J3: 2020 | K3: 2021 | L3: 2022 | M3: Total Amort | N3: VCN
A4: Logiciels de gestion | B4: =+C22 -> 5000 | C4: 0.3333 | F4: =+B4*C4 -> 1666.5 | G4: =+F4 -> 1666.5 | H4: =+G4+0.5 -> 1667 | I4: 0 | J4: 0 | K4: 0 | L4: 0 | M4: =+SUM(F4:L4) -> 5000 | N4: =+B4-M4 -> 0
A5: Agencement et aménagement construction | B5: =+C24 -> 26358.5 | C5: 0.1 | F5: =+B5*C5 -> 2635.85 | G5: =+F5 -> 2635.85 | H5: =+G5 -> 2635.85 | I5: =+H5 -> 2635.85 | J5: =+I5 -> 2635.85 | K5: =+J5 -> 2635.85 | L5: =+K5 -> 2635.85 | M5: =+SUM(F5:L5) -> 18450.95 | N5: =+B5-M5 -> 7907.55
A6: Matériels industriels | B6: =+C25 -> 253709.4 | C6: 0.1 | F6: =+B6*C6 -> 25370.94 | G6: =+F6 -> 25370.94 | H6: =+G6 -> 25370.94 | I6: =+H6 -> 25370.94 | J6: =+I6 -> 25370.94 | K6: =+J6 -> 25370.94 | L6: =+K6 -> 25370.94 | M6: =+SUM(F6:L6) -> 177596.58 | N6: =+B6-M6 -> 76112.82
A7: Matériel de transport | B7: =+C26 -> 97000 | C7: 0.2 | F7: =+B7*C7 -> 19400 | G7: =+F7 -> 19400 | H7: =+G7 -> 19400 | I7: =+H7 -> 19400 | J7: =+I7 -> 19400 | K7: 0 | L7: 0 | M7: =+SUM(F7:L7) -> 97000 | N7: =+B7-M7 -> 0
A8: Matériels et mobiliers de bureau | B8: =+C27 -> 12000 | C8: 0.1 | F8: =+B8*C8 -> 1200 | G8: =+F8 -> 1200 | H8: =+G8 -> 1200 | I8: =+H8 -> 1200 | J8: =+I8 -> 1200 | K8: =+J8 -> 1200 | L8: =+K8 -> 1200 | M8: =+SUM(F8:L8) -> 8400 | N8: =+B8-M8 -> 3600
A9: Autres matériels | B9: =+C28 -> 3500 | C9: 0.1 | F9: =+B9*C9 -> 350 | G9: =+F9 -> 350 | H9: =+G9 -> 350 | I9: =+H9 -> 350 | J9: =+I9 -> 350 | K9: =+J9 -> 350 | L9: =+K9 -> 350 | M9: =+SUM(F9:L9) -> 2450 | N9: =+B9-M9 -> 1050
A10: Frais préliminaires | B10: =+C30 -> 20500 | C10: 0.3333 | F10: =+B10*C10 -> 6832.65 | G10: =+F10 -> 6832.65 | H10: =+B10-(F10+G10) -> 6834.7 | I10: 0 | J10: 0 | K10: 0 | L10: 0 | M10: =+SUM(F10:L10) -> 20500 | N10: =+B10-M10 -> 0
B11: =SUM(B4:B10) -> 418067.9 | F11: =SUM(F5:F10) -> 55789.44 | G11: =SUM(G5:G10) -> 55789.44 | H11: =SUM(H5:H10) -> 55791.49 | I11: =SUM(I5:I10) -> 48956.79 | J11: =SUM(J5:J10) -> 48956.79 | K11: =SUM(K5:K10) -> 29556.79 | L11: =SUM(L5:L10) -> 29556.79 | M11: =SUM(M5:M10) -> 324397.53 | N11: =SUM(N5:N10) -> 88670.37
A13: Production anuelle | F13: =+#REF! -> #REF! | G13: =+#REF! -> #REF! | H13: =+#REF! -> #REF! | I13: =+#REF! -> #REF! | J13: =+#REF! -> #REF!
A15: Cout d'amort unit | F15: =+F6/F13 -> #REF! | G15: =+G6/G13 -> #REF! | H15: =+H6/H13 -> #REF! | I15: =+I6/I13 -> #REF! | J15: =+J6/J13 -> #REF!
A17: Droit de douane
A18: frais de transit
A19: frais de transport
A21: Investissements | C21: Valeur en DT | D21: %
A22: Logiciels de gestion | C22: 5000 | D22: =+C22/$C$32 -> 0.0083333324
A23: Sous-total Immobilisations Incorporelles | C23: =SUM(C22) -> 5000 | D23: =+C23/$C$32 -> 0.0083333324
A24: Agencement et aménagement construction | C24: =+D54 -> 26358.5 | D24: =+C24/$C$32 -> 0.043930829
A25: Matériels industriels | C25: =+D40 -> 253709.4 | D25: =+C25/$C$32 -> 0.42284895
A26: Matériels de transport | C26: =+D45 -> 97000 | D26: =+C26/$C$32 -> 0.16166665
A27: Matériels et mobiliers de bureau | C27: 12000 | D27: =+C27/$C$32 -> 0.019999998
A28: Autres matériels | C28: 3500 | D28: =+C28/$C$32 -> 0.0058333327
A29: Sous-total Immobilisations Corporelles | C29: =SUM(C24:C28) -> 392567.9 | D29: =+C29/$C$32 -> 0.65427976
A30: Frais préliminaires | C30: =+D61 -> 20500 | D30: =+C30/$C$32 -> 0.034166663
A31: Fonds de roulement | C31: =+ACTIFS!D27+ACTIFS!D31+ACTIFS!D35-PASSIFS!D34-PASSIFS!D35 -> 181932.16 | D31: =+C31/$C$32 -> 0.30322024 | F31: =+C31/TVA!D3*360 -> 35.464525 | G31: j de CA TTC
A32: Total | C32: =++C31+C30+C29+C23 -> 600000.06 | D32: =+C32/$C$32 -> 1
A34: Matériels industriels | B34: Quantité | C34: Valeur en USD | D34: Valeur en DT | E34: % | F34: Capacité de production Kg/H | G34: Capacité annuelle en Kg(8H/j) | H34: Production prévue 2016
A35: Machine d'Emballage Vertical | B35: 1 | C35: 53000 | D35: =+C35*2.083 -> 110399 | E35: =+D35/$D$40 -> 0.43513957 | F35: =6*60 -> 360 | G35: =+F35*8*26*12 -> 898560 | H35: =+'Consommations Q'!$C$11 -> 133285.16 | I35: =+H35/G35 -> 0.14833195
A36: Machines à Rôtir OS190 | B36: 2 | C36: 36000 | D36: =+C36*2.083 -> 74988 | E36: =+D36/$D$40 -> 0.2955665 | F36: =50*2 -> 100 | G36: =+F36*8*26*12 -> 249600 | H36: =+'Consommations Q'!$C$11 -> 133285.16 | I36: =+H36/G36 -> 0.53399504
A37: Machine à Salage | B37: 1 | C37: 5300 | D37: =+C37*2.083 -> 11039.9 | E37: =+D37/$D$40 -> 0.043513957 | F37: =40*4 -> 160 | G37: =+F37*8*26*12 -> 399360 | H37: =+'Consommations Q'!$C$11 -> 133285.16 | I37: =+H37/G37 -> 0.3337469
A38: Machine Dragée | B38: 3 | C38: 20000 | D38: =+C38*2.083 -> 41660 | E38: =+D38/$D$40 -> 0.16420361 | F38: 50 | G38: =+(F38*8*26*12)*4 -> 499200 | H38: =+'Consommations Q'!$C$11 -> 133285.16 | I38: =+H38/G38 -> 0.26699752
A39: Machine d'épluchage de noisette et cacahuète | B39: 1 | C39: 7500 | D39: =+C39*2.083 -> 15622.5 | E39: =+D39/$D$40 -> 0.061576355 | F39: 250 | G39: =+F39*8*26*12 -> 624000 | H39: =+'Consommations Q'!$C$11 -> 133285.16 | I39: =+H39/G39 -> 0.21359801
C40: =SUM(C35:C39) -> 121800 | D40: =SUM(D35:D39) -> 253709.4 | E40: =SUM(E35:E39) -> 1
A42: Matériels de transport | B42: Quantité | D42: Valeur en DT
A43: Fourgon (Jumper) | B43: 1 | D43: 45000
A44: Fourgonnette (Berlinguo) | B44: 2 | D44: 52000
D45: =SUM(D43:D44) -> 97000
A47: Agencement et aménagements construction | D47: Valeur en DT
A48: Climatisations | D48: 5700
A49: Installations Eléctricité | D49: 6500
A50: Installations téléphonique | D50: 4000
A51: Installation sécurité | D51: 3800
A52: Portes et fenêtre métalliques | D52: 5125
A53: Autres agencements | D53: =1665+22-4-570+147-32+7-1-1+1-0.5 -> 1233.5
D54: =SUM(D48:D53) -> 26358.5
A56: Frais préliminaires | D56: Valeur en DT
A57: Prospection commerciale et publicité | D57: 12000
A58: Etude de rentabilité | D58: 5000
A59: Formation du personnel | D59: 2000
A60: Frais de constitution | D60: 1500
D61: =SUM(D57:D60) -> 20500
A62: Autres immobilisations | D62: Valeur en DT
A63: Matériels et mobiliers de bureau | D63: 12000
A64: Autres matériels | D64: 3500
D65: =SUM(D63:D64) -> 15500

Sheet Prix achat-ventes
A1: Désignation de la rubrique | B1: Prix d'achat Kg | C1: Prix de vente Kg | D1: Prix de vente revendeur en sachet | E1: Prix marché sachet
A2: PF Mais | B2: =+Données!B28 -> 2.8 | C2: =+D2*10 -> 10 | D2: 1 | E2: 1
A3: PF Cacahuète | B3: =+Données!B29 -> 5.1 | C3: =+D3*10 -> 14 | D3: 1.4 | E3: 1.9
A4: PF Pois chiche | B4: =+Données!B30 -> 3.8 | C4: =+D4*10 -> 12 | D4: 1.2 | E4: 1.25
A5: PF Noisette | B5: =+Données!B34 -> 24 | C5: =+D5*10 -> 35 | D5: 3.5 | E5: 3
A6: PF Pistache | B6: =+Données!B33 -> 24 | C6: =+D6*10 -> 35 | D6: 3.5 | E6: 3.7
A7: PF Noix de Cajou | B7: =+Données!B32 -> 22 | C7: =+D7*10 -> 35 | D7: 3.5 | E7: 3.7
A8: PF Amande | B8: =+Données!B31 -> 25 | C8: =+D8*10 -> 35 | D8: 3.5 | E8: 3.7

Sheet Chiffre d'affaire
J1: 2016 | K1: 2017 | M1: 2018 | O1: 2019 | Q1: 2020 | S1: 2021 | U1: 2022
A2: Désignation de la rubrique | B2: QT produites en Kg/mois | C2: QT - sachet/mois | D2: PX UNIT | E2: CA Global mensuelle | F2: QT annuelle en Kg | G2: CA Annuelle/Sachet | H2: Ristourne 10% | I2: CA Net | J2: QT Annuel /Sachet | K2: QT Annuel /Sachet | L2: Valeurs | M2: QT Annuel /Sachet | N2: Valeurs | O2: QT Annuel /Sachet | P2: Valeurs | Q2: QT Annuel /Sachet | R2: Valeurs | S2: QT Annuel /Sachet | T2: Valeurs | U2: QT Annuel /Sachet | V2: Valeurs
A3: PF Mais | B3: 3120 | C3: =+B3*10 -> 31200 | D3: 1 | E3: =+C3*D3 -> 31200 | F3: =+B3*12 -> 37440 | G3: =+E3*12 -> 374400 | H3: =+G3*0.1 -> 37440 | I3: =+G3-H3 -> 336960 | J3: =+C3*12 -> 374400 | K3: =+J3*1.15 -> 430560 | L3: =+(K3*D3)*0.9 -> 387504 | M3: =+K3*1.15 -> 495144 | N3: =+(M3*D3)*0.9 -> 445629.6 | O3: =+M3*1.15 -> 569415.6 | P3: =+(O3*D3)*0.9 -> 512474.04 | Q3: =+O3*1.15 -> 654827.94 | R3: =+(Q3*D3)*0.9 -> 589345.15 | S3: =+Q3 -> 654827.94 | T3: =+(S3*D3)*0.9 -> 589345.15 | U3: =+S3 -> 654827.94 | V3: =+(U3*D3)*0.9 -> 589345.15
A4: PF Cacahuète | B4: 3120 | C4: =+B4*10 -> 31200 | D4: 1.4 | E4: =+C4*D4 -> 43680 | F4: =+B4*12 -> 37440 | G4: =+E4*12 -> 524160 | H4: =+G4*0.1 -> 52416 | I4: =+G4-H4 -> 471744 | J4: =+C4*12 -> 374400 | K4: =+J4*1.15 -> 430560 | L4: =+(K4*D4)*0.9 -> 542505.6 | M4: =+K4*1.15 -> 495144 | N4: =+(M4*D4)*0.9 -> 623881.44 | O4: =+M4*1.15 -> 569415.6 | P4: =+(O4*D4)*0.9 -> 717463.66 | Q4: =+O4*1.15 -> 654827.94 | R4: =+(Q4*D4)*0.9 -> 825083.2 | S4: =+Q4 -> 654827.94 | T4: =+(S4*D4)*0.9 -> 825083.2 | U4: =+S4 -> 654827.94 | V4: =+(U4*D4)*0.9 -> 825083.2
A5: PF Pois chiche | B5: 3120 | C5: =+B5*10 -> 31200 | D5: 1.2 | E5: =+C5*D5 -> 37440 | F5: =+B5*12 -> 37440 | G5: =+E5*12 -> 449280 | H5: =+G5*0.1 -> 44928 | I5: =+G5-H5 -> 404352 | J5: =+C5*12 -> 374400 | K5: =+J5*1.15 -> 430560 | L5: =+(K5*D5)*0.9 -> 465004.8 | M5: =+K5*1.15 -> 495144 | N5: =+(M5*D5)*0.9 -> 534755.52 | O5: =+M5*1.15 -> 569415.6 | P5: =+(O5*D5)*0.9 -> 614968.85 | Q5: =+O5*1.15 -> 654827.94 | R5: =+(Q5*D5)*0.9 -> 707214.18 | S5: =+Q5 -> 654827.94 | T5: =+(S5*D5)*0.9 -> 707214.18 | U5: =+S5 -> 654827.94 | V5: =+(U5*D5)*0.9 -> 707214.18
A6: PF noisette | B6: 350 | C6: =+B6*10 -> 3500 | D6: 3.5 | E6: =+C6*D6 -> 12250 | F6: =+B6*12 -> 4200 | G6: =+E6*12 -> 147000 | H6: =+G6*0.1 -> 14700 | I6: =+G6-H6 -> 132300 | J6: =+C6*12 -> 42000 | K6: =+J6*1.15 -> 48300 | L6: =+(K6*D6)*0.9 -> 152145 | M6: =+K6*1.15 -> 55545 | N6: =+(M6*D6)*0.9 -> 174966.75 | O6: =+M6*1.15 -> 63876.75 | P6: =+(O6*D6)*0.9 -> 201211.76 | Q6: =+O6*1.15 -> 73458.262 | R6: =+(Q6*D6)*0.9 -> 231393.53 | S6: =+Q6 -> 73458.262 | T6: =+(S6*D6)*0.9 -> 231393.53 | U6: =+S6 -> 73458.262 | V6: =+(U6*D6)*0.9 -> 231393.53
A7: PF pistche | B7: 350 | C7: =+B7*10 -> 3500 | D7: 3.5 | E7: =+C7*D7 -> 12250 | F7: =+B7*12 -> 4200 | G7: =+E7*12 -> 147000 | H7: =+G7*0.1 -> 14700 | I7: =+G7-H7 -> 132300 | J7: =+C7*12 -> 42000 | K7: =+J7*1.15 -> 48300 | L7: =+(K7*D7)*0.9 -> 152145 | M7: =+K7*1.15 -> 55545 | N7: =+(M7*D7)*0.9 -> 174966.75 | O7: =+M7*1.15 -> 63876.75 | P7: =+(O7*D7)*0.9 -> 201211.76 | Q7: =+O7*1.15 -> 73458.262 | R7: =+(Q7*D7)*0.9 -> 231393.53 | S7: =+Q7 -> 73458.262 | T7: =+(S7*D7)*0.9 -> 231393.53 | U7: =+S7 -> 73458.262 | V7: =+(U7*D7)*0.9 -> 231393.53
A8: PF acajou | B8: 350 | C8: =+B8*10 -> 3500 | D8: 3.5 | E8: =+C8*D8 -> 12250 | F8: =+B8*12 -> 4200 | G8: =+E8*12 -> 147000 | H8: =+G8*0.1 -> 14700 | I8: =+G8-H8 -> 132300 | J8: =+C8*12 -> 42000 | K8: =+J8*1.15 -> 48300 | L8: =+(K8*D8)*0.9 -> 152145 | M8: =+K8*1.15 -> 55545 | N8: =+(M8*D8)*0.9 -> 174966.75 | O8: =+M8*1.15 -> 63876.75 | P8: =+(O8*D8)*0.9 -> 201211.76 | Q8: =+O8*1.15 -> 73458.262 | R8: =+(Q8*D8)*0.9 -> 231393.53 | S8: =+Q8 -> 73458.262 | T8: =+(S8*D8)*0.9 -> 231393.53 | U8: =+S8 -> 73458.262 | V8: =+(U8*D8)*0.9 -> 231393.53
A9: PF Amande | B9: 350 | C9: =+B9*10 -> 3500 | D9: 3.5 | E9: =+C9*D9 -> 12250 | F9: =+B9*12 -> 4200 | G9: =+E9*12 -> 147000 | H9: =+G9*0.1 -> 14700 | I9: =+G9-H9 -> 132300 | J9: =+C9*12 -> 42000 | K9: =+J9*1.15 -> 48300 | L9: =+(K9*D9)*0.9 -> 152145 | M9: =+K9*1.15 -> 55545 | N9: =+(M9*D9)*0.9 -> 174966.75 | O9: =+M9*1.15 -> 63876.75 | P9: =+(O9*D9)*0.9 -> 201211.76 | Q9: =+O9*1.15 -> 73458.262 | R9: =+(Q9*D9)*0.9 -> 231393.53 | S9: =+Q9 -> 73458.262 | T9: =+(S9*D9)*0.9 -> 231393.53 | U9: =+S9 -> 73458.262 | V9: =+(U9*D9)*0.9 -> 231393.53
B10: =SUM(B3:B9) -> 10760 | C10: =SUM(C3:C9) -> 107600 | E10: =SUM(E3:E9) -> 161320 | F10: =SUM(F3:F9) -> 129120 | G10: =SUM(G3:G9) -> 1935840 | H10: =SUM(H3:H9) -> 193584 | I10: =SUM(I3:I9) -> 1742256 | J10: =SUM(J3:J9) -> 1291200 | K10: =SUM(K3:K9) -> 1484880 | L10: =SUM(L3:L9) -> 2003594.4 | ... V10: =SUM(V3:V9) -> 3047216.6
C11: =+C10*12 -> 1291200
K12: =+(K10-J10)/J10 -> 0.15 | M12: =+(M10-K10)/K10 -> 0.15 | N12: =+(N10-L10)/L10 -> 0.15 | O12: =+(O10-M10)/M10 -> 0.15 | P12: =+(P10-N10)/N10 -> 0.15 | Q12: =+(Q10-O10)/O10 -> 0.15 | R12: =+(R10-P10)/P10 -> 0.15 | S12: =+(S10-Q10)/Q10 -> 0 | T12: =+(T10-R10)/R10 -> 0 | V12: =+(V10-T10)/T10 -> 0
I13: Chiffre d'affaire y compris ristoune | N13: =+N10/0.9 -> 2560148.4 | P13: =+P10/0.9 -> 2944170.7 | R13: =+R10/0.9 -> 3385796.3 | T13: =+T10/0.9 -> 3385796.3
A17: Superette | B17: 100 | C17: =30*360*B17 -> 1080000 | D17: =+(C17/36)/100 -> 300
A18: Hotels | B18: 10 | C18: =100*360*B18 -> 360000 | D18: =+(C18/36)/100 -> 100
C19: =SUM(C17:C18) -> 1440000
A23: Produits | C23: Capacité de Ption annuelle
A24: Mais | B24: =+B3/$B$10 -> 0.28996283 | C24: =+B24*Investissements!$G$36*10 -> 723747.21
A25: Cacahuète | B25: =+B4/$B$10 -> 0.28996283 | C25: =+B25*Investissements!$G$36*10 -> 723747.21
A26: Pois chiche | B26: =+B5/$B$10 -> 0.28996283 | C26: =+B26*Investissements!$G$36*10 -> 723747.21
A27: Noisette | B27: =+B6/$B$10 -> 0.032527881 | C27: =+B27*Investissements!$G$36*10 -> 81189.591
A28: Pistche | B28: =+B7/$B$10 -> 0.032527881 | C28: =+B28*Investissements!$G$36*10 -> 81189.591
A29: Noix de Cajou | B29: =+B8/$B$10 -> 0.032527881 | C29: =+B29*Investissements!$G$36*10 -> 81189.591
A30: Amande | B30: =+B9/$B$10 -> 0.032527881 | C30: =+B30*Investissements!$G$36*10 -> 81189.591
B31: =SUM(B24:B30) -> 1 | C31: =SUM(C24:C30) -> 2496000
A34: Produits | B34: 2016 | C34: 2017 | D34: 2018 | E34: 2019 | F34: 2020 | G34: 2021 | H34: 2022
A35: Niveau de production/Capacité de production | B35: =+'Consommations Q'!C11*10/C31 -> 0.53399504 | C35: =+B35*1.15 -> 0.61409429 | D35: =+C35*1.15 -> 0.70620844 | E35: =+D35*1.15 -> 0.8121397 | F35: =+E35*1.15 -> 0.93396066 | G35: =+F35 -> 0.93396066 | H35: =+G35 -> 0.93396066
A36: Mais | B36: =+I3 -> 336960 | C36: =+L3 -> 387504 | D36: =+N3 -> 445629.6 | E36: =+P3 -> 512474.04 | F36: =+R3 -> 589345.15 | G36: =+T3 -> 589345.15 | H36: =+G36 -> 589345.15
A37: Cacahuète | B37: =+I4 -> 471744 | C37: =+L4 -> 542505.6 | D37: =+N4 -> 623881.44 | E37: =+P4 -> 717463.66 | F37: =+R4 -> 825083.2 | G37: =+T4 -> 825083.2 | H37: =+G37 -> 825083.2
A38: Pois chiche | B38: =+I5 -> 404352 | C38: =+L5 -> 465004.8 | D38: =+N5 -> 534755.52 | E38: =+P5 -> 614968.85 | F38: =+R5 -> 707214.18 | G38: =+T5 -> 707214.18 | H38: =+G38 -> 707214.18
A39: Noisette | B39: =+I6 -> 132300 | C39: =+L6 -> 152145 | D39: =+N6 -> 174966.75 | E39: =+P6 -> 201211.76 | F39: =+R6 -> 231393.53 | G39: =+T6 -> 231393.53 | H39: =+G39 -> 231393.53
A40: Pistche | B40: =+I7 -> 132300 | C40: =+L7 -> 152145 | D40: =+N7 -> 174966.75 | E40: =+P7 -> 201211.76 | F40: =+R7 -> 231393.53 | G40: =+T7 -> 231393.53 | H40: =+G40 -> 231393.53
A41: Noix de Cajou | B41: =+I8 -> 132300 | C41: =+L8 -> 152145 | D41: =+N8 -> 174966.75 | E41: =+P8 -> 201211.76 | F41: =+R8 -> 231393.53 | G41: =+T8 -> 231393.53 | H41: =+G41 -> 231393.53
A42: Amande | B42: =+I9 -> 132300 | C42: =+L9 -> 152145 | D42: =+N9 -> 174966.75 | E42: =+P9 -> 201211.76 | F42: =+R9 -> 231393.53 | G42: =+T9 -> 231393.53 | H42: =+G42 -> 231393.53
B43: =SUM(B36:B42) -> 1742256 | C43: =SUM(C36:C42) -> 2003594.4 | D43: =SUM(D36:D42) -> 2304133.6 | E43: =SUM(E36:E42) -> 2649753.6 | F43: =SUM(F36:F42) -> 3047216.6 | G43: =SUM(G36:G42) -> 3047216.6 | H43: =SUM(H36:H42) -> 3047216.6
B44: =+B43-'P&L'!C10 -> 0 | C44: =+C43-'P&L'!E10 -> 0 | D44: =+D43-'P&L'!G10 -> 0 | E44: =+E43-'P&L'!I10 -> 0 | F44: =+F43-'P&L'!K10 -> 0
B48: 2016 | D48: 2017 | F48: 2018 | H48: 2019 | J48: 2020 | L48: 2021 | N48: 2022
A49: Produits | B49: QT Annuel /Sachet | C49: Valeurs | D49: QT Annuel /Sachet | E49: Valeurs | F49: QT Annuel /Sachet | G49: Valeurs | H49: QT Annuel /Sachet | I49: Valeurs | J49: QT Annuel /Sachet | K49: Valeurs | L49: QT Annuel /Sachet | M49: Valeurs | N49: QT Annuel /Sachet | O49: Valeurs
A50: Mais | B50: 374400 | C50: 336960 | D50: 430560 | E50: 387504 | F50: 495144 | G50: 445629.6 | H50: 569415.6 | I50: 512474.04 | J50: 654827.94 | K50: 589345.15 | L50: 654827.94 | M50: 589345.15 | N50: 654827.94 | O50: 589345.15
A51: Cacahuète | B51: 374400 | C51: 471744 | D51: 430560 | E51: 542505.6 | F51: 495144 | G51: 623881.44 | H51: 569415.6 | I51: 717463.66 | J51: 654827.94 | K51: 825083.2 | L51: 654827.94 | M51: 825083.2 | N51: 654827.94 | O51: 825083.2
A52: Pois chiche | B52: 374400 | C52: 404352 | D52: 430560 | E52: 465004.8 | F52: 495144 | G52: 534755.52 | H52: 569415.6 | I52: 614968.85 | J52: 654827.94 | K52: 707214.18 | L52: 654827.94 | M52: 707214.18 | N52: 654827.94 | O52: 707214.18
A53: Noisette | B53: 42000 | C53: 132300 | D53: 48300 | E53: 152145 | F53: 55545 | G53: 174966.75 | H53: 63876.75 | I53: 201211.76 | J53: 73458.262 | K53: 231393.53 | L53: 73458.262 | M53: 231393.53 | N53: 73458.262 | O53: 231393.53
A54: Pistche | B54: 42000 | C54: 132300 | D54: 48300 | E54: 152145 | F54: 55545 | G54: 174966.75 | H54: 63876.75 | I54: 201211.76 | J54: 73458.262 | K54: 231393.53 | L54: 73458.262 | M54: 231393.53 | N54: 73458.262 | O54: 231393.53
A55: Noix de Cajou | B55: 42000 | C55: 132300 | D55: 48300 | E55: 152145 | F55: 55545 | G55: 174966.75 | H55: 63876.75 | I55: 201211.76 | J55: 73458.262 | K55: 231393.53 | L55: 73458.262 | M55: 231393.53 | N55: 73458.262 | O55: 231393.53
A56: Amande | B56: 42000 | C56: 132300 | D56: 48300 | E56: 152145 | F56: 55545 | G56: 174966.75 | H56: 63876.75 | I56: 201211.76 | J56: 73458.262 | K56: 231393.53 | L56: 73458.262 | M56: 231393.53 | N56: 73458.262 | O56: 231393.53
B57: =SUM(B50:B56) -> 1291200 | C57: =SUM(C50:C56) -> 1742256 | D57: =SUM(D50:D56) -> 1484880 | E57: =SUM(E50:E56) -> 2003594.4 | F57: =SUM(F50:F56) -> 1707612 | G57: =SUM(G50:G56) -> 2304133.6 | H57: =SUM(H50:H56) -> 1963753.8 | I57: =SUM(I50:I56) -> 2649753.6 | ... O57: =SUM(O50:O56) -> 3047216.6
B60: 2016 | C60: 2017 | D60: 2018 | E60: 2019 | F60: 2020 | G60: 2021 | H60: 2022
A61: Chiffre d'affaires | B61: =+B43 -> 1742256 | C61: =+C43 -> 2003594.4 | D61: =+D43 -> 2304133.6 | E61: =+E43 -> 2649753.6 | F61: =+F43 -> 3047216.6 | G61: =+G43 -> 3047216.6 | H61: =+H43 -> 3047216.6
A62: Achats consommés | B62: =+'Ach prévisionnel'!B97 -> 1131254.3 | C62: =+'Ach prévisionnel'!C97 -> 1306374.8 | D62: =+'Ach prévisionnel'!D97 -> 1502331 | E62: =+'Ach prévisionnel'!E97 -> 1727680.6 | F62: =+'Ach prévisionnel'!F97 -> 1986832.7 | G62: =+'Ach prévisionnel'!G97 -> 1988072 | H62: =+'Ach prévisionnel'!H97 -> 1988072
A63: Marge brute | B63: =+B61-B62 -> 611001.73 | C63: =+C61-C62 -> 697219.64 | D63: =+D61-D62 -> 801802.59 | E63: =+E61-E62 -> 922072.98 | F63: =+F61-F62 -> 1060383.9 | G63: =+G61-G62 -> 1059144.6 | H63: =+H61-H62 -> 1059144.6
A64: Taux de marge | B64: =+B63/B61 -> 0.35069573 | C64: =+C63/C61 -> 0.34798442 | D64: =+D63/D61 -> 0.34798442 | E64: =+E63/E61 -> 0.34798442 | F64: =+F63/F61 -> 0.34798442 | G64: =+G63/G61 -> 0.34757773 | H64: =+H63/H61 -> 0.34757773

Sheet Calcul Coût Ption
A1: Désignation de la rubrique | B1: QT annuelle en Kg | C1: Cout de Production | D1: Q st final | E1: Valeur stock final
A2: PF Mais aromatisés | B2: =+'Chiffre d''affaire'!F3+('Chiffre d''affaire'!F3/310*10) -> 38647.742 | C2: =+B23 -> 5.8884015 | D2: =+B2-'Chiffre d''affaire'!F3 -> 1207.7419 | E2: =+D2*C2 -> 7111.6695
A3: PF Cacahuète aromatisés | B3: =+'Chiffre d''affaire'!F4+('Chiffre d''affaire'!F4/310*10) -> 38647.742 | C3: =+C23 -> 8.3114015 | D3: =+B3-'Chiffre d''affaire'!F4 -> 1207.7419 | E3: =+D3*C3 -> 10038.028
A4: PF Pois chiche aromatisés | B4: =+'Chiffre d''affaire'!F5+('Chiffre d''affaire'!F5/310*10) -> 38647.742 | C4: =+D23 -> 6.9484015 | D4: =+B4-'Chiffre d''affaire'!F5 -> 1207.7419 | E4: =+D4*C4 -> 8391.8759
A5: PF noisette | B5: =+'Chiffre d''affaire'!F6+('Chiffre d''affaire'!F6/310*10) -> 4335.4839 | C5: =+E23 -> 27.925402 | D5: =+B5-'Chiffre d''affaire'!F6 -> 135.48387 | E5: =+D5*C5 -> 3783.4415
A6: PF pistche | B6: =+'Chiffre d''affaire'!F7+('Chiffre d''affaire'!F7/310*10) -> 4335.4839 | C6: =+F23 -> 27.925402 | D6: =+B6-'Chiffre d''affaire'!F7 -> 135.48387 | E6: =+D6*C6 -> 3783.4415
A7: PF acajou | B7: =+'Chiffre d''affaire'!F8+('Chiffre d''affaire'!F8/310*10) -> 4335.4839 | C7: =+G23 -> 25.905402 | D7: =+B7-'Chiffre d''affaire'!F8 -> 135.48387 | E7: =+D7*C7 -> 3509.7641
A8: PF Amande | B8: =+'Chiffre d''affaire'!F9+('Chiffre d''affaire'!F9/310*10) -> 4335.4839 | C8: =+H23 -> 28.935402 | D8: =+B8-'Chiffre d''affaire'!F9 -> 135.48387 | E8: =+D8*C8 -> 3920.2802
B9: =SUM(B2:B8) -> 133285.16 | D9: =SUM(D2:D8) -> 4165.1613 | E9: =SUM(E2:E8) -> 40538.501
B12: PF Mais | C12: PF Cacahuète | D12: PF Pois chiche | E12: PF noisette | F12: PF pistche | G12: PF acajou | H12: PF amande
A13: Calcul cout de production2016
A14: Achat MP | B14: ='Achat Matière'!C3 -> 2.8 | C14: =+'Achat Matière'!C4 -> 5.1 | D14: =+'Achat Matière'!C5 -> 3.8 | E14: =+'Achat Matière'!C6 -> 24 | F14: =+'Achat Matière'!C7 -> 24 | G14: =+'Achat Matière'!C8 -> 22 | H14: =+'Achat Matière'!C9 -> 25
A15: Achats Aromes | B15: =+Données!$B$35/1000*60 -> 1.33098 | C15: =+Données!$B$35/1000*60 -> 1.33098 | D15: =+Données!$B$35/1000*60 -> 1.33098 | E15: =+Données!$B$35/1000*60 -> 1.33098 | F15: =+Données!$B$35/1000*60 -> 1.33098 | G15: =+Données!$B$35/1000*60 -> 1.33098 | H15: =+Données!$B$35/1000*60 -> 1.33098
A16: Achat emballage | B16: =+'Achat Matière'!$F$14/1000*50 -> 0.55 | C16: =+'Achat Matière'!$F$14/1000*50 -> 0.55 | D16: =+'Achat Matière'!$F$14/1000*50 -> 0.55 | E16: =+'Achat Matière'!$F$14/1000*50 -> 0.55 | F16: =+'Achat Matière'!$F$14/1000*50 -> 0.55 | G16: =+'Achat Matière'!$F$14/1000*50 -> 0.55 | H16: =+'Achat Matière'!$F$14/1000*50 -> 0.55
A17: Gaz | B17: =+'Chiffre d''affaire'!D3*10*0.01 -> 0.1 | C17: =+'Chiffre d''affaire'!D4*10*0.01 -> 0.14 | D17: =+'Chiffre d''affaire'!D5*10*0.01 -> 0.12 | E17: =+'Chiffre d''affaire'!D6*10*0.01 -> 0.35 | F17: =+'Chiffre d''affaire'!$D$7*10*0.01 -> 0.35 | G17: =+'Chiffre d''affaire'!$D$8*10*0.01 -> 0.35 | H17: =+'Chiffre d''affaire'!$D$9*10*0.01 -> 0.35
A18: Electricité | B18: =+'Chiffre d''affaire'!D3*10*0.01 -> 0.1 | C18: =+'Chiffre d''affaire'!D4*10*0.01 -> 0.14 | D18: =+'Chiffre d''affaire'!D5*10*0.01 -> 0.12 | E18: =+'Chiffre d''affaire'!D6*10*0.01 -> 0.35 | F18: =+'Chiffre d''affaire'!$D$7*10*0.01 -> 0.35 | G18: =+'Chiffre d''affaire'!$D$8*10*0.01 -> 0.35 | H18: =+'Chiffre d''affaire'!$D$9*10*0.01 -> 0.35
A19: Eau | B19: =+'Chiffre d''affaire'!D3*10*0.005 -> 0.05 | C19: =+'Chiffre d''affaire'!D4*10*0.005 -> 0.07 | D19: =+'Chiffre d''affaire'!D5*10*0.005 -> 0.06 | E19: =+'Chiffre d''affaire'!D6*10*0.005 -> 0.175 | F19: =+'Chiffre d''affaire'!$D$7*10*0.005 -> 0.175 | G19: =+'Chiffre d''affaire'!$D$8*10*0.005 -> 0.175 | H19: =+'Chiffre d''affaire'!$D$9*10*0.005 -> 0.175
A20: Main d'œuvre | B20: =+SALAIRE!$C$27 -> 0.73907072 | C20: =+SALAIRE!$C$27 -> 0.73907072 | D20: =+SALAIRE!$C$27 -> 0.73907072 | E20: =+SALAIRE!$C$27 -> 0.73907072 | F20: =+SALAIRE!$C$27 -> 0.73907072 | G20: =+SALAIRE!$C$27 -> 0.73907072 | H20: =+SALAIRE!$C$27 -> 0.73907072
A21: Amortissement machine | B21: =+Investissements!$F$6/'Calcul Coût Ption'!$B$9 -> 0.19035082 | C21: =+Investissements!$F$6/'Calcul Coût Ption'!$B$9 -> 0.19035082 | D21: =+Investissements!$F$6/'Calcul Coût Ption'!$B$9 -> 0.19035082 | E21: =+Investissements!$F$6/'Calcul Coût Ption'!$B$9 -> 0.19035082 | F21: =+Investissements!$F$6/'Calcul Coût Ption'!$B$9 -> 0.19035082 | G21: =+Investissements!$F$6/'Calcul Coût Ption'!$B$9 -> 0.19035082 | H21: =+Investissements!$F$6/'Calcul Coût Ption'!$B$9 -> 0.19035082
A22: Dechets(1%) | B22: =1%*B14 -> 0.028 | C22: =1%*C14 -> 0.051 | D22: =1%*D14 -> 0.038 | E22: =1%*E14 -> 0.24 | F22: =1%*F14 -> 0.24 | G22: =1%*G14 -> 0.22 | H22: =1%*H14 -> 0.25
B23: =SUM(B14:B22) -> 5.8884015 | C23: =SUM(C14:C22) -> 8.3114015 | D23: =SUM(D14:D22) -> 6.9484015 | E23: =SUM(E14:E22) -> 27.925402 | F23: =SUM(F14:F22) -> 27.925402 | G23: =SUM(G14:G22) -> 25.905402 | H23: =SUM(H14:H22) -> 28.935402
A24: Prix de vente unitaire | B24: =+('Chiffre d''affaire'!D3*10)*0.9 -> 9 | C24: =+('Chiffre d''affaire'!D4*10)*0.9 -> 12.6 | D24: =+'Chiffre d''affaire'!D5*10*0.9 -> 10.8 | E24: =+'Chiffre d''affaire'!D6*10*0.9 -> 31.5 | F24: =+'Chiffre d''affaire'!D7*10*0.9 -> 31.5 | G24: =+'Chiffre d''affaire'!D8*10*0.9 -> 31.5 | H24: =+'Chiffre d''affaire'!D9*10*0.9 -> 31.5
A25: Marge/cout matière unit | B25: =+B24-SUM(B14:B19)-B22 -> 4.04102 | C25: =+C24-SUM(C14:C19)-C22 -> 5.21802 | D25: =+D24-SUM(D14:D19)-D22 -> 4.78102 | E25: =+E24-SUM(E14:E19)-E22 -> 4.50402 | F25: =+F24-SUM(F14:F19)-F22 -> 4.50402 | G25: =+G24-SUM(G14:G19)-G22 -> 6.52402 | H25: =+H24-SUM(H14:H19)-H22 -> 3.49402
A26: Taux de marge | B26: =+B25/B24 -> 0.44900222 | C26: =+C25/C24 -> 0.41412857 | D26: =+D25/D24 -> 0.44268704 | E26: =+E25/E24 -> 0.14298476 | F26: =+F25/F24 -> 0.14298476 | G26: =+G25/G24 -> 0.20711175 | H26: =+H25/H24 -> 0.11092127
B27: =+'Taux de marge'!G4 -> 0.45322954 | C27: =+'Taux de marge'!G5 -> 0.4174041 | D27: =+'Taux de marge'!G6 -> 0.44635914 | E27: =+'Taux de marge'!G7 -> 0.14483261 | F27: =+'Taux de marge'!G8 -> 0.14483261 | G27: =+'Taux de marge'!G9 -> 0.20895959 | H27: =+'Taux de marge'!G10 -> 0.11276912

Sheet Cout de production prévisionnel
B1: 2016 | F1: 2017 | J1: 2018 | N1: 2019 | R1: 2020 | V1: 2021 | Z1: 2022
A2: Désignation de la rubrique | B2: QT vendues annuelle en Kg | C2: Cout de Production | D2: Q st final | E2: Valeur stock final | F2: QT vendues annuelle en Kg | G2: Cout de Production | H2: Q st final | I2: Valeur stock final | J2: QT vendues annuelle en Kg | K2: Cout de Production | L2: Q st final | M2: Valeur stock final | N2: QT vendues annuelle en Kg | O2: Cout de Production | P2: Q st final | Q2: Valeur stock final | R2: QT vendues annuelle en Kg | S2: Cout de Production | T2: Q st final | U2: Valeur stock final | V2: QT vendues annuelle en Kg | W2: Cout de Production | X2: Q st final | Y2: Valeur stock final | Z2: QT vendues annuelle en Kg | AA2: Cout de Production | AB2: Q st final | AC2: Valeur stock final
A3: PF Mais aromatisés | B3: =+'Consommations Q'!B4 -> 37440 | C3: =+'Calcul Coût Ption'!C2 -> 5.8884015 | D3: =+B3/310*10 -> 1207.7419 | E3: =+C3*D3 -> 7111.6695 | F3: =+'Consommations Q'!G4 -> 43056 | G3: =+C3 -> 5.8884015 | H3: =+F3/310*10 -> 1388.9032 | I3: =+G3*H3 -> 8178.4199 | J3: =+'Consommations Q'!L4 -> 49514.4 | K3: =+G3 -> 5.8884015 | L3: =+J3/310*10 -> 1597.2387 | M3: =+K3*L3 -> 9405.1829 | N3: =+'Consommations Q'!Q4 -> 56941.56 | O3: =+K3 -> 5.8884015 | P3: =+N3/310*10 -> 1836.8245 | Q3: =+O3*P3 -> 10815.96 | R3: =+'Consommations Q'!V4 -> 65482.794 | S3: =+O3 -> 5.8884015 | T3: =+R3/310*10 -> 2112.3482 | U3: =+S3*T3 -> 12438.354 | V3: =+'Consommations Q'!AA4 -> 65482.794 | W3: =+S3 -> 5.8884015 | X3: =+V3/310*10 -> 2112.3482 | Y3: =+W3*X3 -> 12438.354 | Z3: =+'Consommations Q'!AF4 -> 65482.794 | AA3: =+W3 -> 5.8884015 | AB3: =+Z3/310*10 -> 2112.3482 | AC3: =+AA3*AB3 -> 12438.354
A4: PF Cacahuète aromatisés | B4: =+'Consommations Q'!B5 -> 37440 | C4: =+'Calcul Coût Ption'!C3 -> 8.3114015 | D4: =+B4/310*10 -> 1207.7419 | E4: =+C4*D4 -> 10038.028 | F4: =+'Consommations Q'!G5 -> 43056 | G4: =+C4 -> 8.3114015 | H4: =+F4/310*10 -> 1388.9032 | I4: =+G4*H4 -> 11543.732 | J4: =+'Consommations Q'!L5 -> 49514.4 | K4: =+G4 -> 8.3114015 | L4: =+J4/310*10 -> 1597.2387 | M4: =+K4*L4 -> 13275.292 | N4: =+'Consommations Q'!Q5 -> 56941.56 | O4: =+K4 -> 8.3114015 | P4: =+N4/310*10 -> 1836.8245 | Q4: =+O4*P4 -> 15266.586 | R4: =+'Consommations Q'!V5 -> 65482.794 | S4: =+O4 -> 8.3114015 | T4: =+R4/310*10 -> 2112.3482 | U4: =+S4*T4 -> 17556.574 | V4: =+'Consommations Q'!AA5 -> 65482.794 | W4: =+S4 -> 8.3114015 | X4: =+V4/310*10 -> 2112.3482 | Y4: =+W4*X4 -> 17556.574 | Z4: =+'Consommations Q'!AF5 -> 65482.794 | AA4: =+W4 -> 8.3114015 | AB4: =+Z4/310*10 -> 2112.3482 | AC4: =+AA4*AB4 -> 17556.574
A5: PF Pois chiche aromatisés | B5: =+'Consommations Q'!B6 -> 37440 | C5: =+'Calcul Coût Ption'!C4 -> 6.9484015 | D5: =+B5/310*10 -> 1207.7419 | E5: =+C5*D5 -> 8391.8759 | F5: =+'Consommations Q'!G6 -> 43056 | G5: =+C5 -> 6.9484015 | H5: =+F5/310*10 -> 1388.9032 | I5: =+G5*H5 -> 9650.6573 | J5: =+'Consommations Q'!L6 -> 49514.4 | K5: =+G5 -> 6.9484015 | L5: =+J5/310*10 -> 1597.2387 | M5: =+K5*L5 -> 11098.256 | N5: =+'Consommations Q'!Q6 -> 56941.56 | O5: =+K5 -> 6.9484015 | P5: =+N5/310*10 -> 1836.8245 | Q5: =+O5*P5 -> 12762.994 | R5: =+'Consommations Q'!V6 -> 65482.794 | S5: =+O5 -> 6.9484015 | T5: =+R5/310*10 -> 2112.3482 | U5: =+S5*T5 -> 14677.443 | V5: =+'Consommations Q'!AA6 -> 65482.794 | W5: =+S5 -> 6.9484015 | X5: =+V5/310*10 -> 2112.3482 | Y5: =+W5*X5 -> 14677.443 | Z5: =+'Consommations Q'!AF6 -> 65482.794 | AA5: =+W5 -> 6.9484015 | AB5: =+Z5/310*10 -> 2112.3482 | AC5: =+AA5*AB5 -> 14677.443
A6: PF noisette | B6: =+'Consommations Q'!B7 -> 4200 | C6: =+'Calcul Coût Ption'!C5 -> 27.925402 | D6: =+B6/310*10 -> 135.48387 | E6: =+C6*D6 -> 3783.4415 | F6: =+'Consommations Q'!G7 -> 4830 | G6: =+C6 -> 27.925402 | H6: =+F6/310*10 -> 155.80645 | I6: =+G6*H6 -> 4350.9577 | J6: =+'Consommations Q'!L7 -> 5554.5 | K6: =+G6 -> 27.925402 | L6: =+J6/310*10 -> 179.17742 | M6: =+K6*L6 -> 5003.6014 | N6: =+'Consommations Q'!Q7 -> 6387.675 | O6: =+K6 -> 27.925402 | P6: =+N6/310*10 -> 206.05403 | Q6: =+O6*P6 -> 5754.1416 | R6: =+'Consommations Q'!V7 -> 7345.8262 | S6: =+O6 -> 27.925402 | T6: =+R6/310*10 -> 236.96214 | U6: =+S6*T6 -> 6617.2628 | V6: =+'Consommations Q'!AA7 -> 7345.8262 | W6: =+S6 -> 27.925402 | X6: =+V6/310*10 -> 236.96214 | Y6: =+W6*X6 -> 6617.2628 | Z6: =+'Consommations Q'!AF7 -> 7345.8262 | AA6: =+W6 -> 27.925402 | AB6: =+Z6/310*10 -> 236.96214 | AC6: =+AA6*AB6 -> 6617.2628
A7: PF pistche | B7: =+'Consommations Q'!B8 -> 4200 | C7: =+'Calcul Coût Ption'!C6 -> 27.925402 | D7: =+B7/310*10 -> 135.48387 | E7: =+C7*D7 -> 3783.4415 | F7: =+'Consommations Q'!G8 -> 4830 | G7: =+C7 -> 27.925402 | H7: =+F7/310*10 -> 155.80645 | I7: =+G7*H7 -> 4350.9577 | J7: =+'Consommations Q'!L8 -> 5554.5 | K7: =+G7 -> 27.925402 | L7: =+J7/310*10 -> 179.17742 | M7: =+K7*L7 -> 5003.6014 | N7: =+'Consommations Q'!Q8 -> 6387.675 | O7: =+K7 -> 27.925402 | P7: =+N7/310*10 -> 206.05403 | Q7: =+O7*P7 -> 5754.1416 | R7: =+'Consommations Q'!V8 -> 7345.8262 | S7: =+O7 -> 27.925402 | T7: =+R7/310*10 -> 236.96214 | U7: =+S7*T7 -> 6617.2628 | V7: =+'Consommations Q'!AA8 -> 7345.8262 | W7: =+S7 -> 27.925402 | X7: =+V7/310*10 -> 236.96214 | Y7: =+W7*X7 -> 6617.2628 | Z7: =+'Consommations Q'!AF8 -> 7345.8262 | AA7: =+W7 -> 27.925402 | AB7: =+Z7/310*10 -> 236.96214 | AC7: =+AA7*AB7 -> 6617.2628
A8: PF acajou | B8: =+'Consommations Q'!B9 -> 4200 | C8: =+'Calcul Coût Ption'!C7 -> 25.905402 | D8: =+B8/310*10 -> 135.48387 | E8: =+C8*D8 -> 3509.7641 | F8: =+'Consommations Q'!G9 -> 4830 | G8: =+C8 -> 25.905402 | H8: =+F8/310*10 -> 155.80645 | I8: =+G8*H8 -> 4036.2287 | J8: =+'Consommations Q'!L9 -> 5554.5 | K8: =+G8 -> 25.905402 | L8: =+J8/310*10 -> 179.17742 | M8: =+K8*L8 -> 4641.663 | N8: =+'Consommations Q'!Q9 -> 6387.675 | O8: =+K8 -> 25.905402 | P8: =+N8/310*10 -> 206.05403 | Q8: =+O8*P8 -> 5337.9124 | R8: =+'Consommations Q'!V9 -> 7345.8262 | S8: =+O8 -> 25.905402 | T8: =+R8/310*10 -> 236.96214 | U8: =+S8*T8 -> 6138.5993 | V8: =+'Consommations Q'!AA9 -> 7345.8262 | W8: =+S8 -> 25.905402 | X8: =+V8/310*10 -> 236.96214 | Y8: =+W8*X8 -> 6138.5993 | Z8: =+'Consommations Q'!AF9 -> 7345.8262 | AA8: =+W8 -> 25.905402 | AB8: =+Z8/310*10 -> 236.96214 | AC8: =+AA8*AB8 -> 6138.5993
A9: PF Amande | B9: =+'Consommations Q'!B10 -> 4200 | C9: =+'Calcul Coût Ption'!C8 -> 28.935402 | D9: =+B9/310*10 -> 135.48387 | E9: =+C9*D9 -> 3920.2802 | F9: =+'Consommations Q'!G10 -> 4830 | G9: =+C9 -> 28.935402 | H9: =+F9/310*10 -> 155.80645 | I9: =+G9*H9 -> 4508.3222 | J9: =+'Consommations Q'!L10 -> 5554.5 | K9: =+G9 -> 28.935402 | L9: =+J9/310*10 -> 179.17742 | M9: =+K9*L9 -> 5184.5706 | N9: =+'Consommations Q'!Q10 -> 6387.675 | O9: =+K9 -> 28.935402 | P9: =+N9/310*10 -> 206.05403 | Q9: =+O9*P9 -> 5962.2562 | R9: =+'Consommations Q'!V10 -> 7345.8262 | S9: =+O9 -> 28.935402 | T9: =+R9/310*10 -> 236.96214 | U9: =+S9*T9 -> 6856.5946 | V9: =+'Consommations Q'!AA10 -> 7345.8262 | W9: =+S9 -> 28.935402 | X9: =+V9/310*10 -> 236.96214 | Y9: =+W9*X9 -> 6856.5946 | Z9: =+'Consommations Q'!AF10 -> 7345.8262 | AA9: =+W9 -> 28.935402 | AB9: =+Z9/310*10 -> 236.96214 | AC9: =+AA9*AB9 -> 6856.5946
B10: =SUM(B3:B9) -> 129120 | D10: =SUM(D3:D9) -> 4165.1613 | E10: =SUM(E3:E9) -> 40538.501 | F10: =SUM(F3:F9) -> 148488 | H10: =SUM(H3:H9) -> 4789.9355 | I10: =SUM(I3:I9) -> 46619.276 | J10: =SUM(J3:J9) -> 170761.2 | K10: =SUM(K3:K9) -> 131.83981 | L10: =SUM(L3:L9) -> 5508.4258 | M10: =SUM(M3:M9) -> 53612.167 | N10: =SUM(N3:N9) -> 196375.38 | O10: =SUM(O3:O9) -> 131.83981 | ... AC10: =SUM(AC3:AC9) -> 70902.091
A12: Variation du Stock | E12: =0-E10 -> -40538.501 | I12: =+E10-I10 -> -6080.7751 | M12: =+I10-M10 -> -6992.8914 | Q12: =+M10-Q10 -> -8041.8251 | U12: =+Q10-U10 -> -9248.0989 | Y12: =+U10-Y10 -> 0 | AC12: =+Y10-AC10 -> 0
B14: 2016 | C14: 2017 | D14: 2018 | E14: 2019 | F14: 2020 | G14: 2021 | H14: 2022
A15: Désignation de la rubrique | B15: Qt matière consommées | C15: Qt matière consommées | D15: Qt matière consommées | E15: Qt matière consommées | F15: Qt matière consommées | G15: Qt matière consommées | H15: Qt matière consommées
A16: PF Mais aromatisés
A17: PF Cacahuète aromatisés
A18: PF Pois chiche aromatisés
A19: PF noisette
A20: PF pistche
A21: PF acajou
A22: PF Amande
B23: =SUM(B16:B22) -> 0 | C23: =SUM(C16:C22) -> 0 | D23: =SUM(D16:D22) -> 0 | E23: =SUM(E16:E22) -> 0 | F23: =SUM(F16:F22) -> 0 | G23: =SUM(G16:G22) -> 0 | H23: =SUM(H16:H22) -> 0

Sheet Taux de marge
A1: 2016
A3: Produits | B3: Chiffre d'affaire net | C3: Consommations matière | D3: Consommations Autres approv | E3: Variation St. P finis | F3: Marge Brut | G3: Taux de marge
A4: PF Mais | B4: =+'Chiffre d''affaire'!I3 -> 336960 | C4: =+(('Ach prévisionnel'!D3-'Ach prévisionnel'!F3)+('Ach prévisionnel'!D17+'Ach prévisionnel'!D30)) -> 181991.44 | D4: =+(B4/0.9)*0.025 -> 9360 | E4: =-'Cout de production prévisionnel'!E3 -> -7111.6695 | F4: =+(B4-(C4+D4+E4)) -> 152720.23 | G4: =+F4/B4 -> 0.45322954
A5: PF Cacahuète | B5: =+'Chiffre d''affaire'!I4 -> 471744 | C5: =+(('Ach prévisionnel'!D4-'Ach prévisionnel'!F4)+'Ach prévisionnel'!D18+'Ach prévisionnel'!D31) -> 271770.15 | D5: =+(B5/0.9)*0.025 -> 13104 | E5: =-'Cout de production prévisionnel'!E4 -> -10038.028 | F5: =+(B5-(C5+D5+E5)) -> 196907.88 | G5: =+F5/B5 -> 0.4174041
A6: PF Pois chiche | B6: =+'Chiffre d''affaire'!I5 -> 404352 | C6: =+('Ach prévisionnel'!D5-'Ach prévisionnel'!F5)+'Ach prévisionnel'!D19+'Ach prévisionnel'!D32 -> 221025.66 | D6: =+(B6/0.9)*0.025 -> 11232 | E6: =-'Cout de production prévisionnel'!E5 -> -8391.8759 | F6: =+(B6-(C6+D6+E6)) -> 180486.21 | G6: =+F6/B6 -> 0.44635914
A7: PF noisette | B7: =+'Chiffre d''affaire'!I6 -> 132300 | C7: =+('Ach prévisionnel'!D6-'Ach prévisionnel'!F6)+'Ach prévisionnel'!D20+'Ach prévisionnel'!D33 -> 113247.09 | D7: =+(B7/0.9)*0.025 -> 3675 | E7: =-'Cout de production prévisionnel'!E6 -> -3783.4415 | F7: =+(B7-(C7+D7+E7)) -> 19161.354 | G7: =+F7/B7 -> 0.14483261
A8: PF pistche | B8: =+'Chiffre d''affaire'!I7 -> 132300 | C8: =+('Ach prévisionnel'!D7-'Ach prévisionnel'!F7)+'Ach prévisionnel'!D21+'Ach prévisionnel'!D34 -> 113247.09 | D8: =+(B8/0.9)*0.025 -> 3675 | E8: =-'Cout de production prévisionnel'!E7 -> -3783.4415 | F8: =+(B8-(C8+D8+E8)) -> 19161.354 | G8: =+F8/B8 -> 0.14483261
A9: PF acajou | B9: =+'Chiffre d''affaire'!I8 -> 132300 | C9: =+('Ach prévisionnel'!D8-'Ach prévisionnel'!F8)+'Ach prévisionnel'!D22+'Ach prévisionnel'!D35 -> 104489.41 | D9: =+(B9/0.9)*0.025 -> 3675 | E9: =-'Cout de production prévisionnel'!E8 -> -3509.7641 | F9: =+(B9-(C9+D9+E9)) -> 27645.354 | G9: =+F9/B9 -> 0.20895959
A10: PF Amande | B10: =+'Chiffre d''affaire'!I9 -> 132300 | C10: =+('Ach prévisionnel'!D9-'Ach prévisionnel'!F9)+'Ach prévisionnel'!D23+'Ach prévisionnel'!D36 -> 117625.93 | D10: =+(B10/0.9)*0.025 -> 3675 | E10: =-'Cout de production prévisionnel'!E9 -> -3920.2802 | F10: =+(B10-(C10+D10+E10)) -> 14919.354 | G10: =+F10/B10 -> 0.11276912
B12: =SUM(B4:B11) -> 1742256 | C12: =SUM(C4:C11) -> 1123396.8 | D12: =SUM(D4:D11) -> 48396 | E12: =SUM(E4:E11) -> -40538.501 | F12: =SUM(F4:F11) -> 611001.73 | G12: =+F12/B12 -> 0.35069573 | I12: =SUM(C12:E12) -> 1131254.3
A14: 2017
A15: Produits | B15: Chiffre d'affaire | C15: Consommations matière | D15: Consommations Autres approv | E15: Variation St. P finis | F15: Marge Brut | G15: Taux de marge
A16: PF Mais | B16: =+'Chiffre d''affaire'!L3 -> 387504 | C16: =('Ach prévisionnel'!I3+'Ach prévisionnel'!F3-'Ach prévisionnel'!K3)+'Ach prévisionnel'!I17+'Ach prévisionnel'!I30 -> 203602.93 | D16: =+(B16/0.9)*0.025 -> 10764 | E16: =+'Cout de production prévisionnel'!E3-'Cout de production prévisionnel'!I3 -> -1066.7504 | F16: =+(B16-(C16+D16+E16)) -> 174203.82 | G16: =+F16/B16 -> 0.44955361
A17: PF Cacahuète | B17: =+'Chiffre d''affaire'!L4 -> 542505.6 | C17: =('Ach prévisionnel'!I4+'Ach prévisionnel'!F4-'Ach prévisionnel'!K4)+'Ach prévisionnel'!I18+'Ach prévisionnel'!I31 -> 304042.85 | D17: =+(B17/0.9)*0.025 -> 15069.6 | E17: =+'Cout de production prévisionnel'!E4-'Cout de production prévisionnel'!I4 -> -1505.7042 | F17: =+(B17-(C17+D17+E17)) -> 224898.85 | G17: =+F17/B17 -> 0.41455581
A18: PF Pois chiche | B18: =+'Chiffre d''affaire'!L5 -> 465004.8 | C18: =('Ach prévisionnel'!I5+'Ach prévisionnel'!F5-'Ach prévisionnel'!K5)+'Ach prévisionnel'!I19+'Ach prévisionnel'!I32 -> 247272.46 | D18: =+(B18/0.9)*0.025 -> 12916.8 | E18: =+'Cout de production prévisionnel'!E5-'Cout de production prévisionnel'!I5 -> -1258.7814 | F18: =+(B18-(C18+D18+E18)) -> 206074.32 | G18: =+F18/B18 -> 0.44316601
A19: PF noisette | B19: =+'Chiffre d''affaire'!L6 -> 152145 | C19: =('Ach prévisionnel'!I6+'Ach prévisionnel'!F6-'Ach prévisionnel'!K6)+'Ach prévisionnel'!I20+'Ach prévisionnel'!I33 -> 126695.18 | D19: =+(B19/0.9)*0.025 -> 4226.25 | E19: =+'Cout de production prévisionnel'!E6-'Cout de production prévisionnel'!I6 -> -567.51622 | F19: =+(B19-(C19+D19+E19)) -> 21791.087 | G19: =+F19/B19 -> 0.14322579
A20: PF pistche | B20: =+'Chiffre d''affaire'!L7 -> 152145 | C20: =('Ach prévisionnel'!I7+'Ach prévisionnel'!F7-'Ach prévisionnel'!K7)+'Ach prévisionnel'!I21+'Ach prévisionnel'!I34 -> 126695.18 | D20: =+(B20/0.9)*0.025 -> 4226.25 | E20: =+'Cout de production prévisionnel'!E7-'Cout de production prévisionnel'!I7 -> -567.51622 | F20: =+(B20-(C20+D20+E20)) -> 21791.087 | G20: =+F20/B20 -> 0.14322579
A21: PF acajou | B21: =+'Chiffre d''affaire'!L8 -> 152145 | C21: =('Ach prévisionnel'!I8+'Ach prévisionnel'!F8-'Ach prévisionnel'!K8)+'Ach prévisionnel'!I22+'Ach prévisionnel'!I35 -> 116897.53 | D21: =+(B21/0.9)*0.025 -> 4226.25 | E21: =+'Cout de production prévisionnel'!E8-'Cout de production prévisionnel'!I8 -> -526.46461 | F21: =+(B21-(C21+D21+E21)) -> 31547.687 | G21: =+F21/B21 -> 0.20735277
A22: PF Amande | B22: =+'Chiffre d''affaire'!L9 -> 152145 | C22: =('Ach prévisionnel'!I9+'Ach prévisionnel'!F9-'Ach prévisionnel'!K9)+'Ach prévisionnel'!I23+'Ach prévisionnel'!I36 -> 131594 | D22: =+(B22/0.9)*0.025 -> 4226.25 | E22: =+'Cout de production prévisionnel'!E9-'Cout de production prévisionnel'!I9 -> -588.04203 | F22: =+(B22-(C22+D22+E22)) -> 16912.787 | G22: =+F22/B22 -> 0.11116229
B24: =SUM(B16:B23) -> 2003594.4 | C24: =SUM(C16:C23) -> 1256800.1 | D24: =SUM(D16:D23) -> 55655.4 | E24: =SUM(E16:E23) -> -6080.7751 | F24: =SUM(F16:F23) -> 697219.64 | G24: =+F24/B24 -> 0.34798442 | I24: =SUM(C24:E24) -> 1306374.8
A25: 2018
A26: Produits | B26: Chiffre d'affaire | C26: Consommations matière | D26: Consommations Autres approv | E26: Variation St. P finis | F26: Marge Brut | G26: Taux de marge
A27: PF Mais | B27: =+'Chiffre d''affaire'!N3 -> 445629.6 | C27: =+('Ach prévisionnel'!N3+'Ach prévisionnel'!K3-'Ach prévisionnel'!P3)+'Ach prévisionnel'!N17+'Ach prévisionnel'!N30 -> 234143.37 | D27: =+(B27/0.9)*0.025 -> 12378.6 | E27: ='Cout de production prévisionnel'!I3-'Cout de production prévisionnel'!M3 -> -1226.763 | F27: =+(B27-(C27+D27+E27)) -> 200334.4 | G27: =+F27/B27 -> 0.44955361
A28: PF Cacahuète | B28: =+'Chiffre d''affaire'!N4 -> 623881.44 | C28: =+('Ach prévisionnel'!N4+'Ach prévisionnel'!K4-'Ach prévisionnel'!P4)+'Ach prévisionnel'!N18+'Ach prévisionnel'!N31 -> 349649.28 | D28: =+(B28/0.9)*0.025 -> 17330.04 | E28: ='Cout de production prévisionnel'!I4-'Cout de production prévisionnel'!M4 -> -1731.5599 | F28: =+(B28-(C28+D28+E28)) -> 258633.68 | G28: =+F28/B28 -> 0.41455581
A29: PF Pois chiche | B29: =+'Chiffre d''affaire'!N5 -> 534755.52 | C29: =+('Ach prévisionnel'!N5+'Ach prévisionnel'!K5-'Ach prévisionnel'!P5)+'Ach prévisionnel'!N19+'Ach prévisionnel'!N32 -> 284363.33 | D29: =+(B29/0.9)*0.025 -> 14854.32 | E29: ='Cout de production prévisionnel'!I5-'Cout de production prévisionnel'!M5 -> -1447.5986 | F29: =+(B29-(C29+D29+E29)) -> 236985.47 | G29: =+F29/B29 -> 0.44316601
A30: PF noisette | B30: =+'Chiffre d''affaire'!N6 -> 174966.75 | C30: =+('Ach prévisionnel'!N6+'Ach prévisionnel'!K6-'Ach prévisionnel'!P6)+'Ach prévisionnel'!N20+'Ach prévisionnel'!N33 -> 145699.46 | D30: =+(B30/0.9)*0.025 -> 4860.1875 | E30: ='Cout de production prévisionnel'!I6-'Cout de production prévisionnel'!M6 -> -652.64366 | F30: =+(B30-(C30+D30+E30)) -> 25059.75 | G30: =+F30/B30 -> 0.14322579
A31: PF pistche | B31: =+'Chiffre d''affaire'!N7 -> 174966.75 | C31: =+('Ach prévisionnel'!N7+'Ach prévisionnel'!K7-'Ach prévisionnel'!P7)+'Ach prévisionnel'!N21+'Ach prévisionnel'!N34 -> 145699.46 | D31: =+(B31/0.9)*0.025 -> 4860.1875 | E31: ='Cout de production prévisionnel'!I7-'Cout de production prévisionnel'!M7 -> -652.64366 | F31: =+(B31-(C31+D31+E31)) -> 25059.75 | G31: =+F31/B31 -> 0.14322579
A32: PF acajou | B32: =+'Chiffre d''affaire'!N8 -> 174966.75 | C32: =+('Ach prévisionnel'!N8+'Ach prévisionnel'!K8-'Ach prévisionnel'!P8)+'Ach prévisionnel'!N22+'Ach prévisionnel'!N35 -> 134432.16 | D32: =+(B32/0.9)*0.025 -> 4860.1875 | E32: ='Cout de production prévisionnel'!I8-'Cout de production prévisionnel'!M8 -> -605.4343 | F32: =+(B32-(C32+D32+E32)) -> 36279.84 | G32: =+F32/B32 -> 0.20735277
A33: PF Amande | B33: =+'Chiffre d''affaire'!N9 -> 174966.75 | C33: =+('Ach prévisionnel'!N9+'Ach prévisionnel'!K9-'Ach prévisionnel'!P9)+'Ach prévisionnel'!N23+'Ach prévisionnel'!N36 -> 151333.11 | D33: =+(B33/0.9)*0.025 -> 4860.1875 | E33: ='Cout de production prévisionnel'!I9-'Cout de production prévisionnel'!M9 -> -676.24834 | F33: =+(B33-(C33+D33+E33)) -> 19449.705 | G33: =+F33/B33 -> 0.11116229
B35: =SUM(B27:B34) -> 2304133.6 | C35: =SUM(C27:C34) -> 1445320.2 | D35: =SUM(D27:D34) -> 64003.71 | E35: =SUM(E27:E34) -> -6992.8914 | F35: =SUM(F27:F34) -> 801802.59 | G35: =+F35/B35 -> 0.34798442 | I35: =SUM(C35:E35) -> 1502331
A36: 2019
A37: Produits | B37: Chiffre d'affaire | C37: Consommations matière | D37: Consommations Autres approv | E37: Variation St. P finis | F37: Marge Brut | G37: Taux de marge
A38: PF Mais | B38: =+'Chiffre d''affaire'!P3 -> 512474.04 | C38: =+('Ach prévisionnel'!S3+'Ach prévisionnel'!P3-'Ach prévisionnel'!U3)+'Ach prévisionnel'!S17+'Ach prévisionnel'!S30 -> 269264.87 | D38: =+(B38/0.9)*0.025 -> 14235.39 | E38: =+'Cout de production prévisionnel'!M3-'Cout de production prévisionnel'!Q3 -> -1410.7774 | F38: =+(B38-(C38+D38+E38)) -> 230384.56 | G38: =+F38/B38 -> 0.44955361
A39: PF Cacahuète | B39: =+'Chiffre d''affaire'!P4 -> 717463.66 | C39: =+('Ach prévisionnel'!S4+'Ach prévisionnel'!P4-'Ach prévisionnel'!U4)+'Ach prévisionnel'!S18+'Ach prévisionnel'!S31 -> 402096.67 | D39: =+(B39/0.9)*0.025 -> 19929.546 | E39: =+'Cout de production prévisionnel'!M4-'Cout de production prévisionnel'!Q4 -> -1991.2938 | F39: =+(B39-(C39+D39+E39)) -> 297428.73 | G39: =+F39/B39 -> 0.41455581
A40: PF Pois chiche | B40: =+'Chiffre d''affaire'!P5 -> 614968.85 | C40: =+('Ach prévisionnel'!S5+'Ach prévisionnel'!P5-'Ach prévisionnel'!U5)+'Ach prévisionnel'!S19+'Ach prévisionnel'!S32 -> 327017.83 | D40: =+(B40/0.9)*0.025 -> 17082.468 | E40: =+'Cout de production prévisionnel'!M5-'Cout de production prévisionnel'!Q5 -> -1664.7384 | F40: =+(B40-(C40+D40+E40)) -> 272533.29 | G40: =+F40/B40 -> 0.44316601
A41: PF noisette | B41: =+'Chiffre d''affaire'!P6 -> 201211.76 | C41: =+('Ach prévisionnel'!S6+'Ach prévisionnel'!P6-'Ach prévisionnel'!U6)+'Ach prévisionnel'!S20+'Ach prévisionnel'!S33 -> 167554.37 | D41: =+(B41/0.9)*0.025 -> 5589.2156 | E41: =+'Cout de production prévisionnel'!M6-'Cout de production prévisionnel'!Q6 -> -750.54021 | F41: =+(B41-(C41+D41+E41)) -> 28818.713 | G41: =+F41/B41 -> 0.14322579
A42: PF pistche | B42: =+'Chiffre d''affaire'!P7 -> 201211.76 | C42: =+('Ach prévisionnel'!S7+'Ach prévisionnel'!P7-'Ach prévisionnel'!U7)+'Ach prévisionnel'!S21+'Ach prévisionnel'!S34 -> 167554.37 | D42: =+(B42/0.9)*0.025 -> 5589.2156 | E42: =+'Cout de production prévisionnel'!M7-'Cout de production prévisionnel'!Q7 -> -750.54021 | F42: =+(B42-(C42+D42+E42)) -> 28818.713 | G42: =+F42/B42 -> 0.14322579
A43: PF acajou | B43: =+'Chiffre d''affaire'!P8 -> 201211.76 | C43: =+('Ach prévisionnel'!S8+'Ach prévisionnel'!P8-'Ach prévisionnel'!U8)+'Ach prévisionnel'!S22+'Ach prévisionnel'!S35 -> 154596.98 | D43: =+(B43/0.9)*0.025 -> 5589.2156 | E43: =+'Cout de production prévisionnel'!M8-'Cout de production prévisionnel'!Q8 -> -696.24945 | F43: =+(B43-(C43+D43+E43)) -> 41721.816 | G43: =+F43/B43 -> 0.20735277
A44: PF Amande | B44: =+'Chiffre d''affaire'!P9 -> 201211.76 | C44: =+('Ach prévisionnel'!S9+'Ach prévisionnel'!P9-'Ach prévisionnel'!U9)+'Ach prévisionnel'!S23+'Ach prévisionnel'!S36 -> 174033.07 | D44: =+(B44/0.9)*0.025 -> 5589.2156 | E44: =+'Cout de production prévisionnel'!M9-'Cout de production prévisionnel'!Q9 -> -777.68559 | F44: =+(B44-(C44+D44+E44)) -> 22367.161 | G44: =+F44/B44 -> 0.11116229
B46: =SUM(B38:B45) -> 2649753.6 | C46: =SUM(C38:C45) -> 1662118.2 | D46: =SUM(D38:D45) -> 73604.266 | E46: =SUM(E38:E45) -> -8041.8251 | F46: =SUM(F38:F45) -> 922072.98 | G46: =+F46/B46 -> 0.34798442 | I46: =SUM(C46:E46) -> 1727680.6
A48: 2020
A49: Produits | B49: Chiffre d'affaire | C49: Consommations matière | D49: Consommations Autres approv | E49: Variation St. P finis | F49: Marge Brut | G49: Taux de marge
A50: PF Mais | B50: =+'Chiffre d''affaire'!R3 -> 589345.15 | C50: =+('Ach prévisionnel'!X3+'Ach prévisionnel'!U3-'Ach prévisionnel'!Z3)+'Ach prévisionnel'!X17+'Ach prévisionnel'!X30 -> 309654.6 | D50: =+(B50/0.9)*0.025 -> 16370.698 | E50: =+'Cout de production prévisionnel'!Q3-'Cout de production prévisionnel'!U3 -> -1622.394 | F50: =+(B50-(C50+D50+E50)) -> 264942.24 | G50: =+F50/B50 -> 0.44955361
A51: PF Cacahuète | B51: =+'Chiffre d''affaire'!R4 -> 825083.2 | C51: =+('Ach prévisionnel'!X4+'Ach prévisionnel'!U4-'Ach prévisionnel'!Z4)+'Ach prévisionnel'!X18+'Ach prévisionnel'!X31 -> 462411.17 | D51: =+(B51/0.9)*0.025 -> 22918.978 | E51: =+'Cout de production prévisionnel'!Q4-'Cout de production prévisionnel'!U4 -> -2289.9879 | F51: =+(B51-(C51+D51+E51)) -> 342043.04 | G51: =+F51/B51 -> 0.41455581
A52: PF Pois chiche | B52: =+'Chiffre d''affaire'!R5 -> 707214.18 | C52: =+('Ach prévisionnel'!X5+'Ach prévisionnel'!U5-'Ach prévisionnel'!Z5)+'Ach prévisionnel'!X19+'Ach prévisionnel'!X32 -> 376070.5 | D52: =+(B52/0.9)*0.025 -> 19644.838 | E52: =+'Cout de production prévisionnel'!Q5-'Cout de production prévisionnel'!U5 -> -1914.4491 | F52: =+(B52-(C52+D52+E52)) -> 313413.28 | G52: =+F52/B52 -> 0.44316601
A53: PF noisette | B53: =+'Chiffre d''affaire'!R6 -> 231393.53 | C53: =+('Ach prévisionnel'!X6+'Ach prévisionnel'!U6-'Ach prévisionnel'!Z6)+'Ach prévisionnel'!X20+'Ach prévisionnel'!X33 -> 192687.53 | D53: =+(B53/0.9)*0.025 -> 6427.598 | E53: =+'Cout de production prévisionnel'!Q6-'Cout de production prévisionnel'!U6 -> -863.12124 | F53: =+(B53-(C53+D53+E53)) -> 33141.52 | G53: =+F53/B53 -> 0.14322579
A54: PF pistche | B54: =+'Chiffre d''affaire'!R7 -> 231393.53 | C54: =+('Ach prévisionnel'!X7+'Ach prévisionnel'!U7-'Ach prévisionnel'!Z7)+'Ach prévisionnel'!X21+'Ach prévisionnel'!X34 -> 192687.53 | D54: =+(B54/0.9)*0.025 -> 6427.598 | E54: =+'Cout de production prévisionnel'!Q7-'Cout de production prévisionnel'!U7 -> -863.12124 | F54: =+(B54-(C54+D54+E54)) -> 33141.52 | G54: =+F54/B54 -> 0.14322579
A55: PF acajou | B55: =+'Chiffre d''affaire'!R8 -> 231393.53 | C55: =+('Ach prévisionnel'!X8+'Ach prévisionnel'!U8-'Ach prévisionnel'!Z8)+'Ach prévisionnel'!X22+'Ach prévisionnel'!X35 -> 177786.53 | D55: =+(B55/0.9)*0.025 -> 6427.598 | E55: =+'Cout de production prévisionnel'!Q8-'Cout de production prévisionnel'!U8 -> -800.68687 | F55: =+(B55-(C55+D55+E55)) -> 47980.089 | G55: =+F55/B55 -> 0.20735277
A56: PF Amande | B56: =+'Chiffre d''affaire'!R9 -> 231393.53 | C56: =+('Ach prévisionnel'!X9+'Ach prévisionnel'!U9-'Ach prévisionnel'!Z9)+'Ach prévisionnel'!X23+'Ach prévisionnel'!X36 -> 200138.03 | D56: =+(B56/0.9)*0.025 -> 6427.598 | E56: =+'Cout de production prévisionnel'!Q9-'Cout de production prévisionnel'!U9 -> -894.33842 | F56: =+(B56-(C56+D56+E56)) -> 25722.235 | G56: =+F56/B56 -> 0.11116229
B58: =SUM(B50:B57) -> 3047216.6 | C58: =SUM(C50:C57) -> 1911435.9 | D58: =SUM(D50:D57) -> 84644.906 | E58: =SUM(E50:E57) -> -9248.0989 | F58: =SUM(F50:F57) -> 1060383.9 | G58: =+F58/B58 -> 0.34798442 | I58: =SUM(C58:E58) -> 1986832.7
A61: 2021
A62: Produits | B62: Chiffre d'affaire | C62: Consommations matière | D62: Consommations Autres approv | E62: Variation St. P finis | F62: Marge Brut | G62: Taux de marge
A63: PF Mais | B63: =+'Chiffre d''affaire'!T3 -> 589345.15 | C63: =+('Ach prévisionnel'!AC3+'Ach prévisionnel'!Z3-'Ach prévisionnel'!AE3)+'Ach prévisionnel'!AC17+'Ach prévisionnel'!AC30 -> 308357.17 | D63: =+(B63/0.9)*0.025 -> 16370.698 | E63: =+'Cout de production prévisionnel'!U3-'Cout de production prévisionnel'!Y3 -> 0 | F63: =+(B63-(C63+D63+E63)) -> 264617.28 | G63: =+F63/B63 -> 0.44900222
A64: PF Cacahuète | B64: =+'Chiffre d''affaire'!T4 -> 825083.2 | C64: =+('Ach prévisionnel'!AC4+'Ach prévisionnel'!Z4-'Ach prévisionnel'!AE4)+'Ach prévisionnel'!AC18+'Ach prévisionnel'!AC31 -> 460473.7 | D64: =+(B64/0.9)*0.025 -> 22918.978 | E64: =+'Cout de production prévisionnel'!U4-'Cout de production prévisionnel'!Y4 -> 0 | F64: =+(B64-(C64+D64+E64)) -> 341690.53 | G64: =+F64/B64 -> 0.41412857
A65: PF Pois chiche | B65: =+'Chiffre d''affaire'!T5 -> 707214.18 | C65: =+('Ach prévisionnel'!AC5+'Ach prévisionnel'!Z5-'Ach prévisionnel'!AE5)+'Ach prévisionnel'!AC19+'Ach prévisionnel'!AC32 -> 374494.79 | D65: =+(B65/0.9)*0.025 -> 19644.838 | E65: =+'Cout de production prévisionnel'!U5-'Cout de production prévisionnel'!Y5 -> 0 | F65: =+(B65-(C65+D65+E65)) -> 313074.55 | G65: =+F65/B65 -> 0.44268704
A66: PF noisette | B66: =+'Chiffre d''affaire'!T6 -> 231393.53 | C66: =+('Ach prévisionnel'!AC6+'Ach prévisionnel'!Z6-'Ach prévisionnel'!AE6)+'Ach prévisionnel'!AC20+'Ach prévisionnel'!AC33 -> 191880.18 | D66: =+(B66/0.9)*0.025 -> 6427.598 | E66: =+'Cout de production prévisionnel'!U6-'Cout de production prévisionnel'!Y6 -> 0 | F66: =+(B66-(C66+D66+E66)) -> 33085.748 | G66: =+F66/B66 -> 0.14298476
A67: PF pistche | B67: =+'Chiffre d''affaire'!T7 -> 231393.53 | C67: =+('Ach prévisionnel'!AC7+'Ach prévisionnel'!Z7-'Ach prévisionnel'!AE7)+'Ach prévisionnel'!AC21+'Ach prévisionnel'!AC34 -> 191880.18 | D67: =+(B67/0.9)*0.025 -> 6427.598 | E67: =+'Cout de production prévisionnel'!U7-'Cout de production prévisionnel'!Y7 -> 0 | F67: =+(B67-(C67+D67+E67)) -> 33085.748 | G67: =+F67/B67 -> 0.14298476
A68: PF acajou | B68: =+'Chiffre d''affaire'!T8 -> 231393.53 | C68: =+('Ach prévisionnel'!AC8+'Ach prévisionnel'!Z8-'Ach prévisionnel'!AE8)+'Ach prévisionnel'!AC22+'Ach prévisionnel'!AC35 -> 177041.61 | D68: =+(B68/0.9)*0.025 -> 6427.598 | E68: =+'Cout de production prévisionnel'!U8-'Cout de production prévisionnel'!Y8 -> 0 | F68: =+(B68-(C68+D68+E68)) -> 47924.317 | G68: =+F68/B68 -> 0.20711175
A69: PF Amande | B69: =+'Chiffre d''affaire'!T9 -> 231393.53 | C69: =+('Ach prévisionnel'!AC9+'Ach prévisionnel'!Z9-'Ach prévisionnel'!AE9)+'Ach prévisionnel'!AC23+'Ach prévisionnel'!AC36 -> 199299.47 | D69: =+(B69/0.9)*0.025 -> 6427.598 | E69: =+'Cout de production prévisionnel'!U9-'Cout de production prévisionnel'!Y9 -> 0 | F69: =+(B69-(C69+D69+E69)) -> 25666.464 | G69: =+F69/B69 -> 0.11092127
B71: =SUM(B63:B70) -> 3047216.6 | C71: =SUM(C63:C70) -> 1903427.1 | D71: =SUM(D63:D70) -> 84644.906 | E71: =SUM(E63:E70) -> 0 | F71: =SUM(F63:F70) -> 1059144.6 | G71: =+F71/B71 -> 0.34757773 | I71: =SUM(C71:E71) -> 1988072
A74: 2022
A75: Produits | B75: Chiffre d'affaire | C75: Consommations matière | D75: Consommations Autres approv | E75: Variation St. P finis | F75: Marge Brut | G75: Taux de marge
A76: PF Mais | B76: =+'Chiffre d''affaire'!V3 -> 589345.15 | C76: =+('Ach prévisionnel'!AH3+'Ach prévisionnel'!AE3-'Ach prévisionnel'!AJ3)+'Ach prévisionnel'!AH17+'Ach prévisionnel'!AH30 -> 308357.17 | D76: =+(B76/0.9)*0.025 -> 16370.698 | E76: =+'Cout de production prévisionnel'!Q28-'Cout de production prévisionnel'!U28 -> 0 | F76: =+(B76-(C76+D76+E76)) -> 264617.28 | G76: =+F76/B76 -> 0.44900222
A77: PF Cacahuète | B77: =+'Chiffre d''affaire'!V4 -> 825083.2 | C77: =+('Ach prévisionnel'!AH4+'Ach prévisionnel'!AE4-'Ach prévisionnel'!AJ4)+'Ach prévisionnel'!AH18+'Ach prévisionnel'!AH31 -> 460473.7 | D77: =+(B77/0.9)*0.025 -> 22918.978 | E77: =+'Cout de production prévisionnel'!Q29-'Cout de production prévisionnel'!U29 -> 0 | F77: =+(B77-(C77+D77+E77)) -> 341690.53 | G77: =+F77/B77 -> 0.41412857
A78: PF Pois chiche | B78: =+'Chiffre d''affaire'!V5 -> 707214.18 | C78: =+('Ach prévisionnel'!AH5+'Ach prévisionnel'!AE5-'Ach prévisionnel'!AJ5)+'Ach prévisionnel'!AH19+'Ach prévisionnel'!AH32 -> 374494.79 | D78: =+(B78/0.9)*0.025 -> 19644.838 | E78: =+'Cout de production prévisionnel'!Q30-'Cout de production prévisionnel'!U30 -> 0 | F78: =+(B78-(C78+D78+E78)) -> 313074.55 | G78: =+F78/B78 -> 0.44268704
A79: PF noisette | B79: =+'Chiffre d''affaire'!V6 -> 231393.53 | C79: =+('Ach prévisionnel'!AH6+'Ach prévisionnel'!AE6-'Ach prévisionnel'!AJ6)+'Ach prévisionnel'!AH20+'Ach prévisionnel'!AH33 -> 191880.18 | D79: =+(B79/0.9)*0.025 -> 6427.598 | E79: =+'Cout de production prévisionnel'!Q31-'Cout de production prévisionnel'!U31 -> 0 | F79: =+(B79-(C79+D79+E79)) -> 33085.748 | G79: =+F79/B79 -> 0.14298476
A80: PF pistche | B80: =+'Chiffre d''affaire'!V7 -> 231393.53 | C80: =+('Ach prévisionnel'!AH7+'Ach prévisionnel'!AE7-'Ach prévisionnel'!AJ7)+'Ach prévisionnel'!AH21+'Ach prévisionnel'!AH34 -> 191880.18 | D80: =+(B80/0.9)*0.025 -> 6427.598 | E80: =+'Cout de production prévisionnel'!Q32-'Cout de production prévisionnel'!U32 -> 0 | F80: =+(B80-(C80+D80+E80)) -> 33085.748 | G80: =+F80/B80 -> 0.14298476
A81: PF acajou | B81: =+'Chiffre d''affaire'!V8 -> 231393.53 | C81: =+('Ach prévisionnel'!AH8+'Ach prévisionnel'!AE8-'Ach prévisionnel'!AJ8)+'Ach prévisionnel'!AH22+'Ach prévisionnel'!AH35 -> 177041.61 | D81: =+(B81/0.9)*0.025 -> 6427.598 | E81: =+'Cout de production prévisionnel'!Q33-'Cout de production prévisionnel'!U33 -> 0 | F81: =+(B81-(C81+D81+E81)) -> 47924.317 | G81: =+F81/B81 -> 0.20711175
A82: PF Amande | B82: =+'Chiffre d''affaire'!V9 -> 231393.53 | C82: =+('Ach prévisionnel'!AH9+'Ach prévisionnel'!AE9-'Ach prévisionnel'!AJ9)+'Ach prévisionnel'!AH23+'Ach prévisionnel'!AH36 -> 199299.47 | D82: =+(B82/0.9)*0.025 -> 6427.598 | E82: =+'Cout de production prévisionnel'!Q34-'Cout de production prévisionnel'!U34 -> 0 | F82: =+(B82-(C82+D82+E82)) -> 25666.464 | G82: =+F82/B82 -> 0.11092127
B84: =SUM(B76:B83) -> 3047216.6 | C84: =SUM(C76:C83) -> 1903427.1 | D84: =SUM(D76:D83) -> 84644.906 | F84: =SUM(F76:F83) -> 1059144.6 | G84: =+F84/B84 -> 0.34757773 | I84: =SUM(C84:E84) -> 1988072

Sheet Consommations Q
A2: Matière premières | B2: 2016 | G2: 2017 | L2: 2018 | Q2: 2019 | V2: 2020 | AA2: 2021 | AF2: 2022
B3: Qt Vendu | C3: Qt produite | D3: Qt Consommées | E3: Qt achétées | F3: Qt SF | G3: Qt Vendu | H3: Qt produite | I3: Qt Consommées | J3: Qt achétée | K3: Qt SF | L3: Qt Vendu | M3: Qt produite | N3: Qt Consommées | O3: Qt achétée | P3: Qt SF | Q3: Qt Vendu | R3: Qt produite | S3: Qt Consommées | T3: Qt achétée | U3: Qt SF | V3: Qt Vendu | W3: Qt produite | X3: Qt Consommées | Y3: Qt achétée | Z3: Qt SF | AA3: Qt Vendu | AB3: Qt produite | AC3: Qt Consommées | AD3: Qt achétée | AE3: Qt SF | AF3: Qt Vendu | AG3: Qt produite | AH3: Qt Consommées | AI3: Qt achétée | AJ3: Qt SF
A4: MP MAIS | B4: =+'Chiffre d''affaire'!F3 -> 37440 | C4: =+B4+'Cout de production prévisionnel'!D3 -> 38647.742 | D4: =+C4*1.01 -> 39034.219 | E4: =+D4*13/12 -> 42287.071 | F4: =+E4/13 -> 3252.8516 | G4: =+B4*1.15 -> 43056 | H4: =+G4+'Cout de production prévisionnel'!H3-'Cout de production prévisionnel'!D3 -> 43237.161 | I4: =+H4*1.01 -> 43669.533 | J4: =+(I4-F4)*13/12 -> 43784.738 | K4: =+J4/13 -> 3368.0568 | L4: =+G4*1.15 -> 49514.4 | M4: =+L4+'Cout de production prévisionnel'!L3-'Cout de production prévisionnel'!H3 -> 49722.735 | N4: =+M4*1.01 -> 50219.963 | O4: =+(N4-K4)*13/12 -> 50756.232 | P4: =+O4/13 -> 3904.3255 | Q4: =+L4*1.15 -> 56941.56 | R4: =+Q4+'Cout de production prévisionnel'!P3-'Cout de production prévisionnel'!L3 -> 57181.146 | S4: =+R4*1.01 -> 57752.957 | T4: =+(S4-P4)*13/12 -> 58336.018 | U4: =+T4/13 -> 4487.386 | V4: =+Q4*1.15 -> 65482.794 | W4: =+V4+'Cout de production prévisionnel'!T3-'Cout de production prévisionnel'!P3 -> 65758.318 | X4: =+W4*1.01 -> 66415.901 | Y4: =+(X4-U4)*13/12 -> 67089.224 | Z4: =+Y4/13 -> 5160.7096 | AA4: =+V4 -> 65482.794 | AB4: =+AA4+'Cout de production prévisionnel'!X3-'Cout de production prévisionnel'!T3 -> 65482.794 | AC4: =+AB4*1.01 -> 66137.622 | AD4: =+(AC4-Z4)*13/12 -> 66058.322 | AE4: =+AD4/13 -> 5081.4094 | AF4: =+AA4 -> 65482.794 | AG4: =+AF4+'Cout de production prévisionnel'!AB3-'Cout de production prévisionnel'!X3 -> 65482.794 | AH4: =+AG4*1.01 -> 66137.622 | AI4: =+(AH4-AE4)*13/12 -> 66144.23 | AJ4: =+AI4/13 -> 5088.0177
A5: MP Cacahuète | B5: =+'Chiffre d''affaire'!F4 -> 37440 | C5: =+B5+'Cout de production prévisionnel'!D4 -> 38647.742 | D5: =+C5*1.01 -> 39034.219 | E5: =+D5*13/12 -> 42287.071 | F5: =+E5/13 -> 3252.8516 | G5: =+B5*1.15 -> 43056 | H5: =+G5+'Cout de production prévisionnel'!H4-'Cout de production prévisionnel'!D4 -> 43237.161 | I5: =+H5*1.01 -> 43669.533 | J5: =+(I5-F5)*13/12 -> 43784.738 | K5: =+J5/13 -> 3368.0568 | L5: =+G5*1.15 -> 49514.4 | M5: =+L5+'Cout de production prévisionnel'!L4-'Cout de production prévisionnel'!H4 -> 49722.735 | N5: =+M5*1.01 -> 50219.963 | O5: =+(N5-K5)*13/12 -> 50756.232 | P5: =+O5/13 -> 3904.3255 | Q5: =+L5*1.15 -> 56941.56 | R5: =+Q5+'Cout de production prévisionnel'!P4-'Cout de production prévisionnel'!L4 -> 57181.146 | S5: =+R5*1.01 -> 57752.957 | T5: =+(S5-P5)*13/12 -> 58336.018 | U5: =+T5/13 -> 4487.386 | V5: =+Q5*1.15 -> 65482.794 | W5: =+V5+'Cout de production prévisionnel'!T4-'Cout de production prévisionnel'!P4 -> 65758.318 | X5: =+W5*1.01 -> 66415.901 | Y5: =+(X5-U5)*13/12 -> 67089.224 | Z5: =+Y5/13 -> 5160.7096 | AA5: =+V5 -> 65482.794 | AB5: =+AA5+'Cout de production prévisionnel'!X4-'Cout de production prévisionnel'!T4 -> 65482.794 | AC5: =+AB5*1.01 -> 66137.622 | AD5: =+(AC5-Z5)*13/12 -> 66058.322 | AE5: =+AD5/13 -> 5081.4094 | AF5: =+AA5 -> 65482.794 | AG5: =+AF5+'Cout de production prévisionnel'!AB4-'Cout de production prévisionnel'!X4 -> 65482.794 | AH5: =+AG5*1.01 -> 66137.622 | AI5: =+(AH5-AE5)*13/12 -> 66144.23 | AJ5: =+AI5/13 -> 5088.0177
A6: Pois chiche | B6: =+'Chiffre d''affaire'!F5 -> 37440 | C6: =+B6+'Cout de production prévisionnel'!D5 -> 38647.742 | D6: =+C6*1.01 -> 39034.219 | E6: =+D6*13/12 -> 42287.071 | F6: =+E6/13 -> 3252.8516 | G6: =+B6*1.15 -> 43056 | H6: =+G6+'Cout de production prévisionnel'!H5-'Cout de production prévisionnel'!D5 -> 43237.161 | I6: =+H6*1.01 -> 43669.533 | J6: =+(I6-F6)*13/12 -> 43784.738 | K6: =+J6/13 -> 3368.0568 | L6: =+G6*1.15 -> 49514.4 | M6: =+L6+'Cout de production prévisionnel'!L5-'Cout de production prévisionnel'!H5 -> 49722.735 | N6: =+M6*1.01 -> 50219.963 | O6: =+(N6-K6)*13/12 -> 50756.232 | P6: =+O6/13 -> 3904.3255 | Q6: =+L6*1.15 -> 56941.56 | R6: =+Q6+'Cout de production prévisionnel'!P5-'Cout de production prévisionnel'!L5 -> 57181.146 | S6: =+R6*1.01 -> 57752.957 | T6: =+(S6-P6)*13/12 -> 58336.018 | U6: =+T6/13 -> 4487.386 | V6: =+Q6*1.15 -> 65482.794 | W6: =+V6+'Cout de production prévisionnel'!T5-'Cout de production prévisionnel'!P5 -> 65758.318 | X6: =+W6*1.01 -> 66415.901 | Y6: =+(X6-U6)*13/12 -> 67089.224 | Z6: =+Y6/13 -> 5160.7096 | AA6: =+V6 -> 65482.794 | AB6: =+AA6+'Cout de production prévisionnel'!X5-'Cout de production prévisionnel'!T5 -> 65482.794 | AC6: =+AB6*1.01 -> 66137.622 | AD6: =+(AC6-Z6)*13/12 -> 66058.322 | AE6: =+AD6/13 -> 5081.4094 | AF6: =+AA6 -> 65482.794 | AG6: =+AF6+'Cout de production prévisionnel'!AB5-'Cout de production prévisionnel'!X5 -> 65482.794 | AH6: =+AG6*1.01 -> 66137.622 | AI6: =+(AH6-AE6)*13/12 -> 66144.23 | AJ6: =+AI6/13 -> 5088.0177
A7: MP noisette | B7: =+'Chiffre d''affaire'!F6 -> 4200 | C7: =+B7+'Cout de production prévisionnel'!D6 -> 4335.4839 | D7: =+C7*1.01 -> 4378.8387 | E7: =+D7*13/12 -> 4743.7419 | F7: =+E7/13 -> 364.90323 | G7: =+B7*1.15 -> 4830 | H7: =+G7+'Cout de production prévisionnel'!H6-'Cout de production prévisionnel'!D6 -> 4850.3226 | I7: =+H7*1.01 -> 4898.8258 | J7: =+(I7-F7)*13/12 -> 4911.7495 | K7: =+J7/13 -> 377.82688 | L7: =+G7*1.15 -> 5554.5 | M7: =+L7+'Cout de production prévisionnel'!L6-'Cout de production prévisionnel'!H6 -> 5577.871 | N7: =+M7*1.01 -> 5633.6497 | O7: =+(N7-K7)*13/12 -> 5693.808 | P7: =+O7/13 -> 437.98523 | Q7: =+L7*1.15 -> 6387.675 | R7: =+Q7+'Cout de production prévisionnel'!P6-'Cout de production prévisionnel'!L6 -> 6414.5516 | S7: =+R7*1.01 -> 6478.6971 | T7: =+(S7-P7)*13/12 -> 6544.1046 | U7: =+T7/13 -> 503.39266 | V7: =+Q7*1.15 -> 7345.8262 | W7: =+V7+'Cout de production prévisionnel'!T6-'Cout de production prévisionnel'!P6 -> 7376.7344 | X7: =+W7*1.01 -> 7450.5017 | Y7: =+(X7-U7)*13/12 -> 7526.0348 | Z7: =+Y7/13 -> 578.92575 | AA7: =+V7 -> 7345.8262 | AB7: =+AA7+'Cout de production prévisionnel'!X6-'Cout de production prévisionnel'!T6 -> 7345.8262 | AC7: =+AB7*1.01 -> 7419.2845 | AD7: =+(AC7-Z7)*13/12 -> 7410.3887 | AE7: =+AD7/13 -> 570.0299 | AF7: =+AA7 -> 7345.8262 | AG7: =+AF7+'Cout de production prévisionnel'!AB6-'Cout de production prévisionnel'!X6 -> 7345.8262 | AH7: =+AG7*1.01 -> 7419.2845 | AI7: =+(AH7-AE7)*13/12 -> 7420.0258 | AJ7: =+AI7/13 -> 570.77122
A8: MP pistche | B8: =+'Chiffre d''affaire'!F7 -> 4200 | C8: =+B8+'Cout de production prévisionnel'!D7 -> 4335.4839 | D8: =+C8*1.01 -> 4378.8387 | E8: =+D8*13/12 -> 4743.7419 | F8: =+E8/13 -> 364.90323 | G8: =+B8*1.15 -> 4830 | H8: =+G8+'Cout de production prévisionnel'!H7-'Cout de production prévisionnel'!D7 -> 4850.3226 | I8: =+H8*1.01 -> 4898.8258 | J8: =+(I8-F8)*13/12 -> 4911.7495 | K8: =+J8/13 -> 377.82688 | L8: =+G8*1.15 -> 5554.5 | M8: =+L8+'Cout de production prévisionnel'!L7-'Cout de production prévisionnel'!H7 -> 5577.871 | N8: =+M8*1.01 -> 5633.6497 | O8: =+(N8-K8)*13/12 -> 5693.808 | P8: =+O8/13 -> 437.98523 | Q8: =+L8*1.15 -> 6387.675 | R8: =+Q8+'Cout de production prévisionnel'!P7-'Cout de production prévisionnel'!L7 -> 6414.5516 | S8: =+R8*1.01 -> 6478.6971 | T8: =+(S8-P8)*13/12 -> 6544.1046 | U8: =+T8/13 -> 503.39266 | V8: =+Q8*1.15 -> 7345.8262 | W8: =+V8+'Cout de production prévisionnel'!T7-'Cout de production prévisionnel'!P7 -> 7376.7344 | X8: =+W8*1.01 -> 7450.5017 | Y8: =+(X8-U8)*13/12 -> 7526.0348 | Z8: =+Y8/13 -> 578.92575 | AA8: =+V8 -> 7345.8262 | AB8: =+AA8+'Cout de production prévisionnel'!X7-'Cout de production prévisionnel'!T7 -> 7345.8262 | AC8: =+AB8*1.01 -> 7419.2845 | AD8: =+(AC8-Z8)*13/12 -> 7410.3887 | AE8: =+AD8/13 -> 570.0299 | AF8: =+AA8 -> 7345.8262 | AG8: =+AF8+'Cout de production prévisionnel'!AB7-'Cout de production prévisionnel'!X7 -> 7345.8262 | AH8: =+AG8*1.01 -> 7419.2845 | AI8: =+(AH8-AE8)*13/12 -> 7420.0258 | AJ8: =+AI8/13 -> 570.77122
A9: MP acajou | B9: =+'Chiffre d''affaire'!F8 -> 4200 | C9: =+B9+'Cout de production prévisionnel'!D8 -> 4335.4839 | D9: =+C9*1.01 -> 4378.8387 | E9: =+D9*13/12 -> 4743.7419 | F9: =+E9/13 -> 364.90323 | G9: =+B9*1.15 -> 4830 | H9: =+G9+'Cout de production prévisionnel'!H8-'Cout de production prévisionnel'!D8 -> 4850.3226 | I9: =+H9*1.01 -> 4898.8258 | J9: =+(I9-F9)*13/12 -> 4911.7495 | K9: =+J9/13 -> 377.82688 | L9: =+G9*1.15 -> 5554.5 | M9: =+L9+'Cout de production prévisionnel'!L8-'Cout de production prévisionnel'!H8 -> 5577.871 | N9: =+M9*1.01 -> 5633.6497 | O9: =+(N9-K9)*13/12 -> 5693.808 | P9: =+O9/13 -> 437.98523 | Q9: =+L9*1.15 -> 6387.675 | R9: =+Q9+'Cout de production prévisionnel'!P8-'Cout de production prévisionnel'!L8 -> 6414.5516 | S9: =+R9*1.01 -> 6478.6971 | T9: =+(S9-P9)*13/12 -> 6544.1046 | U9: =+T9/13 -> 503.39266 | V9: =+Q9*1.15 -> 7345.8262 | W9: =+V9+'Cout de production prévisionnel'!T8-'Cout de production prévisionnel'!P8 -> 7376.7344 | X9: =+W9*1.01 -> 7450.5017 | Y9: =+(X9-U9)*13/12 -> 7526.0348 | Z9: =+Y9/13 -> 578.92575 | AA9: =+V9 -> 7345.8262 | AB9: =+AA9+'Cout de production prévisionnel'!X8-'Cout de production prévisionnel'!T8 -> 7345.8262 | AC9: =+AB9*1.01 -> 7419.2845 | AD9: =+(AC9-Z9)*13/12 -> 7410.3887 | AE9: =+AD9/13 -> 570.0299 | AF9: =+AA9 -> 7345.8262 | AG9: =+AF9+'Cout de production prévisionnel'!AB8-'Cout de production prévisionnel'!X8 -> 7345.8262 | AH9: =+AG9*1.01 -> 7419.2845 | AI9: =+(AH9-AE9)*13/12 -> 7420.0258 | AJ9: =+AI9/13 -> 570.77122
A10: MP Amande | B10: =+'Chiffre d''affaire'!F9 -> 4200 | C10: =+B10+'Cout de production prévisionnel'!D9 -> 4335.4839 | D10: =+C10*1.01 -> 4378.8387 | E10: =+D10*13/12 -> 4743.7419 | F10: =+E10/13 -> 364.90323 | G10: =+B10*1.15 -> 4830 | H10: =+G10+'Cout de production prévisionnel'!H9-'Cout de production prévisionnel'!D9 -> 4850.3226 | I10: =+H10*1.01 -> 4898.8258 | J10: =+(I10-F10)*13/12 -> 4911.7495 | K10: =+J10/13 -> 377.82688 | L10: =+G10*1.15 -> 5554.5 | M10: =+L10+'Cout de production prévisionnel'!L9-'Cout de production prévisionnel'!H9 -> 5577.871 | N10: =+M10*1.01 -> 5633.6497 | O10: =+(N10-K10)*13/12 -> 5693.808 | P10: =+O10/13 -> 437.98523 | Q10: =+L10*1.15 -> 6387.675 | R10: =+Q10+'Cout de production prévisionnel'!P9-'Cout de production prévisionnel'!L9 -> 6414.5516 | S10: =+R10*1.01 -> 6478.6971 | T10: =+(S10-P10)*13/12 -> 6544.1046 | U10: =+T10/13 -> 503.39266 | V10: =+Q10*1.15 -> 7345.8262 | W10: =+V10+'Cout de production prévisionnel'!T9-'Cout de production prévisionnel'!P9 -> 7376.7344 | X10: =+W10*1.01 -> 7450.5017 | Y10: =+(X10-U10)*13/12 -> 7526.0348 | Z10: =+Y10/13 -> 578.92575 | AA10: =+V10 -> 7345.8262 | AB10: =+AA10+'Cout de production prévisionnel'!X9-'Cout de production prévisionnel'!T9 -> 7345.8262 | AC10: =+AB10*1.01 -> 7419.2845 | AD10: =+(AC10-Z10)*13/12 -> 7410.3887 | AE10: =+AD10/13 -> 570.0299 | AF10: =+AA10 -> 7345.8262 | AG10: =+AF10+'Cout de production prévisionnel'!AB9-'Cout de production prévisionnel'!X9 -> 7345.8262 | AH10: =+AG10*1.01 -> 7419.2845 | AI10: =+(AH10-AE10)*13/12 -> 7420.0258 | AJ10: =+AI10/13 -> 570.77122
B11: =SUM(B4:B10) -> 129120 | C11: =SUM(C4:C10) -> 133285.16 | D11: =SUM(D4:D10) -> 134618.01 | E11: =SUM(E4:E10) -> 145836.18 | F11: =SUM(F4:F10) -> 11218.168 | G11: =SUM(G4:G10) -> 148488 | H11: =SUM(H4:H10) -> 149112.77 | I11: =SUM(I4:I10) -> 150603.9 | ... AJ11: =SUM(AJ4:AJ10) -> 17547.138
G12: =+H11+'Cout de production prévisionnel'!D10-'Cout de production prévisionnel'!H10 -> 148488
A13: Check St. F | F13: =+E11-D11-F11 -> 1.6370905e-11 | K13: =+J11-I11+F11-K11 -> -5.0931703e-11 | P13: =+O11-N11+K11-P11 -> -3.2741809e-11 | U13: =+T11-S11+P11-U11 -> 0 | Z13: =+Y11-X11+U11-Z11 -> 0 | AE13: =+AD11-AC11+Z11-AE11 -> 0 | AJ13: =+AI11-AH11+AE11-AJ11 -> 9.8225428e-11
A14: Check augmentation consommation | I14: =+(I11-D11)/D11 -> 0.11875 | N14: =+(N11-I11)/I11 -> 0.15 | S14: =+(S11-N11)/N11 -> 0.15 | X14: =+(X11-S11)/S11 -> 0.15 | AC14: =+(AC11-X11)/X11 -> -0.0041899441 | AH14: =+(AH11-AC11)/AC11 -> 0
A15: Check augmentation Qt vendues | G15: =+(G11-B11)/B11 -> 0.15 | L15: =+(L11-G11)/G11 -> 0.15 | Q15: =+(Q11-L11)/L11 -> 0.15 | V15: =+(V11-Q11)/Q11 -> 0.15
A17: Achat aromes | B17: 2016 | E17: 2017 | H17: 2018 | K17: 2019 | N17: 2020 | Q17: 2021 | T17: 2022
B18: Qt Consommées | C18: Qt achétées | D18: Qt SF | E18: Qt Consommées | F18: Qt achétées | G18: Qt SF | H18: Qt Consommées | I18: Qt achétées | J18: Qt SF | K18: Qt Consommées | L18: Qt achétées | M18: Qt SF | N18: Qt Consommées | O18: Qt achétées | P18: Qt SF | Q18: Qt Consommées | R18: Qt achétées | S18: Qt SF | T18: Qt Consommées | U18: Qt achétées | V18: Qt SF
A19: MAIS | B19: =+C4*0.06 -> 2318.8645 | C19: =+B19*13/12 -> 2512.1032 | D19: =+C19/13 -> 193.23871 | E19: =+H4*0.06 -> 2594.2297 | F19: =+(E19-D19)*13/12 -> 2601.0735 | G19: =+F19/13 -> 200.08258 | H19: =+M4*0.06 -> 2983.3641 | I19: =+(H19-G19)*13/12 -> 3015.2217 | J19: =+I19/13 -> 231.94013 | K19: =+R4*0.06 -> 3430.8687 | L19: =+(K19-J19)*13/12 -> 3465.506 | M19: =+L19/13 -> 266.57738 | N19: =+W4*0.06 -> 3945.4991 | O19: =+(N19-M19)*13/12 -> 3985.4985 | P19: =+O19/13 -> 306.57681 | Q19: =+AB4*0.06 -> 3928.9676 | R19: =+(Q19-P19)*13/12 -> 3924.2567 | S19: =+R19/13 -> 301.8659 | T19: =+AG4*0.06 -> 3928.9676 | U19: =+(T19-S19)*13/12 -> 3929.3602 | V19: =+U19/13 -> 302.25848
A20: Cacahuète | B20: =+C5*0.06 -> 2318.8645 | C20: =+B20*13/12 -> 2512.1032 | D20: =+C20/13 -> 193.23871 | E20: =+H5*0.06 -> 2594.2297 | F20: =+(E20-D20)*13/12 -> 2601.0735 | G20: =+F20/13 -> 200.08258 | H20: =+M5*0.06 -> 2983.3641 | I20: =+(H20-G20)*13/12 -> 3015.2217 | J20: =+I20/13 -> 231.94013 | K20: =+R5*0.06 -> 3430.8687 | L20: =+(K20-J20)*13/12 -> 3465.506 | M20: =+L20/13 -> 266.57738 | N20: =+W5*0.06 -> 3945.4991 | O20: =+(N20-M20)*13/12 -> 3985.4985 | P20: =+O20/13 -> 306.57681 | Q20: =+AB5*0.06 -> 3928.9676 | R20: =+(Q20-P20)*13/12 -> 3924.2567 | S20: =+R20/13 -> 301.8659 | T20: =+AG5*0.06 -> 3928.9676 | U20: =+(T20-S20)*13/12 -> 3929.3602 | V20: =+U20/13 -> 302.25848
A21: Pois chiche | B21: =+C6*0.06 -> 2318.8645 | C21: =+B21*13/12 -> 2512.1032 | D21: =+C21/13 -> 193.23871 | E21: =+H6*0.06 -> 2594.2297 | F21: =+(E21-D21)*13/12 -> 2601.0735 | G21: =+F21/13 -> 200.08258 | H21: =+M6*0.06 -> 2983.3641 | I21: =+(H21-G21)*13/12 -> 3015.2217 | J21: =+I21/13 -> 231.94013 | K21: =+R6*0.06 -> 3430.8687 | L21: =+(K21-J21)*13/12 -> 3465.506 | M21: =+L21/13 -> 266.57738 | N21: =+W6*0.06 -> 3945.4991 | O21: =+(N21-M21)*13/12 -> 3985.4985 | P21: =+O21/13 -> 306.57681 | Q21: =+AB6*0.06 -> 3928.9676 | R21: =+(Q21-P21)*13/12 -> 3924.2567 | S21: =+R21/13 -> 301.8659 | T21: =+AG6*0.06 -> 3928.9676 | U21: =+(T21-S21)*13/12 -> 3929.3602 | V21: =+U21/13 -> 302.25848
A22: noisette | B22: =+C7*0.06 -> 260.12903 | C22: =+B22*13/12 -> 281.80645 | D22: =+C22/13 -> 21.677419 | E22: =+H7*0.06 -> 291.01935 | F22: =+(E22-D22)*13/12 -> 291.7871 | G22: =+F22/13 -> 22.445161 | H22: =+M7*0.06 -> 334.67226 | I22: =+(H22-G22)*13/12 -> 338.24602 | J22: =+I22/13 -> 26.018925 | K22: =+R7*0.06 -> 384.8731 | L22: =+(K22-J22)*13/12 -> 388.75869 | M22: =+L22/13 -> 29.904514 | N22: =+W7*0.06 -> 442.60406 | O22: =+(N22-M22)*13/12 -> 447.09118 | P22: =+O22/13 -> 34.391629 | Q22: =+AB7*0.06 -> 440.74957 | R22: =+(Q22-P22)*13/12 -> 440.22111 | S22: =+R22/13 -> 33.863162 | T22: =+AG7*0.06 -> 440.74957 | U22: =+(T22-S22)*13/12 -> 440.79361 | V22: =+U22/13 -> 33.907201
A23: pistche | B23: =+C8*0.06 -> 260.12903 | C23: =+B23*13/12 -> 281.80645 | D23: =+C23/13 -> 21.677419 | E23: =+H8*0.06 -> 291.01935 | F23: =+(E23-D23)*13/12 -> 291.7871 | G23: =+F23/13 -> 22.445161 | H23: =+M8*0.06 -> 334.67226 | I23: =+(H23-G23)*13/12 -> 338.24602 | J23: =+I23/13 -> 26.018925 | K23: =+R8*0.06 -> 384.8731 | L23: =+(K23-J23)*13/12 -> 388.75869 | M23: =+L23/13 -> 29.904514 | N23: =+W8*0.06 -> 442.60406 | O23: =+(N23-M23)*13/12 -> 447.09118 | P23: =+O23/13 -> 34.391629 | Q23: =+AB8*0.06 -> 440.74957 | R23: =+(Q23-P23)*13/12 -> 440.22111 | S23: =+R23/13 -> 33.863162 | T23: =+AG8*0.06 -> 440.74957 | U23: =+(T23-S23)*13/12 -> 440.79361 | V23: =+U23/13 -> 33.907201
A24: acajou | B24: =+C9*0.06 -> 260.12903 | C24: =+B24*13/12 -> 281.80645 | D24: =+C24/13 -> 21.677419 | E24: =+H9*0.06 -> 291.01935 | F24: =+(E24-D24)*13/12 -> 291.7871 | G24: =+F24/13 -> 22.445161 | H24: =+M9*0.06 -> 334.67226 | I24: =+(H24-G24)*13/12 -> 338.24602 | J24: =+I24/13 -> 26.018925 | K24: =+R9*0.06 -> 384.8731 | L24: =+(K24-J24)*13/12 -> 388.75869 | M24: =+L24/13 -> 29.904514 | N24: =+W9*0.06 -> 442.60406 | O24: =+(N24-M24)*13/12 -> 447.09118 | P24: =+O24/13 -> 34.391629 | Q24: =+AB9*0.06 -> 440.74957 | R24: =+(Q24-P24)*13/12 -> 440.22111 | S24: =+R24/13 -> 33.863162 | T24: =+AG9*0.06 -> 440.74957 | U24: =+(T24-S24)*13/12 -> 440.79361 | V24: =+U24/13 -> 33.907201
A25: Amande | B25: =+C10*0.06 -> 260.12903 | C25: =+B25*13/12 -> 281.80645 | D25: =+C25/13 -> 21.677419 | E25: =+H10*0.06 -> 291.01935 | F25: =+(E25-D25)*13/12 -> 291.7871 | G25: =+F25/13 -> 22.445161 | H25: =+M10*0.06 -> 334.67226 | I25: =+(H25-G25)*13/12 -> 338.24602 | J25: =+I25/13 -> 26.018925 | K25: =+R10*0.06 -> 384.8731 | L25: =+(K25-J25)*13/12 -> 388.75869 | M25: =+L25/13 -> 29.904514 | N25: =+W10*0.06 -> 442.60406 | O25: =+(N25-M25)*13/12 -> 447.09118 | P25: =+O25/13 -> 34.391629 | Q25: =+AB10*0.06 -> 440.74957 | R25: =+(Q25-P25)*13/12 -> 440.22111 | S25: =+R25/13 -> 33.863162 | T25: =+AG10*0.06 -> 440.74957 | U25: =+(T25-S25)*13/12 -> 440.79361 | V25: =+U25/13 -> 33.907201
A26: Achat d'approvisionnement | B26: =SUM(B19:B25) -> 7997.1097 | C26: =SUM(C19:C25) -> 8663.5355 | D26: =SUM(D19:D25) -> 666.42581 | E26: =SUM(E19:E25) -> 8946.7665 | F26: =SUM(F19:F25) -> 8970.369 | G26: =SUM(G19:G25) -> 690.02839 | H26: =SUM(H19:H25) -> 10288.781 | I26: =SUM(I19:I25) -> 10398.649 | ... V26: =SUM(V19:V25) -> 1042.4042
A28: Check | D28: =+(B26-C26+D26) -> -2.3874236e-12 | E28: =+(E26-B26)/B26 -> 0.11875 | G28: =+(E26-F26+G26)-D26 -> 3.524292e-12 | H28: =+(H26-E26)/E26 -> 0.15 | J28: =+(H26-I26+J26)-G26 -> 2.0463631e-12 | K28: =+(K26-H26)/H26 -> 0.15 | M28: =+(K26-L26+M26)-J26 -> 2.8421709e-12 | N28: =+(N26-K26)/K26 -> 0.15 | P28: =+(N26-O26+P26)-M26 -> -7.6170181e-12 | Q28: =+(Q26-N26)/N26 -> -0.0041899441 | S28: =+(Q26-R26+S26)-P26 -> 1.8189894e-12 | T28: =+(T26-Q26)/Q26 -> 0 | V28: =+(T26-U26+V26)-S26 -> -2.7284841e-12
A30: Achat emballage | B30: 2016 | E30: 2017 | H30: 2018 | K30: 2019 | N30: 2020 | Q30: 2021 | T30: 2022
B31: Qt Consommées | C31: Qt achétées | D31: Qt SF | E31: Qt Consommées | F31: Qt achétées | G31: Qt SF | H31: Qt Consommées | I31: Qt achétées | J31: Qt SF | K31: Qt Consommées | L31: Qt achétées | M31: Qt SF | N31: Qt Consommées | O31: Qt achétées | P31: Qt SF | Q31: Qt Consommées | R31: Qt achétées | S31: Qt SF | T31: Qt Consommées | U31: Qt achétées | V31: Qt SF
A32: MAIS | B32: =+C4*0.05 -> 1932.3871 | C32: =+B32*13/12 -> 2093.4194 | D32: =+C32/13 -> 161.03226 | E32: =+H4*0.05 -> 2161.8581 | F32: =+(E32-D32)*13/12 -> 2167.5613 | G32: =+F32/13 -> 166.73548 | H32: =+M4*0.05 -> 2486.1368 | I32: =+(H32-G32)*13/12 -> 2512.6847 | J32: =+I32/13 -> 193.28344 | K32: =+R4*0.05 -> 2859.0573 | L32: =+(K32-J32)*13/12 -> 2887.9217 | M32: =+L32/13 -> 222.14782 | N32: =+W4*0.05 -> 3287.9159 | O32: =+(N32-M32)*13/12 -> 3321.2487 | P32: =+O32/13 -> 255.48067 | Q32: =+AB4*0.05 -> 3274.1397 | R32: =+(Q32-P32)*13/12 -> 3270.2139 | S32: =+R32/13 -> 251.55492 | T32: =+AG4*0.05 -> 3274.1397 | U32: =+(T32-S32)*13/12 -> 3274.4668 | V32: =+U32/13 -> 251.88207
A33: Cacahuète | B33: =+C5*0.05 -> 1932.3871 | C33: =+B33*13/12 -> 2093.4194 | D33: =+C33/13 -> 161.03226 | E33: =+H5*0.05 -> 2161.8581 | F33: =+(E33-D33)*13/12 -> 2167.5613 | G33: =+F33/13 -> 166.73548 | H33: =+M5*0.05 -> 2486.1368 | I33: =+(H33-G33)*13/12 -> 2512.6847 | J33: =+I33/13 -> 193.28344 | K33: =+R5*0.05 -> 2859.0573 | L33: =+(K33-J33)*13/12 -> 2887.9217 | M33: =+L33/13 -> 222.14782 | N33: =+W5*0.05 -> 3287.9159 | O33: =+(N33-M33)*13/12 -> 3321.2487 | P33: =+O33/13 -> 255.48067 | Q33: =+AB5*0.05 -> 3274.1397 | R33: =+(Q33-P33)*13/12 -> 3270.2139 | S33: =+R33/13 -> 251.55492 | T33: =+AG5*0.05 -> 3274.1397 | U33: =+(T33-S33)*13/12 -> 3274.4668 | V33: =+U33/13 -> 251.88207
A34: Pois chiche | B34: =+C6*0.05 -> 1932.3871 | C34: =+B34*13/12 -> 2093.4194 | D34: =+C34/13 -> 161.03226 | E34: =+H6*0.05 -> 2161.8581 | F34: =+(E34-D34)*13/12 -> 2167.5613 | G34: =+F34/13 -> 166.73548 | H34: =+M6*0.05 -> 2486.1368 | I34: =+(H34-G34)*13/12 -> 2512.6847 | J34: =+I34/13 -> 193.28344 | K34: =+R6*0.05 -> 2859.0573 | L34: =+(K34-J34)*13/12 -> 2887.9217 | M34: =+L34/13 -> 222.14782 | N34: =+W6*0.05 -> 3287.9159 | O34: =+(N34-M34)*13/12 -> 3321.2487 | P34: =+O34/13 -> 255.48067 | Q34: =+AB6*0.05 -> 3274.1397 | R34: =+(Q34-P34)*13/12 -> 3270.2139 | S34: =+R34/13 -> 251.55492 | T34: =+AG6*0.05 -> 3274.1397 | U34: =+(T34-S34)*13/12 -> 3274.4668 | V34: =+U34/13 -> 251.88207
A35: noisette | B35: =+C7*0.05 -> 216.77419 | C35: =+B35*13/12 -> 234.83871 | D35: =+C35/13 -> 18.064516 | E35: =+H7*0.05 -> 242.51613 | F35: =+(E35-D35)*13/12 -> 243.15591 | G35: =+F35/13 -> 18.704301 | H35: =+M7*0.05 -> 278.89355 | I35: =+(H35-G35)*13/12 -> 281.87168 | J35: =+I35/13 -> 21.682437 | K35: =+R7*0.05 -> 320.72758 | L35: =+(K35-J35)*13/12 -> 323.96557 | M35: =+L35/13 -> 24.920429 | N35: =+W7*0.05 -> 368.83672 | O35: =+(N35-M35)*13/12 -> 372.57598 | P35: =+O35/13 -> 28.659691 | Q35: =+AB7*0.05 -> 367.29131 | R35: =+(Q35-P35)*13/12 -> 366.85092 | S35: =+R35/13 -> 28.219302 | T35: =+AG7*0.05 -> 367.29131 | U35: =+(T35-S35)*13/12 -> 367.32801 | V35: =+U35/13 -> 28.256001
A36: pistche | B36: =+C8*0.05 -> 216.77419 | C36: =+B36*13/12 -> 234.83871 | D36: =+C36/13 -> 18.064516 | E36: =+H8*0.05 -> 242.51613 | F36: =+(E36-D36)*13/12 -> 243.15591 | G36: =+F36/13 -> 18.704301 | H36: =+M8*0.05 -> 278.89355 | I36: =+(H36-G36)*13/12 -> 281.87168 | J36: =+I36/13 -> 21.682437 | K36: =+R8*0.05 -> 320.72758 | L36: =+(K36-J36)*13/12 -> 323.96557 | M36: =+L36/13 -> 24.920429 | N36: =+W8*0.05 -> 368.83672 | O36: =+(N36-M36)*13/12 -> 372.57598 | P36: =+O36/13 -> 28.659691 | Q36: =+AB8*0.05 -> 367.29131 | R36: =+(Q36-P36)*13/12 -> 366.85092 | S36: =+R36/13 -> 28.219302 | T36: =+AG8*0.05 -> 367.29131 | U36: =+(T36-S36)*13/12 -> 367.32801 | V36: =+U36/13 -> 28.256001
A37: acajou | B37: =+C9*0.05 -> 216.77419 | C37: =+B37*13/12 -> 234.83871 | D37: =+C37/13 -> 18.064516 | E37: =+H9*0.05 -> 242.51613 | F37: =+(E37-D37)*13/12 -> 243.15591 | G37: =+F37/13 -> 18.704301 | H37: =+M9*0.05 -> 278.89355 | I37: =+(H37-G37)*13/12 -> 281.87168 | J37: =+I37/13 -> 21.682437 | K37: =+R9*0.05 -> 320.72758 | L37: =+(K37-J37)*13/12 -> 323.96557 | M37: =+L37/13 -> 24.920429 | N37: =+W9*0.05 -> 368.83672 | O37: =+(N37-M37)*13/12 -> 372.57598 | P37: =+O37/13 -> 28.659691 | Q37: =+AB9*0.05 -> 367.29131 | R37: =+(Q37-P37)*13/12 -> 366.85092 | S37: =+R37/13 -> 28.219302 | T37: =+AG9*0.05 -> 367.29131 | U37: =+(T37-S37)*13/12 -> 367.32801 | V37: =+U37/13 -> 28.256001
A38: Amande | B38: =+C10*0.05 -> 216.77419 | C38: =+B38*13/12 -> 234.83871 | D38: =+C38/13 -> 18.064516 | E38: =+H10*0.05 -> 242.51613 | F38: =+(E38-D38)*13/12 -> 243.15591 | G38: =+F38/13 -> 18.704301 | H38: =+M10*0.05 -> 278.89355 | I38: =+(H38-G38)*13/12 -> 281.87168 | J38: =+I38/13 -> 21.682437 | K38: =+R10*0.05 -> 320.72758 | L38: =+(K38-J38)*13/12 -> 323.96557 | M38: =+L38/13 -> 24.920429 | N38: =+W10*0.05 -> 368.83672 | O38: =+(N38-M38)*13/12 -> 372.57598 | P38: =+O38/13 -> 28.659691 | Q38: =+AB10*0.05 -> 367.29131 | R38: =+(Q38-P38)*13/12 -> 366.85092 | S38: =+R38/13 -> 28.219302 | T38: =+AG10*0.05 -> 367.29131 | U38: =+(T38-S38)*13/12 -> 367.32801 | V38: =+U38/13 -> 28.256001
A39: Achat d'approvisionnement | B39: =SUM(B32:B38) -> 6664.2581 | C39: =SUM(C32:C38) -> 7219.6129 | D39: =SUM(D32:D38) -> 555.35484 | E39: =SUM(E32:E38) -> 7455.6387 | F39: =SUM(F32:F38) -> 7475.3075 | G39: =SUM(G32:G38) -> 575.02366 | H39: =SUM(H32:H38) -> 8573.9845 | I39: =SUM(I32:I38) -> 8665.5409 | ... V39: =SUM(V32:V38) -> 868.6702
D41: =+(B39-C39+D39) -> 1.3642421e-12 | E41: =+(E39-B39)/B39 -> 0.11875 | G41: =+(E39-F39+G39)-D39 -> -2.1600499e-12 | H41: =+(H39-E39)/E39 -> 0.15 | J41: =+(H39-I39+J39)-G39 -> 0 | K41: =+(K39-H39)/H39 -> 0.15 | M41: =+(K39-L39+M39)-J39 -> 2.3874236e-12 | N41: =+(N39-K39)/K39 -> 0.15 | P41: =+(N39-O39+P39)-M39 -> 0 | Q41: =+(Q39-N39)/N39 -> -0.0041899441 | S41: =+(Q39-R39+S39)-P39 -> -3.2969183e-12 | T41: =+(T39-Q39)/Q39 -> 0 | V41: =+(T39-U39+V39)-S39 -> -5.9117156e-12

Sheet Ach prévisionnel
B1: 2016 | G1: 2017 | L1: 2018 | Q1: 2019 | V1: 2020 | AA1: 2021 | AF1: 2022
B2: QT achetée en Kg | C2: PU | D2: Total Achat | E2: QT st Final | F2: Valeur St Final | G2: QT achetée | H2: PU | I2: Total Achat | J2: QT st Final | K2: Valeur St Final | L2: QT achetée | M2: PU | N2: Total Achat | O2: QT st Final | P2: Valeur St Final | Q2: QT achetée | R2: PU | S2: Total Achat | T2: QT st Final | U2: Valeur St Final | V2: QT achetée | W2: PU | X2: Total Achat | Y2: QT st Final | Z2: Valeur St Final | AA2: QT achetée | AB2: PU | AC2: Total Achat | AD2: QT st Final | AE2: Valeur St Final | AF2: QT achetée | AG2: PU | AH2: Total Achat | AI2: QT st Final | AJ2: Valeur St Final
A3: MP MAIS | B3: =+'Consommations Q'!E4 -> 42287.071 | C3: =+Données!B28 -> 2.8 | D3: =+B3*C3 -> 118403.8 | E3: =+'Consommations Q'!F4 -> 3252.8516 | F3: =+C3*E3 -> 9107.9845 | G3: =+'Consommations Q'!J4 -> 43784.738 | H3: =+$C$3 -> 2.8 | I3: =+G3*H3 -> 122597.27 | J3: =+'Consommations Q'!K4 -> 3368.0568 | K3: =+H3*J3 -> 9430.559 | L3: =+'Consommations Q'!O4 -> 50756.232 | M3: =+$C$3 -> 2.8 | N3: =+L3*M3 -> 142117.45 | O3: =+'Consommations Q'!P4 -> 3904.3255 | P3: =+O3*M3 -> 10932.111 | Q3: =+'Consommations Q'!T4 -> 58336.018 | R3: =+$C$3 -> 2.8 | S3: =+Q3*R3 -> 163340.85 | T3: =+'Consommations Q'!U4 -> 4487.386 | U3: =+T3*R3 -> 12564.681 | V3: =+'Consommations Q'!Y4 -> 67089.224 | W3: =+$C$3 -> 2.8 | X3: =+V3*W3 -> 187849.83 | Y3: =+'Consommations Q'!Z4 -> 5160.7096 | Z3: =+Y3*W3 -> 14449.987 | AA3: =+'Consommations Q'!AD4 -> 66058.322 | AB3: =+$C$3 -> 2.8 | AC3: =+AA3*AB3 -> 184963.3 | AD3: =+'Consommations Q'!AE4 -> 5081.4094 | AE3: =+AD3*AB3 -> 14227.946 | AF3: =+'Consommations Q'!AI4 -> 66144.23 | AG3: =+$C$3 -> 2.8 | AH3: =+AF3*AG3 -> 185203.84 | AI3: =+'Consommations Q'!AJ4 -> 5088.0177 | AJ3: =+AI3*AG3 -> 14246.45
A4: MP Cacahuète | B4: =+'Consommations Q'!E5 -> 42287.071 | C4: =+Données!B29 -> 5.1 | D4: =+B4*C4 -> 215664.06 | E4: =+'Consommations Q'!F5 -> 3252.8516 | F4: =+C4*E4 -> 16589.543 | G4: =+'Consommations Q'!J5 -> 43784.738 | H4: =+$C$4 -> 5.1 | I4: =+G4*H4 -> 223302.16 | J4: =+'Consommations Q'!K5 -> 3368.0568 | K4: =+H4*J4 -> 17177.09 | L4: =+'Consommations Q'!O5 -> 50756.232 | M4: =+$C$4 -> 5.1 | N4: =+L4*M4 -> 258856.78 | O4: =+'Consommations Q'!P5 -> 3904.3255 | P4: =+O4*M4 -> 19912.06 | Q4: =+'Consommations Q'!T5 -> 58336.018 | R4: =+$C$4 -> 5.1 | S4: =+Q4*R4 -> 297513.69 | T4: =+'Consommations Q'!U5 -> 4487.386 | U4: =+T4*R4 -> 22885.668 | V4: =+'Consommations Q'!Y5 -> 67089.224 | W4: =+$C$4 -> 5.1 | X4: =+V4*W4 -> 342155.04 | Y4: =+'Consommations Q'!Z5 -> 5160.7096 | Z4: =+Y4*W4 -> 26319.619 | AA4: =+'Consommations Q'!AD5 -> 66058.322 | AB4: =+$C$4 -> 5.1 | AC4: =+AA4*AB4 -> 336897.44 | AD4: =+'Consommations Q'!AE5 -> 5081.4094 | AE4: =+AD4*AB4 -> 25915.188 | AF4: =+'Consommations Q'!AI5 -> 66144.23 | AG4: =+$C$4 -> 5.1 | AH4: =+AF4*AG4 -> 337335.57 | AI4: =+'Consommations Q'!AJ5 -> 5088.0177 | AJ4: =+AI4*AG4 -> 25948.89
A5: Pois chiche | B5: =+'Consommations Q'!E6 -> 42287.071 | C5: =+Données!B30 -> 3.8 | D5: =+B5*C5 -> 160690.87 | E5: =+'Consommations Q'!F6 -> 3252.8516 | F5: =+C5*E5 -> 12360.836 | G5: =+'Consommations Q'!J6 -> 43784.738 | H5: =+$C$5 -> 3.8 | I5: =+G5*H5 -> 166382 | J5: =+'Consommations Q'!K6 -> 3368.0568 | K5: =+H5*J5 -> 12798.616 | L5: =+'Consommations Q'!O6 -> 50756.232 | M5: =+$C$5 -> 3.8 | N5: =+L5*M5 -> 192873.68 | O5: =+'Consommations Q'!P6 -> 3904.3255 | P5: =+O5*M5 -> 14836.437 | Q5: =+'Consommations Q'!T6 -> 58336.018 | R5: =+$C$5 -> 3.8 | S5: =+Q5*R5 -> 221676.87 | T5: =+'Consommations Q'!U6 -> 4487.386 | U5: =+T5*R5 -> 17052.067 | V5: =+'Consommations Q'!Y6 -> 67089.224 | W5: =+$C$5 -> 3.8 | X5: =+V5*W5 -> 254939.05 | Y5: =+'Consommations Q'!Z6 -> 5160.7096 | Z5: =+Y5*W5 -> 19610.696 | AA5: =+'Consommations Q'!AD6 -> 66058.322 | AB5: =+$C$5 -> 3.8 | AC5: =+AA5*AB5 -> 251021.62 | AD5: =+'Consommations Q'!AE6 -> 5081.4094 | AE5: =+AD5*AB5 -> 19309.356 | AF5: =+'Consommations Q'!AI6 -> 66144.23 | AG5: =+$C$5 -> 3.8 | AH5: =+AF5*AG5 -> 251348.08 | AI5: =+'Consommations Q'!AJ6 -> 5088.0177 | AJ5: =+AI5*AG5 -> 19334.467
A6: MP noisette | B6: =+'Consommations Q'!E7 -> 4743.7419 | C6: =+Données!B34 -> 24 | D6: =+B6*C6 -> 113849.81 | E6: =+'Consommations Q'!F7 -> 364.90323 | F6: =+C6*E6 -> 8757.6774 | G6: =+'Consommations Q'!J7 -> 4911.7495 | H6: =+$C$6 -> 24 | I6: =+G6*H6 -> 117881.99 | J6: =+'Consommations Q'!K7 -> 377.82688 | K6: =+H6*J6 -> 9067.8452 | L6: =+'Consommations Q'!O7 -> 5693.808 | M6: =+$C$6 -> 24 | N6: =+L6*M6 -> 136651.39 | O6: =+'Consommations Q'!P7 -> 437.98523 | P6: =+O6*M6 -> 10511.646 | Q6: =+'Consommations Q'!T7 -> 6544.1046 | R6: =+$C$6 -> 24 | S6: =+Q6*R6 -> 157058.51 | T6: =+'Consommations Q'!U7 -> 503.39266 | U6: =+T6*R6 -> 12081.424 | V6: =+'Consommations Q'!Y7 -> 7526.0348 | W6: =+$C$6 -> 24 | X6: =+V6*W6 -> 180624.84 | Y6: =+'Consommations Q'!Z7 -> 578.92575 | Z6: =+Y6*W6 -> 13894.218 | AA6: =+'Consommations Q'!AD7 -> 7410.3887 | AB6: =+$C$6 -> 24 | AC6: =+AA6*AB6 -> 177849.33 | AD6: =+'Consommations Q'!AE7 -> 570.0299 | AE6: =+AD6*AB6 -> 13680.718 | AF6: =+'Consommations Q'!AI7 -> 7420.0258 | AG6: =+$C$6 -> 24 | AH6: =+AF6*AG6 -> 178080.62 | AI6: =+'Consommations Q'!AJ7 -> 570.77122 | AJ6: =+AI6*AG6 -> 13698.509
A7: MP pistche | B7: =+'Consommations Q'!E8 -> 4743.7419 | C7: =+Données!B33 -> 24 | D7: =+B7*C7 -> 113849.81 | E7: =+'Consommations Q'!F8 -> 364.90323 | F7: =+C7*E7 -> 8757.6774 | G7: =+'Consommations Q'!J8 -> 4911.7495 | H7: =+$C$7 -> 24 | I7: =+G7*H7 -> 117881.99 | J7: =+'Consommations Q'!K8 -> 377.82688 | K7: =+H7*J7 -> 9067.8452 | L7: =+'Consommations Q'!O8 -> 5693.808 | M7: =+$C$7 -> 24 | N7: =+L7*M7 -> 136651.39 | O7: =+'Consommations Q'!P8 -> 437.98523 | P7: =+O7*M7 -> 10511.646 | Q7: =+'Consommations Q'!T8 -> 6544.1046 | R7: =+$C$7 -> 24 | S7: =+Q7*R7 -> 157058.51 | T7: =+'Consommations Q'!U8 -> 503.39266 | U7: =+T7*R7 -> 12081.424 | V7: =+'Consommations Q'!Y8 -> 7526.0348 | W7: =+$C$7 -> 24 | X7: =+V7*W7 -> 180624.84 | Y7: =+'Consommations Q'!Z8 -> 578.92575 | Z7: =+Y7*W7 -> 13894.218 | AA7: =+'Consommations Q'!AD8 -> 7410.3887 | AB7: =+$C$7 -> 24 | AC7: =+AA7*AB7 -> 177849.33 | AD7: =+'Consommations Q'!AE8 -> 570.0299 | AE7: =+AD7*AB7 -> 13680.718 | AF7: =+'Consommations Q'!AI8 -> 7420.0258 | AG7: =+$C$7 -> 24 | AH7: =+AF7*AG7 -> 178080.62 | AI7: =+'Consommations Q'!AJ8 -> 570.77122 | AJ7: =+AI7*AG7 -> 13698.509
A8: MP acajou | B8: =+'Consommations Q'!E9 -> 4743.7419 | C8: =+Données!B32 -> 22 | D8: =+B8*C8 -> 104362.32 | E8: =+'Consommations Q'!F9 -> 364.90323 | F8: =+C8*E8 -> 8027.871 | G8: =+'Consommations Q'!J9 -> 4911.7495 | H8: =+$C$8 -> 22 | I8: =+G8*H8 -> 108058.49 | J8: =+'Consommations Q'!K9 -> 377.82688 | K8: =+H8*J8 -> 8312.1914 | L8: =+'Consommations Q'!O9 -> 5693.808 | M8: =+$C$8 -> 22 | N8: =+L8*M8 -> 125263.78 | O8: =+'Consommations Q'!P9 -> 437.98523 | P8: =+O8*M8 -> 9635.6751 | Q8: =+'Consommations Q'!T9 -> 6544.1046 | R8: =+$C$8 -> 22 | S8: =+Q8*R8 -> 143970.3 | T8: =+'Consommations Q'!U9 -> 503.39266 | U8: =+T8*R8 -> 11074.638 | V8: =+'Consommations Q'!Y9 -> 7526.0348 | W8: =+$C$8 -> 22 | X8: =+V8*W8 -> 165572.77 | Y8: =+'Consommations Q'!Z9 -> 578.92575 | Z8: =+Y8*W8 -> 12736.367 | AA8: =+'Consommations Q'!AD9 -> 7410.3887 | AB8: =+$C$8 -> 22 | AC8: =+AA8*AB8 -> 163028.55 | AD8: =+'Consommations Q'!AE9 -> 570.0299 | AE8: =+AD8*AB8 -> 12540.658 | AF8: =+'Consommations Q'!AI9 -> 7420.0258 | AG8: =+$C$8 -> 22 | AH8: =+AF8*AG8 -> 163240.57 | AI8: =+'Consommations Q'!AJ9 -> 570.77122 | AJ8: =+AI8*AG8 -> 12556.967
A9: MP Amande | B9: =+'Consommations Q'!E10 -> 4743.7419 | C9: =+Données!B31 -> 25 | D9: =+B9*C9 -> 118593.55 | E9: =+'Consommations Q'!F10 -> 364.90323 | F9: =+C9*E9 -> 9122.5806 | G9: =+'Consommations Q'!J10 -> 4911.7495 | H9: =+$C$9 -> 25 | I9: =+G9*H9 -> 122793.74 | J9: =+'Consommations Q'!K10 -> 377.82688 | K9: =+H9*J9 -> 9445.672 | L9: =+'Consommations Q'!O10 -> 5693.808 | M9: =+$C$9 -> 25 | N9: =+L9*M9 -> 142345.2 | O9: =+'Consommations Q'!P10 -> 437.98523 | P9: =+O9*M9 -> 10949.631 | Q9: =+'Consommations Q'!T10 -> 6544.1046 | R9: =+$C$9 -> 25 | S9: =+Q9*R9 -> 163602.61 | T9: =+'Consommations Q'!U10 -> 503.39266 | U9: =+T9*R9 -> 12584.816 | V9: =+'Consommations Q'!Y10 -> 7526.0348 | W9: =+$C$9 -> 25 | X9: =+V9*W9 -> 188150.87 | Y9: =+'Consommations Q'!Z10 -> 578.92575 | Z9: =+Y9*W9 -> 14473.144 | AA9: =+'Consommations Q'!AD10 -> 7410.3887 | AB9: =+$C$9 -> 25 | AC9: =+AA9*AB9 -> 185259.72 | AD9: =+'Consommations Q'!AE10 -> 570.0299 | AE9: =+AD9*AB9 -> 14250.747 | AF9: =+'Consommations Q'!AI10 -> 7420.0258 | AG9: =+$C$9 -> 25 | AH9: =+AF9*AG9 -> 185500.65 | AI9: =+'Consommations Q'!AJ10 -> 570.77122 | AJ9: =+AI9*AG9 -> 14269.28
A10: Total | B10: =SUM(B3:B9) -> 145836.18 | C10: =SUM(C3:C9) -> 106.7 | D10: =SUM(D3:D9) -> 945414.21 | E10: =SUM(E3:E9) -> 11218.168 | F10: =SUM(F3:F9) -> 72724.17 | G10: =SUM(G3:G9) -> 151001.21 | H10: =SUM(H3:H9) -> 106.7 | I10: =SUM(I3:I9) -> 978897.63 | ... AJ10: =SUM(AJ3:AJ9) -> 113753.07
D12: =+B3/13 -> 3252.8516 | G12: =+G10+E10-J10 -> 150603.9 | I12: =+G3+E3-J3 -> 43669.533
B14: 2016 | G14: 2017 | L14: 2018 | Q14: 2019 | V14: 2020 | AA14: 2021 | AF14: 2022
A15: MP Aromes
B16: QT consommées | C16: PU | D16: Valeurs | E16: QT St Final | F16: Valeurs St Final | G16: QT consommées | H16: PU | I16: Valeurs | J16: QT St Final | K16: Valeurs St Final | L16: QT consommées | M16: PU | N16: Valeurs | O16: QT St Final | P16: Valeurs St Final | Q16: QT consommées | R16: PU | S16: Valeurs | T16: QT St Final | U16: Valeurs St Final | V16: QT consommées | W16: PU | X16: Valeurs | Y16: QT St Final | Z16: Valeurs St Final | AA16: QT consommées | AB16: PU | AC16: Valeurs | AD16: QT St Final | AE16: Valeurs St Final | AF16: QT consommées | AG16: PU | AH16: Valeurs | AI16: QT St Final | AJ16: Valeurs St Final
A17: MAIS | B17: =+'Consommations Q'!B19 -> 2318.8645 | C17: =+Données!$B$35 -> 22.183 | D17: =+B17*C17 -> 51439.372 | E17: =+'Consommations Q'!D19 -> 193.23871 | F17: =+C17*E17 -> 4286.6143 | G17: =+'Consommations Q'!E19 -> 2594.2297 | H17: =+Données!$B$35 -> 22.183 | I17: =+G17*H17 -> 57547.797 | J17: =+'Consommations Q'!G19 -> 200.08258 | K17: =+H17*J17 -> 4438.4319 | L17: =+'Consommations Q'!H19 -> 2983.3641 | M17: =+Données!$B$35 -> 22.183 | N17: =+L17*M17 -> 66179.966 | O17: =+'Consommations Q'!J19 -> 231.94013 | P17: =+M17*O17 -> 5145.1279 | Q17: =+'Consommations Q'!K19 -> 3430.8687 | R17: =+Données!$B$35 -> 22.183 | S17: =+Q17*R17 -> 76106.961 | T17: =+'Consommations Q'!M19 -> 266.57738 | U17: =+R17*T17 -> 5913.4861 | V17: =+'Consommations Q'!N19 -> 3945.4991 | W17: =+Données!$B$35 -> 22.183 | X17: =+V17*W17 -> 87523.006 | Y17: =+'Consommations Q'!P19 -> 306.57681 | Z17: =+W17*Y17 -> 6800.7933 | AA17: =+'Consommations Q'!Q19 -> 3928.9676 | AB17: =+Données!$B$35 -> 22.183 | AC17: =+AA17*AB17 -> 87156.289 | AD17: =+'Consommations Q'!S19 -> 301.8659 | AE17: =+AB17*AD17 -> 6696.2913 | AF17: =+'Consommations Q'!T19 -> 3928.9676 | AG17: =+Données!$B$35 -> 22.183 | AH17: =+AF17*AG17 -> 87156.289 | AI17: =+'Consommations Q'!V19 -> 302.25848 | AJ17: =+AG17*AI17 -> 6704.9998
A18: Cacahuète | B18: =+'Consommations Q'!B20 -> 2318.8645 | C18: =+Données!$B$35 -> 22.183 | D18: =+B18*C18 -> 51439.372 | E18: =+'Consommations Q'!D20 -> 193.23871 | F18: =+C18*E18 -> 4286.6143 | G18: =+'Consommations Q'!E20 -> 2594.2297 | H18: =+Données!$B$35 -> 22.183 | I18: =+G18*H18 -> 57547.797 | J18: =+'Consommations Q'!G20 -> 200.08258 | K18: =+H18*J18 -> 4438.4319 | L18: =+'Consommations Q'!H20 -> 2983.3641 | M18: =+Données!$B$35 -> 22.183 | N18: =+L18*M18 -> 66179.966 | O18: =+'Consommations Q'!J20 -> 231.94013 | P18: =+M18*O18 -> 5145.1279 | Q18: =+'Consommations Q'!K20 -> 3430.8687 | R18: =+Données!$B$35 -> 22.183 | S18: =+Q18*R18 -> 76106.961 | T18: =+'Consommations Q'!M20 -> 266.57738 | U18: =+R18*T18 -> 5913.4861 | V18: =+'Consommations Q'!N20 -> 3945.4991 | W18: =+Données!$B$35 -> 22.183 | X18: =+V18*W18 -> 87523.006 | Y18: =+'Consommations Q'!P20 -> 306.57681 | Z18: =+W18*Y18 -> 6800.7933 | AA18: =+'Consommations Q'!Q20 -> 3928.9676 | AB18: =+Données!$B$35 -> 22.183 | AC18: =+AA18*AB18 -> 87156.289 | AD18: =+'Consommations Q'!S20 -> 301.8659 | AE18: =+AB18*AD18 -> 6696.2913 | AF18: =+'Consommations Q'!T20 -> 3928.9676 | AG18: =+Données!$B$35 -> 22.183 | AH18: =+AF18*AG18 -> 87156.289 | AI18: =+'Consommations Q'!V20 -> 302.25848 | AJ18: =+AG18*AI18 -> 6704.9998
A19: Pois chiche | B19: =+'Consommations Q'!B21 -> 2318.8645 | C19: =+Données!$B$35 -> 22.183 | D19: =+B19*C19 -> 51439.372 | E19: =+'Consommations Q'!D21 -> 193.23871 | F19: =+C19*E19 -> 4286.6143 | G19: =+'Consommations Q'!E21 -> 2594.2297 | H19: =+Données!$B$35 -> 22.183 | I19: =+G19*H19 -> 57547.797 | J19: =+'Consommations Q'!G21 -> 200.08258 | K19: =+H19*J19 -> 4438.4319 | L19: =+'Consommations Q'!H21 -> 2983.3641 | M19: =+Données!$B$35 -> 22.183 | N19: =+L19*M19 -> 66179.966 | O19: =+'Consommations Q'!J21 -> 231.94013 | P19: =+M19*O19 -> 5145.1279 | Q19: =+'Consommations Q'!K21 -> 3430.8687 | R19: =+Données!$B$35 -> 22.183 | S19: =+Q19*R19 -> 76106.961 | T19: =+'Consommations Q'!M21 -> 266.57738 | U19: =+R19*T19 -> 5913.4861 | V19: =+'Consommations Q'!N21 -> 3945.4991 | W19: =+Données!$B$35 -> 22.183 | X19: =+V19*W19 -> 87523.006 | Y19: =+'Consommations Q'!P21 -> 306.57681 | Z19: =+W19*Y19 -> 6800.7933 | AA19: =+'Consommations Q'!Q21 -> 3928.9676 | AB19: =+Données!$B$35 -> 22.183 | AC19: =+AA19*AB19 -> 87156.289 | AD19: =+'Consommations Q'!S21 -> 301.8659 | AE19: =+AB19*AD19 -> 6696.2913 | AF19: =+'Consommations Q'!T21 -> 3928.9676 | AG19: =+Données!$B$35 -> 22.183 | AH19: =+AF19*AG19 -> 87156.289 | AI19: =+'Consommations Q'!V21 -> 302.25848 | AJ19: =+AG19*AI19 -> 6704.9998
A20: noisette | B20: =+'Consommations Q'!B22 -> 260.12903 | C20: =+Données!$B$35 -> 22.183 | D20: =+B20*C20 -> 5770.4423 | E20: =+'Consommations Q'!D22 -> 21.677419 | F20: =+C20*E20 -> 480.87019 | G20: =+'Consommations Q'!E22 -> 291.01935 | H20: =+Données!$B$35 -> 22.183 | I20: =+G20*H20 -> 6455.6823 | J20: =+'Consommations Q'!G22 -> 22.445161 | K20: =+H20*J20 -> 497.90101 | L20: =+'Consommations Q'!H22 -> 334.67226 | M20: =+Données!$B$35 -> 22.183 | N20: =+L20*M20 -> 7424.0347 | O20: =+'Consommations Q'!J22 -> 26.018925 | P20: =+M20*O20 -> 577.17781 | Q20: =+'Consommations Q'!K22 -> 384.8731 | R20: =+Données!$B$35 -> 22.183 | S20: =+Q20*R20 -> 8537.6399 | T20: =+'Consommations Q'!M22 -> 29.904514 | U20: =+R20*T20 -> 663.37184 | V20: =+'Consommations Q'!N22 -> 442.60406 | W20: =+Données!$B$35 -> 22.183 | X20: =+V20*W20 -> 9818.2859 | Y20: =+'Consommations Q'!P22 -> 34.391629 | Z20: =+W20*Y20 -> 762.9095 | AA20: =+'Consommations Q'!Q22 -> 440.74957 | AB20: =+Données!$B$35 -> 22.183 | AC20: =+AA20*AB20 -> 9777.1478 | AD20: =+'Consommations Q'!S22 -> 33.863162 | AE20: =+AB20*AD20 -> 751.18653 | AF20: =+'Consommations Q'!T22 -> 440.74957 | AG20: =+Données!$B$35 -> 22.183 | AH20: =+AF20*AG20 -> 9777.1478 | AI20: =+'Consommations Q'!V22 -> 33.907201 | AJ20: =+AG20*AI20 -> 752.16344
A21: pistche | B21: =+'Consommations Q'!B23 -> 260.12903 | C21: =+Données!$B$35 -> 22.183 | D21: =+B21*C21 -> 5770.4423 | E21: =+'Consommations Q'!D23 -> 21.677419 | F21: =+C21*E21 -> 480.87019 | G21: =+'Consommations Q'!E23 -> 291.01935 | H21: =+Données!$B$35 -> 22.183 | I21: =+G21*H21 -> 6455.6823 | J21: =+'Consommations Q'!G23 -> 22.445161 | K21: =+H21*J21 -> 497.90101 | L21: =+'Consommations Q'!H23 -> 334.67226 | M21: =+Données!$B$35 -> 22.183 | N21: =+L21*M21 -> 7424.0347 | O21: =+'Consommations Q'!J23 -> 26.018925 | P21: =+M21*O21 -> 577.17781 | Q21: =+'Consommations Q'!K23 -> 384.8731 | R21: =+Données!$B$35 -> 22.183 | S21: =+Q21*R21 -> 8537.6399 | T21: =+'Consommations Q'!M23 -> 29.904514 | U21: =+R21*T21 -> 663.37184 | V21: =+'Consommations Q'!N23 -> 442.60406 | W21: =+Données!$B$35 -> 22.183 | X21: =+V21*W21 -> 9818.2859 | Y21: =+'Consommations Q'!P23 -> 34.391629 | Z21: =+W21*Y21 -> 762.9095 | AA21: =+'Consommations Q'!Q23 -> 440.74957 | AB21: =+Données!$B$35 -> 22.183 | AC21: =+AA21*AB21 -> 9777.1478 | AD21: =+'Consommations Q'!S23 -> 33.863162 | AE21: =+AB21*AD21 -> 751.18653 | AF21: =+'Consommations Q'!T23 -> 440.74957 | AG21: =+Données!$B$35 -> 22.183 | AH21: =+AF21*AG21 -> 9777.1478 | AI21: =+'Consommations Q'!V23 -> 33.907201 | AJ21: =+AG21*AI21 -> 752.16344
A22: acajou | B22: =+'Consommations Q'!B24 -> 260.12903 | C22: =+Données!$B$35 -> 22.183 | D22: =+B22*C22 -> 5770.4423 | E22: =+'Consommations Q'!D24 -> 21.677419 | F22: =+C22*E22 -> 480.87019 | G22: =+'Consommations Q'!E24 -> 291.01935 | H22: =+Données!$B$35 -> 22.183 | I22: =+G22*H22 -> 6455.6823 | J22: =+'Consommations Q'!G24 -> 22.445161 | K22: =+H22*J22 -> 497.90101 | L22: =+'Consommations Q'!H24 -> 334.67226 | M22: =+Données!$B$35 -> 22.183 | N22: =+L22*M22 -> 7424.0347 | O22: =+'Consommations Q'!J24 -> 26.018925 | P22: =+M22*O22 -> 577.17781 | Q22: =+'Consommations Q'!K24 -> 384.8731 | R22: =+Données!$B$35 -> 22.183 | S22: =+Q22*R22 -> 8537.6399 | T22: =+'Consommations Q'!M24 -> 29.904514 | U22: =+R22*T22 -> 663.37184 | V22: =+'Consommations Q'!N24 -> 442.60406 | W22: =+Données!$B$35 -> 22.183 | X22: =+V22*W22 -> 9818.2859 | Y22: =+'Consommations Q'!P24 -> 34.391629 | Z22: =+W22*Y22 -> 762.9095 | AA22: =+'Consommations Q'!Q24 -> 440.74957 | AB22: =+Données!$B$35 -> 22.183 | AC22: =+AA22*AB22 -> 9777.1478 | AD22: =+'Consommations Q'!S24 -> 33.863162 | AE22: =+AB22*AD22 -> 751.18653 | AF22: =+'Consommations Q'!T24 -> 440.74957 | AG22: =+Données!$B$35 -> 22.183 | AH22: =+AF22*AG22 -> 9777.1478 | AI22: =+'Consommations Q'!V24 -> 33.907201 | AJ22: =+AG22*AI22 -> 752.16344
A23: Amande | B23: =+'Consommations Q'!B25 -> 260.12903 | C23: =+Données!$B$35 -> 22.183 | D23: =+B23*C23 -> 5770.4423 | E23: =+'Consommations Q'!D25 -> 21.677419 | F23: =+C23*E23 -> 480.87019 | G23: =+'Consommations Q'!E25 -> 291.01935 | H23: =+Données!$B$35 -> 22.183 | I23: =+G23*H23 -> 6455.6823 | J23: =+'Consommations Q'!G25 -> 22.445161 | K23: =+H23*J23 -> 497.90101 | L23: =+'Consommations Q'!H25 -> 334.67226 | M23: =+Données!$B$35 -> 22.183 | N23: =+L23*M23 -> 7424.0347 | O23: =+'Consommations Q'!J25 -> 26.018925 | P23: =+M23*O23 -> 577.17781 | Q23: =+'Consommations Q'!K25 -> 384.8731 | R23: =+Données!$B$35 -> 22.183 | S23: =+Q23*R23 -> 8537.6399 | T23: =+'Consommations Q'!M25 -> 29.904514 | U23: =+R23*T23 -> 663.37184 | V23: =+'Consommations Q'!N25 -> 442.60406 | W23: =+Données!$B$35 -> 22.183 | X23: =+V23*W23 -> 9818.2859 | Y23: =+'Consommations Q'!P25 -> 34.391629 | Z23: =+W23*Y23 -> 762.9095 | AA23: =+'Consommations Q'!Q25 -> 440.74957 | AB23: =+Données!$B$35 -> 22.183 | AC23: =+AA23*AB23 -> 9777.1478 | AD23: =+'Consommations Q'!S25 -> 33.863162 | AE23: =+AB23*AD23 -> 751.18653 | AF23: =+'Consommations Q'!T25 -> 440.74957 | AG23: =+Données!$B$35 -> 22.183 | AH23: =+AF23*AG23 -> 9777.1478 | AI23: =+'Consommations Q'!V25 -> 33.907201 | AJ23: =+AG23*AI23 -> 752.16344
A24: Achat d'approvisionnement | B24: =SUM(B17:B23) -> 7997.1097 | D24: =SUM(D17:D23) -> 177399.88 | E24: =SUM(E17:E23) -> 666.42581 | F24: =SUM(F17:F23) -> 14783.324 | G24: =SUM(G17:G23) -> 8946.7665 | I24: =SUM(I17:I23) -> 198466.12 | J24: =SUM(J17:J23) -> 690.02839 | K24: =SUM(K17:K23) -> 15306.9 | L24: =SUM(L17:L23) -> 10288.781 | N24: =SUM(N17:N23) -> 228236.04 | O24: =SUM(O17:O23) -> 799.89609 | P24: =SUM(P17:P23) -> 17744.095 | Q24: =SUM(Q17:Q23) -> 11832.099 | S24: =SUM(S17:S23) -> 262471.44 | T24: =SUM(T17:T23) -> 919.35021 | U24: =SUM(U17:U23) -> 20393.946 | V24: =SUM(V17:V23) -> 13606.913 | X24: =SUM(X17:X23) -> 301842.16 | Y24: =SUM(Y17:Y23) -> 1057.2969 | Z24: =SUM(Z17:Z23) -> 23454.018 | AA24: =SUM(AA17:AA23) -> 13549.901 | AC24: =SUM(AC17:AC23) -> 300577.46 | AD24: =SUM(AD17:AD23) -> 1041.0504 | AE24: =SUM(AE17:AE23) -> 23093.62 | AF24: =SUM(AF17:AF23) -> 13549.901 | AH24: =SUM(AH17:AH23) -> 300577.46 | AI24: =SUM(AI17:AI23) -> 1042.4042 | AJ24: =SUM(AJ17:AJ23) -> 23123.653
G26: =+(G24-B24)/B24 -> 0.11875 | I26: =+(I24-D24)/D24 -> 0.11875 | N26: =+(N24-I24)/I24 -> 0.15 | S26: =+(S24-N24)/N24 -> 0.15 | X26: =+(X24-S24)/S24 -> 0.15 | AC26: =+(AC24-X24)/X24 -> -0.0041899441 | AH26: =+(AH24-AC24)/AC24 -> 0
B27: 2016 | G27: 2017 | L27: 2018 | Q27: 2019 | V27: 2020 | AA27: 2021 | AF27: 2022
A28: MP emballage
B29: QT consommées | C29: PU | D29: Valeurs | E29: QT St Final | F29: Valeurs St Final | G29: QT consommées | H29: PU | I29: Valeurs | J29: QT St Final | K29: Valeurs St Final | L29: QT consommées | M29: PU | N29: Valeurs | O29: QT St Final | P29: Valeurs St Final | Q29: QT consommées | R29: PU | S29: Valeurs | T29: QT St Final | U29: Valeurs St Final | V29: QT consommées | W29: PU | X29: Valeurs | Y29: QT St Final | Z29: Valeurs St Final | AA29: QT consommées | AB29: PU | AC29: Valeurs | AD29: QT St Final | AE29: Valeurs St Final | AF29: QT consommées | AG29: PU | AH29: Valeurs | AI29: QT St Final | AJ29: Valeurs St Final
A30: MAIS | B30: =+'Consommations Q'!B32 -> 1932.3871 | C30: =+Données!$B$17 -> 11 | D30: =+B30*C30 -> 21256.258 | E30: =+'Consommations Q'!D32 -> 161.03226 | F30: =+C30*E30 -> 1771.3548 | G30: =+'Consommations Q'!E32 -> 2161.8581 | H30: =+Données!$B$17 -> 11 | I30: =+G30*H30 -> 23780.439 | J30: =+'Consommations Q'!G32 -> 166.73548 | K30: =+H30*J30 -> 1834.0903 | L30: =+'Consommations Q'!H32 -> 2486.1368 | M30: =+Données!$B$17 -> 11 | N30: =+L30*M30 -> 27347.505 | O30: =+'Consommations Q'!J32 -> 193.28344 | P30: =+M30*O30 -> 2126.1178 | Q30: =+'Consommations Q'!K32 -> 2859.0573 | R30: =+Données!$B$17 -> 11 | S30: =+Q30*R30 -> 31449.63 | T30: =+'Consommations Q'!M32 -> 222.14782 | U30: =+R30*T30 -> 2443.626 | V30: =+'Consommations Q'!N32 -> 3287.9159 | W30: =+Données!$B$17 -> 11 | X30: =+V30*W30 -> 36167.075 | Y30: =+'Consommations Q'!P32 -> 255.48067 | Z30: =+W30*Y30 -> 2810.2874 | AA30: =+'Consommations Q'!Q32 -> 3274.1397 | AB30: =+Données!$B$17 -> 11 | AC30: =+AA30*AB30 -> 36015.537 | AD30: =+'Consommations Q'!S32 -> 251.55492 | AE30: =+AB30*AD30 -> 2767.1041 | AF30: =+'Consommations Q'!T32 -> 3274.1397 | AG30: =+Données!$B$17 -> 11 | AH30: =+AF30*AG30 -> 36015.537 | AI30: =+'Consommations Q'!V32 -> 251.88207 | AJ30: =+AG30*AI30 -> 2770.7027
A31: Cacahuète | B31: =+'Consommations Q'!B33 -> 1932.3871 | C31: =+Données!$B$17 -> 11 | D31: =+B31*C31 -> 21256.258 | E31: =+'Consommations Q'!D33 -> 161.03226 | F31: =+C31*E31 -> 1771.3548 | G31: =+'Consommations Q'!E33 -> 2161.8581 | H31: =+Données!$B$17 -> 11 | I31: =+G31*H31 -> 23780.439 | J31: =+'Consommations Q'!G33 -> 166.73548 | K31: =+H31*J31 -> 1834.0903 | L31: =+'Consommations Q'!H33 -> 2486.1368 | M31: =+Données!$B$17 -> 11 | N31: =+L31*M31 -> 27347.505 | O31: =+'Consommations Q'!J33 -> 193.28344 | P31: =+M31*O31 -> 2126.1178 | Q31: =+'Consommations Q'!K33 -> 2859.0573 | R31: =+Données!$B$17 -> 11 | S31: =+Q31*R31 -> 31449.63 | T31: =+'Consommations Q'!M33 -> 222.14782 | U31: =+R31*T31 -> 2443.626 | V31: =+'Consommations Q'!N33 -> 3287.9159 | W31: =+Données!$B$17 -> 11 | X31: =+V31*W31 -> 36167.075 | Y31: =+'Consommations Q'!P33 -> 255.48067 | Z31: =+W31*Y31 -> 2810.2874 | AA31: =+'Consommations Q'!Q33 -> 3274.1397 | AB31: =+Données!$B$17 -> 11 | AC31: =+AA31*AB31 -> 36015.537 | AD31: =+'Consommations Q'!S33 -> 251.55492 | AE31: =+AB31*AD31 -> 2767.1041 | AF31: =+'Consommations Q'!T33 -> 3274.1397 | AG31: =+Données!$B$17 -> 11 | AH31: =+AF31*AG31 -> 36015.537 | AI31: =+'Consommations Q'!V33 -> 251.88207 | AJ31: =+AG31*AI31 -> 2770.7027
A32: Pois chiche | B32: =+'Consommations Q'!B34 -> 1932.3871 | C32: =+Données!$B$17 -> 11 | D32: =+B32*C32 -> 21256.258 | E32: =+'Consommations Q'!D34 -> 161.03226 | F32: =+C32*E32 -> 1771.3548 | G32: =+'Consommations Q'!E34 -> 2161.8581 | H32: =+Données!$B$17 -> 11 | I32: =+G32*H32 -> 23780.439 | J32: =+'Consommations Q'!G34 -> 166.73548 | K32: =+H32*J32 -> 1834.0903 | L32: =+'Consommations Q'!H34 -> 2486.1368 | M32: =+Données!$B$17 -> 11 | N32: =+L32*M32 -> 27347.505 | O32: =+'Consommations Q'!J34 -> 193.28344 | P32: =+M32*O32 -> 2126.1178 | Q32: =+'Consommations Q'!K34 -> 2859.0573 | R32: =+Données!$B$17 -> 11 | S32: =+Q32*R32 -> 31449.63 | T32: =+'Consommations Q'!M34 -> 222.14782 | U32: =+R32*T32 -> 2443.626 | V32: =+'Consommations Q'!N34 -> 3287.9159 | W32: =+Données!$B$17 -> 11 | X32: =+V32*W32 -> 36167.075 | Y32: =+'Consommations Q'!P34 -> 255.48067 | Z32: =+W32*Y32 -> 2810.2874 | AA32: =+'Consommations Q'!Q34 -> 3274.1397 | AB32: =+Données!$B$17 -> 11 | AC32: =+AA32*AB32 -> 36015.537 | AD32: =+'Consommations Q'!S34 -> 251.55492 | AE32: =+AB32*AD32 -> 2767.1041 | AF32: =+'Consommations Q'!T34 -> 3274.1397 | AG32: =+Données!$B$17 -> 11 | AH32: =+AF32*AG32 -> 36015.537 | AI32: =+'Consommations Q'!V34 -> 251.88207 | AJ32: =+AG32*AI32 -> 2770.7027
A33: noisette | B33: =+'Consommations Q'!B35 -> 216.77419 | C33: =+Données!$B$17 -> 11 | D33: =+B33*C33 -> 2384.5161 | E33: =+'Consommations Q'!D35 -> 18.064516 | F33: =+C33*E33 -> 198.70968 | G33: =+'Consommations Q'!E35 -> 242.51613 | H33: =+Données!$B$17 -> 11 | I33: =+G33*H33 -> 2667.6774 | J33: =+'Consommations Q'!G35 -> 18.704301 | K33: =+H33*J33 -> 205.74731 | L33: =+'Consommations Q'!H35 -> 278.89355 | M33: =+Données!$B$17 -> 11 | N33: =+L33*M33 -> 3067.829 | O33: =+'Consommations Q'!J35 -> 21.682437 | P33: =+M33*O33 -> 238.50681 | Q33: =+'Consommations Q'!K35 -> 320.72758 | R33: =+Données!$B$17 -> 11 | S33: =+Q33*R33 -> 3528.0034 | T33: =+'Consommations Q'!M35 -> 24.920429 | U33: =+R33*T33 -> 274.12471 | V33: =+'Consommations Q'!N35 -> 368.83672 | W33: =+Données!$B$17 -> 11 | X33: =+V33*W33 -> 4057.2039 | Y33: =+'Consommations Q'!P35 -> 28.659691 | Z33: =+W33*Y33 -> 315.2566 | AA33: =+'Consommations Q'!Q35 -> 367.29131 | AB33: =+Données!$B$17 -> 11 | AC33: =+AA33*AB33 -> 4040.2044 | AD33: =+'Consommations Q'!S35 -> 28.219302 | AE33: =+AB33*AD33 -> 310.41232 | AF33: =+'Consommations Q'!T35 -> 367.29131 | AG33: =+Données!$B$17 -> 11 | AH33: =+AF33*AG33 -> 4040.2044 | AI33: =+'Consommations Q'!V35 -> 28.256001 | AJ33: =+AG33*AI33 -> 310.81601
A34: pistche | B34: =+'Consommations Q'!B36 -> 216.77419 | C34: =+Données!$B$17 -> 11 | D34: =+B34*C34 -> 2384.5161 | E34: =+'Consommations Q'!D36 -> 18.064516 | F34: =+C34*E34 -> 198.70968 | G34: =+'Consommations Q'!E36 -> 242.51613 | H34: =+Données!$B$17 -> 11 | I34: =+G34*H34 -> 2667.6774 | J34: =+'Consommations Q'!G36 -> 18.704301 | K34: =+H34*J34 -> 205.74731 | L34: =+'Consommations Q'!H36 -> 278.89355 | M34: =+Données!$B$17 -> 11 | N34: =+L34*M34 -> 3067.829 | O34: =+'Consommations Q'!J36 -> 21.682437 | P34: =+M34*O34 -> 238.50681 | Q34: =+'Consommations Q'!K36 -> 320.72758 | R34: =+Données!$B$17 -> 11 | S34: =+Q34*R34 -> 3528.0034 | T34: =+'Consommations Q'!M36 -> 24.920429 | U34: =+R34*T34 -> 274.12471 | V34: =+'Consommations Q'!N36 -> 368.83672 | W34: =+Données!$B$17 -> 11 | X34: =+V34*W34 -> 4057.2039 | Y34: =+'Consommations Q'!P36 -> 28.659691 | Z34: =+W34*Y34 -> 315.2566 | AA34: =+'Consommations Q'!Q36 -> 367.29131 | AB34: =+Données!$B$17 -> 11 | AC34: =+AA34*AB34 -> 4040.2044 | AD34: =+'Consommations Q'!S36 -> 28.219302 | AE34: =+AB34*AD34 -> 310.41232 | AF34: =+'Consommations Q'!T36 -> 367.29131 | AG34: =+Données!$B$17 -> 11 | AH34: =+AF34*AG34 -> 4040.2044 | AI34: =+'Consommations Q'!V36 -> 28.256001 | AJ34: =+AG34*AI34 -> 310.81601
A35: acajou | B35: =+'Consommations Q'!B37 -> 216.77419 | C35: =+Données!$B$17 -> 11 | D35: =+B35*C35 -> 2384.5161 | E35: =+'Consommations Q'!D37 -> 18.064516 | F35: =+C35*E35 -> 198.70968 | G35: =+'Consommations Q'!E37 -> 242.51613 | H35: =+Données!$B$17 -> 11 | I35: =+G35*H35 -> 2667.6774 | J35: =+'Consommations Q'!G37 -> 18.704301 | K35: =+H35*J35 -> 205.74731 | L35: =+'Consommations Q'!H37 -> 278.89355 | M35: =+Données!$B$17 -> 11 | N35: =+L35*M35 -> 3067.829 | O35: =+'Consommations Q'!J37 -> 21.682437 | P35: =+M35*O35 -> 238.50681 | Q35: =+'Consommations Q'!K37 -> 320.72758 | R35: =+Données!$B$17 -> 11 | S35: =+Q35*R35 -> 3528.0034 | T35: =+'Consommations Q'!M37 -> 24.920429 | U35: =+R35*T35 -> 274.12471 | V35: =+'Consommations Q'!N37 -> 368.83672 | W35: =+Données!$B$17 -> 11 | X35: =+V35*W35 -> 4057.2039 | Y35: =+'Consommations Q'!P37 -> 28.659691 | Z35: =+W35*Y35 -> 315.2566 | AA35: =+'Consommations Q'!Q37 -> 367.29131 | AB35: =+Données!$B$17 -> 11 | AC35: =+AA35*AB35 -> 4040.2044 | AD35: =+'Consommations Q'!S37 -> 28.219302 | AE35: =+AB35*AD35 -> 310.41232 | AF35: =+'Consommations Q'!T37 -> 367.29131 | AG35: =+Données!$B$17 -> 11 | AH35: =+AF35*AG35 -> 4040.2044 | AI35: =+'Consommations Q'!V37 -> 28.256001 | AJ35: =+AG35*AI35 -> 310.81601
A36: Amande | B36: =+'Consommations Q'!B38 -> 216.77419 | C36: =+Données!$B$17 -> 11 | D36: =+B36*C36 -> 2384.5161 | E36: =+'Consommations Q'!D38 -> 18.064516 | F36: =+C36*E36 -> 198.70968 | G36: =+'Consommations Q'!E38 -> 242.51613 | H36: =+Données!$B$17 -> 11 | I36: =+G36*H36 -> 2667.6774 | J36: =+'Consommations Q'!G38 -> 18.704301 | K36: =+H36*J36 -> 205.74731 | L36: =+'Consommations Q'!H38 -> 278.89355 | M36: =+Données!$B$17 -> 11 | N36: =+L36*M36 -> 3067.829 | O36: =+'Consommations Q'!J38 -> 21.682437 | P36: =+M36*O36 -> 238.50681 | Q36: =+'Consommations Q'!K38 -> 320.72758 | R36: =+Données!$B$17 -> 11 | S36: =+Q36*R36 -> 3528.0034 | T36: =+'Consommations Q'!M38 -> 24.920429 | U36: =+R36*T36 -> 274.12471 | V36: =+'Consommations Q'!N38 -> 368.83672 | W36: =+Données!$B$17 -> 11 | X36: =+V36*W36 -> 4057.2039 | Y36: =+'Consommations Q'!P38 -> 28.659691 | Z36: =+W36*Y36 -> 315.2566 | AA36: =+'Consommations Q'!Q38 -> 367.29131 | AB36: =+Données!$B$17 -> 11 | AC36: =+AA36*AB36 -> 4040.2044 | AD36: =+'Consommations Q'!S38 -> 28.219302 | AE36: =+AB36*AD36 -> 310.41232 | AF36: =+'Consommations Q'!T38 -> 367.29131 | AG36: =+Données!$B$17 -> 11 | AH36: =+AF36*AG36 -> 4040.2044 | AI36: =+'Consommations Q'!V38 -> 28.256001 | AJ36: =+AG36*AI36 -> 310.81601
A37: Achat d'approvisionnement | B37: =SUM(B30:B36) -> 6664.2581 | D37: =SUM(D30:D36) -> 73306.839 | E37: =SUM(E30:E36) -> 555.35484 | F37: =SUM(F30:F36) -> 6108.9032 | G37: =SUM(G30:G36) -> 7455.6387 | I37: =SUM(I30:I36) -> 82012.026 | J37: =SUM(J30:J36) -> 575.02366 | K37: =SUM(K30:K36) -> 6325.2602 | L37: =SUM(L30:L36) -> 8573.9845 | N37: =SUM(N30:N36) -> 94313.83 | O37: =SUM(O30:O36) -> 666.58007 | P37: =SUM(P30:P36) -> 7332.3808 | Q37: =SUM(Q30:Q36) -> 9860.0822 | S37: =SUM(S30:S36) -> 108460.9 | T37: =SUM(T30:T36) -> 766.12518 | U37: =SUM(U30:U36) -> 8427.3769 | V37: =SUM(V30:V36) -> 11339.095 | X37: =SUM(X30:X36) -> 124730.04 | Y37: =SUM(Y30:Y36) -> 881.08078 | Z37: =SUM(Z30:Z36) -> 9691.8886 | AA37: =SUM(AA30:AA36) -> 11291.584 | AC37: =SUM(AC30:AC36) -> 124207.43 | AD37: =SUM(AD30:AD36) -> 867.54196 | AE37: =SUM(AE30:AE36) -> 9542.9616 | AF37: =SUM(AF30:AF36) -> 11291.584 | AH37: =SUM(AH30:AH36) -> 124207.43 | AI37: =SUM(AI30:AI36) -> 868.6702 | AJ37: =SUM(AJ30:AJ36) -> 9555.3722
I39: =+(I37-D37)/D37 -> 0.11875 | N39: =+(N37-I37)/I37 -> 0.15 | S39: =+(S37-N37)/N37 -> 0.15 | X39: =+(X37-S37)/S37 -> 0.15 | AC39: =+(AC37-X37)/X37 -> -0.0041899441 | AH39: =+(AH37-AC37)/AC37 -> 0
A42: Année | B42: Hypothèse retenue | C42: 2016 | D42: 2017 | E42: 2018 | F42: 2019 | G42: 2020 | H42: 2021 | I42: 2022
A43: Chiffre d'affaire | C43: =+'Chiffre d''affaire'!G10 -> 1935840 | D43: =+'Chiffre d''affaire'!L10/0.9 -> 2226216 | E43: =+'Chiffre d''affaire'!N10/0.9 -> 2560148.4 | F43: =+'Chiffre d''affaire'!P10/0.9 -> 2944170.7 | G43: =+'Chiffre d''affaire'!R10/0.9 -> 3385796.3 | H43: =+'Chiffre d''affaire'!T10/0.9 -> 3385796.3 | I43: =+'Chiffre d''affaire'!V10/0.9 -> 3385796.3
A44: Gaz | C44: =+C43*0.01 -> 19358.4 | D44: =+D43*0.01 -> 22262.16 | E44: =+E43*0.01 -> 25601.484 | F44: =+F43*0.01 -> 29441.707 | G44: =+G43*0.01 -> 33857.963 | H44: =+H43*0.01 -> 33857.963 | I44: =+I43*0.01 -> 33857.963
A45: Electricité | C45: =+C43*0.01 -> 19358.4 | D45: =+D43*0.01 -> 22262.16 | E45: =+E43*0.01 -> 25601.484 | F45: =+F43*0.01 -> 29441.707 | G45: =+G43*0.01 -> 33857.963 | H45: =+H43*0.01 -> 33857.963 | I45: =+I43*0.01 -> 33857.963
A46: Eau | C46: =+C43*0.005 -> 9679.2 | D46: =+D43*0.005 -> 11131.08 | E46: =+E43*0.005 -> 12800.742 | F46: =+F43*0.005 -> 14720.853 | G46: =+G43*0.005 -> 16928.981 | H46: =+H43*0.005 -> 16928.981 | I46: =+I43*0.005 -> 16928.981
C47: =SUM(C44:C46) -> 48396 | D47: =SUM(D44:D46) -> 55655.4 | E47: =SUM(E44:E46) -> 64003.71 | F47: =SUM(F44:F46) -> 73604.266 | G47: =SUM(G44:G46) -> 84644.906 | H47: =SUM(H44:H46) -> 84644.906 | I47: =SUM(I44:I46) -> 84644.906
D49: =+(D47-C47)/C47 -> 0.15 | E49: =+(E47-D47)/D47 -> 0.15 | F49: =+(F47-E47)/E47 -> 0.15 | G49: =+(G47-F47)/F47 -> 0.15 | H49: =+(H47-G47)/G47 -> 0 | I49: =+(I47-H47)/H47 -> 0
A52: Valeurs déchets | D52: 2016 | F52: 2017 | H52: 2018 | J52: 2019 | L52: 2020 | N52: 2021 | P52: 2022
B53: PU | C53: Prix uni*taux dechets | D53: QT produite | E53: Valeur dechets | F53: QT produite | G53: Valeur dechets | H53: QT produite | I53: Valeur dechets | J53: QT produite | K53: Valeur dechets | L53: QT produite | M53: Valeur dechets | N53: QT produite | O53: Valeur dechets | P53: QT produite | Q53: Valeur dechets
A54: MP MAIS | B54: =+Données!B28 -> 2.8 | C54: =+B54*0.01 -> 0.028 | D54: =+'Consommations Q'!C4 -> 38647.742 | E54: =+D54*$C54 -> 1082.1368 | F54: =+'Consommations Q'!H4 -> 43237.161 | G54: =+F54*$C54 -> 1210.6405 | H54: =+'Consommations Q'!M4 -> 49722.735 | I54: =+H54*$C54 -> 1392.2366 | J54: =+'Consommations Q'!R4 -> 57181.146 | K54: =+J54*$C54 -> 1601.0721 | L54: =+'Consommations Q'!W4 -> 65758.318 | M54: =+L54*$C54 -> 1841.2329 | N54: =+'Consommations Q'!AB4 -> 65482.794 | O54: =+N54*$C54 -> 1833.5182 | P54: =+'Consommations Q'!AG4 -> 65482.794 | Q54: =+P54*$C54 -> 1833.5182
A55: MP Cacahuète | B55: =+Données!B29 -> 5.1 | C55: =+B55*0.01 -> 0.051 | D55: =+'Consommations Q'!C5 -> 38647.742 | E55: =+D55*$C55 -> 1971.0348 | F55: =+'Consommations Q'!H5 -> 43237.161 | G55: =+F55*$C55 -> 2205.0952 | H55: =+'Consommations Q'!M5 -> 49722.735 | I55: =+H55*$C55 -> 2535.8595 | J55: =+'Consommations Q'!R5 -> 57181.146 | K55: =+J55*$C55 -> 2916.2384 | L55: =+'Consommations Q'!W5 -> 65758.318 | M55: =+L55*$C55 -> 3353.6742 | N55: =+'Consommations Q'!AB5 -> 65482.794 | O55: =+N55*$C55 -> 3339.6225 | P55: =+'Consommations Q'!AG5 -> 65482.794 | Q55: =+P55*$C55 -> 3339.6225
A56: Pois chiche | B56: =+Données!B30 -> 3.8 | C56: =+B56*0.01 -> 0.038 | D56: =+'Consommations Q'!C6 -> 38647.742 | E56: =+D56*$C56 -> 1468.6142 | F56: =+'Consommations Q'!H6 -> 43237.161 | G56: =+F56*$C56 -> 1643.0121 | H56: =+'Consommations Q'!M6 -> 49722.735 | I56: =+H56*$C56 -> 1889.4639 | J56: =+'Consommations Q'!R6 -> 57181.146 | K56: =+J56*$C56 -> 2172.8835 | L56: =+'Consommations Q'!W6 -> 65758.318 | M56: =+L56*$C56 -> 2498.8161 | N56: =+'Consommations Q'!AB6 -> 65482.794 | O56: =+N56*$C56 -> 2488.3462 | P56: =+'Consommations Q'!AG6 -> 65482.794 | Q56: =+P56*$C56 -> 2488.3462
A57: MP noisette | B57: =+Données!B34 -> 24 | C57: =+B57*0.01 -> 0.24 | D57: =+'Consommations Q'!C7 -> 4335.4839 | E57: =+D57*$C57 -> 1040.5161 | F57: =+'Consommations Q'!H7 -> 4850.3226 | G57: =+F57*$C57 -> 1164.0774 | H57: =+'Consommations Q'!M7 -> 5577.871 | I57: =+H57*$C57 -> 1338.689 | J57: =+'Consommations Q'!R7 -> 6414.5516 | K57: =+J57*$C57 -> 1539.4924 | L57: =+'Consommations Q'!W7 -> 7376.7344 | M57: =+L57*$C57 -> 1770.4162 | N57: =+'Consommations Q'!AB7 -> 7345.8262 | O57: =+N57*$C57 -> 1762.9983 | P57: =+'Consommations Q'!AG7 -> 7345.8262 | Q57: =+P57*$C57 -> 1762.9983
A58: MP pistche | B58: =+Données!B33 -> 24 | C58: =+B58*0.01 -> 0.24 | D58: =+'Consommations Q'!C8 -> 4335.4839 | E58: =+D58*$C58 -> 1040.5161 | F58: =+'Consommations Q'!H8 -> 4850.3226 | G58: =+F58*$C58 -> 1164.0774 | H58: =+'Consommations Q'!M8 -> 5577.871 | I58: =+H58*$C58 -> 1338.689 | J58: =+'Consommations Q'!R8 -> 6414.5516 | K58: =+J58*$C58 -> 1539.4924 | L58: =+'Consommations Q'!W8 -> 7376.7344 | M58: =+L58*$C58 -> 1770.4162 | N58: =+'Consommations Q'!AB8 -> 7345.8262 | O58: =+N58*$C58 -> 1762.9983 | P58: =+'Consommations Q'!AG8 -> 7345.8262 | Q58: =+P58*$C58 -> 1762.9983
A59: MP acajou | B59: =+Données!B32 -> 22 | C59: =+B59*0.01 -> 0.22 | D59: =+'Consommations Q'!C9 -> 4335.4839 | E59: =+D59*$C59 -> 953.80645 | F59: =+'Consommations Q'!H9 -> 4850.3226 | G59: =+F59*$C59 -> 1067.071 | H59: =+'Consommations Q'!M9 -> 5577.871 | I59: =+H59*$C59 -> 1227.1316 | J59: =+'Consommations Q'!R9 -> 6414.5516 | K59: =+J59*$C59 -> 1411.2014 | L59: =+'Consommations Q'!W9 -> 7376.7344 | M59: =+L59*$C59 -> 1622.8816 | N59: =+'Consommations Q'!AB9 -> 7345.8262 | O59: =+N59*$C59 -> 1616.0818 | P59: =+'Consommations Q'!AG9 -> 7345.8262 | Q59: =+P59*$C59 -> 1616.0818
A60: MP Amande | B60: =+Données!B31 -> 25 | C60: =+B60*0.01 -> 0.25 | D60: =+'Consommations Q'!C10 -> 4335.4839 | E60: =+D60*$C60 -> 1083.871 | F60: =+'Consommations Q'!H10 -> 4850.3226 | G60: =+F60*$C60 -> 1212.5806 | H60: =+'Consommations Q'!M10 -> 5577.871 | I60: =+H60*$C60 -> 1394.4677 | J60: =+'Consommations Q'!R10 -> 6414.5516 | K60: =+J60*$C60 -> 1603.6379 | L60: =+'Consommations Q'!W10 -> 7376.7344 | M60: =+L60*$C60 -> 1844.1836 | N60: =+'Consommations Q'!AB10 -> 7345.8262 | O60: =+N60*$C60 -> 1836.4566 | P60: =+'Consommations Q'!AG10 -> 7345.8262 | Q60: =+P60*$C60 -> 1836.4566
A61: Total | D61: =SUM(D54:D60) -> 133285.16 | E61: =SUM(E54:E60) -> 8640.4955 | F61: =SUM(F54:F60) -> 149112.77 | G61: =SUM(G54:G60) -> 9666.5543 | H61: =SUM(H54:H60) -> 171479.69 | I61: =SUM(I54:I60) -> 11116.537 | J61: =SUM(J54:J60) -> 197201.64 | K61: =SUM(K54:K60) -> 12784.018 | ... Q61: =SUM(Q54:Q60) -> 14640.022
F63: =+(F61-D61)/D61 -> 0.11875 | H63: =+(H61-F61)/F61 -> 0.15 | J63: =+(J61-H61)/H61 -> 0.15 | L63: =+(L61-J61)/J61 -> 0.15 | N63: =+(N61-L61)/L61 -> -0.0041899441 | P63: =+(P61-N61)/N61 -> 0
B70: 2016 | C70: 2017 | D70: 2018 | E70: 2019 | F70: 2020 | G70: 2021 | H70: 2022
A71: Consommations
A72: MP | B72: =+(D10-F10) -> 872690.04 | C72: =+I10+F10-K10 -> 976321.99 | D72: =+N10+K10-P10 -> 1122770.3 | E72: =+S10+P10-U10 -> 1291185.8 | F72: =+X10+U10-Z10 -> 1484863.7 | G72: =+AC10+Z10-AE10 -> 1478642.2 | H72: =+AH10+AE10-AJ10 -> 1478642.2
A74: Aromes | B74: =+D24 -> 177399.88 | C74: =+I24 -> 198466.12 | D74: =+N24 -> 228236.04 | E74: =+S24 -> 262471.44 | F74: =+X24 -> 301842.16 | G74: =+AC24 -> 300577.46 | H74: =+AH24 -> 300577.46
A75: emballage | B75: =+D37 -> 73306.839 | C75: =+I37 -> 82012.026 | D75: =+N37 -> 94313.83 | E75: =+S37 -> 108460.9 | F75: =+X37 -> 124730.04 | G75: =+AC37 -> 124207.43 | H75: =+AH37 -> 124207.43
A76: Autres approv | B76: =+C47 -> 48396 | C76: =+D47 -> 55655.4 | D76: =+E47 -> 64003.71 | E76: =+F47 -> 73604.266 | F76: =+G47 -> 84644.906 | G76: =+H47 -> 84644.906 | H76: =+I47 -> 84644.906
A77: Total consommation | B77: =SUM(B72:B76) -> 1171792.8 | C77: =SUM(C72:C76) -> 1312455.5 | D77: =SUM(D72:D76) -> 1509323.9 | E77: =SUM(E72:E76) -> 1735722.4 | F77: =SUM(F72:F76) -> 1996080.8 | G77: =SUM(G72:G76) -> 1988072 | H77: =SUM(H72:H76) -> 1988072
C78: =+(C72-B72)/B72 -> 0.11875 | D78: =+(D72-C72)/C72 -> 0.15 | E78: =+(E72-D72)/D72 -> 0.15 | F78: =+(F72-E72)/E72 -> 0.15 | G78: =+(G72-F72)/F72 -> -0.0041899441 | H78: =+(H72-G72)/G72 -> 0
C79: =+(C74-B74)/B74 -> 0.11875 | D79: =+(D74-C74)/C74 -> 0.15 | E79: =+(E74-D74)/D74 -> 0.15 | F79: =+(F74-E74)/E74 -> 0.15 | G79: =+(G74-F74)/F74 -> -0.0041899441 | H79: =+(H74-G74)/G74 -> 0
C80: =+(C75-B75)/B75 -> 0.11875 | D80: =+(D75-C75)/C75 -> 0.15 | E80: =+(E75-D75)/D75 -> 0.15 | F80: =+(F75-E75)/E75 -> 0.15 | G80: =+(G75-F75)/F75 -> -0.0041899441 | H80: =+(H75-G75)/G75 -> 0
C81: =+(C76-B76)/B76 -> 0.15 | D81: =+(D76-C76)/C76 -> 0.15 | E81: =+(E76-D76)/D76 -> 0.15 | F81: =+(F76-E76)/E76 -> 0.15 | G81: =+(G76-F76)/F76 -> 0 | H81: =+(H76-G76)/G76 -> 0
A83: Achats consommés | B83: 2016 | C83: 2017 | D83: 2018 | E83: 2019 | F83: 2020 | G83: 2021 | H83: 2022
A84: Mais | B84: =+D3-F3-'Cout de production prévisionnel'!E3 -> 102184.14 | C84: =+I3+F3-K3+'Cout de production prévisionnel'!E3-'Cout de production prévisionnel'!I3 -> 121207.94 | D84: =+N3+K3-P3+'Cout de production prévisionnel'!I3-'Cout de production prévisionnel'!M3 -> 139389.13 | E84: =+S3+P3-U3+'Cout de production prévisionnel'!M3-'Cout de production prévisionnel'!Q3 -> 160297.5 | F84: =+X3+U3-Z3+'Cout de production prévisionnel'!Q3-'Cout de production prévisionnel'!U3 -> 184342.13 | G84: =+AC3+Z3-AE3+'Cout de production prévisionnel'!U3-'Cout de production prévisionnel'!Y3 -> 185185.34 | H84: =+AH3+AE3-AJ3+'Cout de production prévisionnel'!Y3-'Cout de production prévisionnel'!AC3 -> 185185.34
A85: Cacahuète | B85: =+D4-F4-'Cout de production prévisionnel'!E4 -> 189036.49 | C85: =+I4+F4-K4+'Cout de production prévisionnel'!E4-'Cout de production prévisionnel'!I4 -> 221208.91 | D85: =+N4+K4-P4+'Cout de production prévisionnel'!I4-'Cout de production prévisionnel'!M4 -> 254390.25 | E85: =+S4+P4-U4+'Cout de production prévisionnel'!M4-'Cout de production prévisionnel'!Q4 -> 292548.79 | F85: =+X4+U4-Z4+'Cout de production prévisionnel'!Q4-'Cout de production prévisionnel'!U4 -> 336431.11 | G85: =+AC4+Z4-AE4+'Cout de production prévisionnel'!U4-'Cout de production prévisionnel'!Y4 -> 337301.87 | H85: =+AH4+AE4-AJ4+'Cout de production prévisionnel'!Y4-'Cout de production prévisionnel'!AC4 -> 337301.87
A86: Pois chiche | B86: =+D5-F5-'Cout de production prévisionnel'!E5 -> 139938.16 | C86: =+I5+F5-K5+'Cout de production prévisionnel'!E5-'Cout de production prévisionnel'!I5 -> 164685.44 | D86: =+N5+K5-P5+'Cout de production prévisionnel'!I5-'Cout de production prévisionnel'!M5 -> 189388.26 | E86: =+S5+P5-U5+'Cout de production prévisionnel'!M5-'Cout de production prévisionnel'!Q5 -> 217796.5 | F86: =+X5+U5-Z5+'Cout de production prévisionnel'!Q5-'Cout de production prévisionnel'!U5 -> 250465.97 | G86: =+AC5+Z5-AE5+'Cout de production prévisionnel'!U5-'Cout de production prévisionnel'!Y5 -> 251322.96 | H86: =+AH5+AE5-AJ5+'Cout de production prévisionnel'!Y5-'Cout de production prévisionnel'!AC5 -> 251322.96
A87: Noisette | B87: =+D6-F6-'Cout de production prévisionnel'!E6 -> 101308.69 | C87: =+I6+F6-K6+'Cout de production prévisionnel'!E6-'Cout de production prévisionnel'!I6 -> 117004.3 | D87: =+N6+K6-P6+'Cout de production prévisionnel'!I6-'Cout de production prévisionnel'!M6 -> 134554.95 | E87: =+S6+P6-U6+'Cout de production prévisionnel'!M6-'Cout de production prévisionnel'!Q6 -> 154738.19 | F87: =+X6+U6-Z6+'Cout de production prévisionnel'!Q6-'Cout de production prévisionnel'!U6 -> 177948.92 | G87: =+AC6+Z6-AE6+'Cout de production prévisionnel'!U6-'Cout de production prévisionnel'!Y6 -> 178062.83 | H87: =+AH6+AE6-AJ6+'Cout de production prévisionnel'!Y6-'Cout de production prévisionnel'!AC6 -> 178062.83
A88: Pistche | B88: =+D7-F7-'Cout de production prévisionnel'!E7 -> 101308.69 | C88: =+I7+F7-K7+'Cout de production prévisionnel'!E7-'Cout de production prévisionnel'!I7 -> 117004.3 | D88: =+N7+K7-P7+'Cout de production prévisionnel'!I7-'Cout de production prévisionnel'!M7 -> 134554.95 | E88: =+S7+P7-U7+'Cout de production prévisionnel'!M7-'Cout de production prévisionnel'!Q7 -> 154738.19 | F88: =+X7+U7-Z7+'Cout de production prévisionnel'!Q7-'Cout de production prévisionnel'!U7 -> 177948.92 | G88: =+AC7+Z7-AE7+'Cout de production prévisionnel'!U7-'Cout de production prévisionnel'!Y7 -> 178062.83 | H88: =+AH7+AE7-AJ7+'Cout de production prévisionnel'!Y7-'Cout de production prévisionnel'!AC7 -> 178062.83
A89: Noix de Cajou | B89: =+D8-F8-'Cout de production prévisionnel'!E8 -> 92824.688 | C89: =+I8+F8-K8+'Cout de production prévisionnel'!E8-'Cout de production prévisionnel'!I8 -> 107247.7 | D89: =+N8+K8-P8+'Cout de production prévisionnel'!I8-'Cout de production prévisionnel'!M8 -> 123334.86 | E89: =+S8+P8-U8+'Cout de production prévisionnel'!M8-'Cout de production prévisionnel'!Q8 -> 141835.09 | F89: =+X8+U8-Z8+'Cout de production prévisionnel'!Q8-'Cout de production prévisionnel'!U8 -> 163110.35 | G89: =+AC8+Z8-AE8+'Cout de production prévisionnel'!U8-'Cout de production prévisionnel'!Y8 -> 163224.26 | H89: =+AH8+AE8-AJ8+'Cout de production prévisionnel'!Y8-'Cout de production prévisionnel'!AC8 -> 163224.26
A90: Amande | B90: =+D9-F9-'Cout de production prévisionnel'!E9 -> 105550.69 | C90: =+I9+F9-K9+'Cout de production prévisionnel'!E9-'Cout de production prévisionnel'!I9 -> 121882.6 | D90: =+N9+K9-P9+'Cout de production prévisionnel'!I9-'Cout de production prévisionnel'!M9 -> 140164.99 | E90: =+S9+P9-U9+'Cout de production prévisionnel'!M9-'Cout de production prévisionnel'!Q9 -> 161189.74 | F90: =+X9+U9-Z9+'Cout de production prévisionnel'!Q9-'Cout de production prévisionnel'!U9 -> 185368.2 | G90: =+AC9+Z9-AE9+'Cout de production prévisionnel'!U9-'Cout de production prévisionnel'!Y9 -> 185482.11 | H90: =+AH9+AE9-AJ9+'Cout de production prévisionnel'!Y9-'Cout de production prévisionnel'!AC9 -> 185482.11
A91: Sous-Total consommation matières | B91: =SUM(B84:B90) -> 832151.54 | C91: =SUM(C84:C90) -> 970241.21 | D91: =SUM(D84:D90) -> 1115777.4 | E91: =SUM(E84:E90) -> 1283144 | F91: =SUM(F84:F90) -> 1475615.6 | G91: =SUM(G84:G90) -> 1478642.2 | H91: =SUM(H84:H90) -> 1478642.2
A92: Arômes | B92: =+D24 -> 177399.88 | C92: =+I24 -> 198466.12 | D92: =+N24 -> 228236.04 | E92: =+S24 -> 262471.44 | F92: =+X24 -> 301842.16 | G92: =+AC24 -> 300577.46 | H92: =+AH24 -> 300577.46
A93: Emballages | B93: =+D37 -> 73306.839 | C93: =+I37 -> 82012.026 | D93: =+N37 -> 94313.83 | E93: =+S37 -> 108460.9 | F93: =+X37 -> 124730.04 | G93: =+AC37 -> 124207.43 | H93: =+AH37 -> 124207.43
A94: Energies | B94: =+C47 -> 48396 | C94: =+D47 -> 55655.4 | D94: =+E47 -> 64003.71 | E94: =+F47 -> 73604.266 | F94: =+G47 -> 84644.906 | G94: =+H47 -> 84644.906 | H94: =+I47 -> 84644.906
A95: Sous-Total consommation autres approvisionnements | B95: =SUM(B92:B94) -> 299102.72 | C95: =SUM(C92:C94) -> 336133.55 | D95: =SUM(D92:D94) -> 386553.58 | E95: =SUM(E92:E94) -> 444536.61 | F95: =SUM(F92:F94) -> 511217.11 | G95: =SUM(G92:G94) -> 509429.79 | H95: =SUM(H92:H94) -> 509429.79
A97: Total achats consommés | B97: =+B95+B91 -> 1131254.3 | C97: =+C95+C91 -> 1306374.8 | D97: =+D95+D91 -> 1502331 | E97: =+E95+E91 -> 1727680.6 | F97: =+F95+F91 -> 1986832.7 | G97: =+G95+G91 -> 1988072 | H97: =+H95+H91 -> 1988072
B98: =+B97+'P&L'!C19+'P&L'!C18 -> 7.2759576e-11 | C98: =+C97+'P&L'!E19+'P&L'!E18 -> -1.0913936e-10 | D98: =+D97+'P&L'!G19+'P&L'!G18 -> 2.9831426e-10 | E98: =+E97+'P&L'!I19+'P&L'!I18 -> 3.2741809e-10 | F98: =+F97+'P&L'!K19+'P&L'!K18 -> -2.6921043e-10 | G98: =+G97+'P&L'!M19+'P&L'!M18 -> -2.3283064e-10 | H98: =+H97+'P&L'!O19+'P&L'!O18 -> -2.3283064e-10

Sheet Achat Matière
B2: QT achetée | C2: PU | D2: Total Achat | E2: QT st Final | F2: Valeur St Final | G2: Taux de déchets | H2: Valeurs déchets | I2: Valeur SF net dechets
A3: MP MAIS | B3: =+'Calcul Coût Ption'!B2/12*13+'Calcul Coût Ption'!B2*'Achat Matière'!G3 -> 42254.865 | C3: =+Données!B28 -> 2.8 | D3: =+B3*C3 -> 118313.62 | E3: =+B3-'Calcul Coût Ption'!B2 -> 3607.1226 | F3: =+C3*E3 -> 10099.943 | G3: 0.01 | H3: =+'Calcul Coût Ption'!B2*'Achat Matière'!G3*C3 -> 1082.1368 | I3: =+F3-H3 -> 9017.8065
A4: MP Cacahuète | B4: =+'Calcul Coût Ption'!B3/12*13+'Calcul Coût Ption'!B3*'Achat Matière'!G4 -> 42254.865 | C4: =+Données!B29 -> 5.1 | D4: =+B4*C4 -> 215499.81 | E4: =+B4-'Calcul Coût Ption'!B3 -> 3607.1226 | F4: =+C4*E4 -> 18396.325 | G4: 0.01 | H4: =+'Calcul Coût Ption'!B3*'Achat Matière'!G4*C4 -> 1971.0348 | I4: =+F4-H4 -> 16425.29
A5: Pois chiche | B5: =+'Calcul Coût Ption'!B4/12*13+'Calcul Coût Ption'!B4*'Achat Matière'!G5 -> 42254.865 | C5: =+Données!B30 -> 3.8 | D5: =+B5*C5 -> 160568.49 | E5: =+B5-'Calcul Coût Ption'!B4 -> 3607.1226 | F5: =+C5*E5 -> 13707.066 | G5: 0.01 | H5: =+'Calcul Coût Ption'!B4*'Achat Matière'!G5*C5 -> 1468.6142 | I5: =+F5-H5 -> 12238.452
A6: MP noisette | B6: =+'Calcul Coût Ption'!B5/12*13+'Calcul Coût Ption'!B5*'Achat Matière'!G6 -> 4740.129 | C6: =+Données!B34 -> 24 | D6: =+B6*C6 -> 113763.1 | E6: =+B6-'Calcul Coût Ption'!B5 -> 404.64516 | F6: =+C6*E6 -> 9711.4839 | G6: 0.01 | H6: =+'Calcul Coût Ption'!B5*'Achat Matière'!G6*C6 -> 1040.5161 | I6: =+F6-H6 -> 8670.9677
A7: MP pistche | B7: =+'Calcul Coût Ption'!B6/12*13+'Calcul Coût Ption'!B6*'Achat Matière'!G7 -> 4740.129 | C7: =+Données!B33 -> 24 | D7: =+B7*C7 -> 113763.1 | E7: =+B7-'Calcul Coût Ption'!B6 -> 404.64516 | F7: =+C7*E7 -> 9711.4839 | G7: 0.01 | H7: =+'Calcul Coût Ption'!B6*'Achat Matière'!G7*C7 -> 1040.5161 | I7: =+F7-H7 -> 8670.9677
A8: MP acajou | B8: =+'Calcul Coût Ption'!B7/12*13+'Calcul Coût Ption'!B7*'Achat Matière'!G8 -> 4740.129 | C8: =+Données!B32 -> 22 | D8: =+B8*C8 -> 104282.84 | E8: =+B8-'Calcul Coût Ption'!B7 -> 404.64516 | F8: =+C8*E8 -> 8902.1935 | G8: 0.01 | H8: =+'Calcul Coût Ption'!B7*'Achat Matière'!G8*C8 -> 953.80645 | I8: =+F8-H8 -> 7948.3871
A9: MP Amande | B9: =+'Calcul Coût Ption'!B8/12*13+'Calcul Coût Ption'!B8*'Achat Matière'!G9 -> 4740.129 | C9: =+Données!B31 -> 25 | D9: =+B9*C9 -> 118503.23 | E9: =+B9-'Calcul Coût Ption'!B8 -> 404.64516 | F9: =+C9*E9 -> 10116.129 | G9: 0.01 | H9: =+'Calcul Coût Ption'!B8*'Achat Matière'!G9*C9 -> 1083.871 | I9: =+F9-H9 -> 9032.2581
A10: Total | B10: =SUM(B3:B9) -> 145725.11 | D10: =SUM(D3:D9) -> 944694.17 | E10: =SUM(E3:E9) -> 12439.948 | F10: =SUM(F3:F9) -> 80644.625 | H10: =SUM(H3:H9) -> 8640.4955 | I10: =SUM(I3:I9) -> 72004.129 | K10: =+D10-F10 -> 864049.55
B12: Aromes | E12: Emballages | H12: Gaz | I12: Electricité | J12: Eau | K12: Total
B13: QT | C13: PU | D13: Valeurs | E13: QT | F13: PU | G13: Valeurs
A14: MAIS | B14: =+('Calcul Coût Ption'!B2*60/1000)/12*13 -> 2512.1032 | C14: =+Données!$B$35 -> 22.183 | D14: =+B14*C14 -> 55725.986 | E14: =+('Calcul Coût Ption'!B2*0.05)/12*13 -> 2093.4194 | F14: =+Données!$B$17 -> 11 | G14: =+E14*F14 -> 23027.613 | H14: =+'Chiffre d''affaire'!G3*0.04 -> 14976 | I14: =+'Chiffre d''affaire'!G3*0.02 -> 7488 | J14: =+'Chiffre d''affaire'!G3*0.01 -> 3744 | K14: =+D14+G14+H14+I14+J14 -> 104961.6
A15: Cacahuète | B15: =+('Calcul Coût Ption'!B3*60/1000)/12*13 -> 2512.1032 | C15: =+Données!$B$35 -> 22.183 | D15: =+B15*C15 -> 55725.986 | E15: =+('Calcul Coût Ption'!B3*0.05)/12*13 -> 2093.4194 | F15: =+Données!$B$17 -> 11 | G15: =+E15*F15 -> 23027.613 | H15: =+'Chiffre d''affaire'!G4*0.04 -> 20966.4 | I15: =+'Chiffre d''affaire'!G4*0.02 -> 10483.2 | J15: =+'Chiffre d''affaire'!G4*0.01 -> 5241.6 | K15: =+D15+G15+H15+I15+J15 -> 115444.8
A16: Pois chiche | B16: =+('Calcul Coût Ption'!B4*60/1000)/12*13 -> 2512.1032 | C16: =+Données!$B$35 -> 22.183 | D16: =+B16*C16 -> 55725.986 | E16: =+('Calcul Coût Ption'!B4*0.05)/12*13 -> 2093.4194 | F16: =+Données!$B$17 -> 11 | G16: =+E16*F16 -> 23027.613 | H16: =+'Chiffre d''affaire'!G5*0.04 -> 17971.2 | I16: =+'Chiffre d''affaire'!G5*0.02 -> 8985.6 | J16: =+'Chiffre d''affaire'!G5*0.01 -> 4492.8 | K16: =+D16+G16+H16+I16+J16 -> 110203.2
A17: noisette | B17: =+('Calcul Coût Ption'!B5*60/1000)/12*13 -> 281.80645 | C17: =+Données!$B$35 -> 22.183 | D17: =+B17*C17 -> 6251.3125 | E17: =+('Calcul Coût Ption'!B5*0.05)/12*13 -> 234.83871 | F17: =+Données!$B$17 -> 11 | G17: =+E17*F17 -> 2583.2258 | H17: =+'Chiffre d''affaire'!G6*0.04 -> 5880 | I17: =+'Chiffre d''affaire'!G6*0.02 -> 2940 | J17: =+'Chiffre d''affaire'!G6*0.01 -> 1470 | K17: =+D17+G17+H17+I17+J17 -> 19124.538
A18: pistche | B18: =+('Calcul Coût Ption'!B6*60/1000)/12*13 -> 281.80645 | C18: =+Données!$B$35 -> 22.183 | D18: =+B18*C18 -> 6251.3125 | E18: =+('Calcul Coût Ption'!B6*0.05)/12*13 -> 234.83871 | F18: =+Données!$B$17 -> 11 | G18: =+E18*F18 -> 2583.2258 | H18: =+'Chiffre d''affaire'!G7*0.04 -> 5880 | I18: =+'Chiffre d''affaire'!G7*0.02 -> 2940 | J18: =+'Chiffre d''affaire'!G7*0.01 -> 1470 | K18: =+D18+G18+H18+I18+J18 -> 19124.538
A19: acajou | B19: =+('Calcul Coût Ption'!B7*60/1000)/12*13 -> 281.80645 | C19: =+Données!$B$35 -> 22.183 | D19: =+B19*C19 -> 6251.3125 | E19: =+('Calcul Coût Ption'!B7*0.05)/12*13 -> 234.83871 | F19: =+Données!$B$17 -> 11 | G19: =+E19*F19 -> 2583.2258 | H19: =+'Chiffre d''affaire'!G8*0.04 -> 5880 | I19: =+'Chiffre d''affaire'!G8*0.02 -> 2940 | J19: =+'Chiffre d''affaire'!G8*0.01 -> 1470 | K19: =+D19+G19+H19+I19+J19 -> 19124.538
A20: Amande | B20: =+('Calcul Coût Ption'!B8*60/1000)/12*13 -> 281.80645 | C20: =+Données!$B$35 -> 22.183 | D20: =+B20*C20 -> 6251.3125 | E20: =+('Calcul Coût Ption'!B8*0.05)/12*13 -> 234.83871 | F20: =+Données!$B$17 -> 11 | G20: =+E20*F20 -> 2583.2258 | H20: =+'Chiffre d''affaire'!G9*0.04 -> 5880 | I20: =+'Chiffre d''affaire'!G9*0.02 -> 2940 | J20: =+'Chiffre d''affaire'!G9*0.01 -> 1470 | K20: =+D20+G20+H20+I20+J20 -> 19124.538
A21: Achat d'approvisionnement | B21: =SUM(B14:B20) -> 8663.5355 | D21: =SUM(D14:D20) -> 192183.21 | E21: =SUM(E14:E20) -> 7219.6129 | G21: =SUM(G14:G20) -> 79415.742 | H21: =SUM(H14:H20) -> 77433.6 | I21: =SUM(I14:I20) -> 38716.8 | J21: =SUM(J14:J20) -> 19358.4 | K21: =SUM(K14:K20) -> 407107.75
B24: Aromes | E24: Emballages
B25: QT St Final | C25: PU | D25: Valeurs St Final | E25: QT St Final | F25: PU | G25: Valeurs St Final
A26: MAIS | B26: =+B14/13 -> 193.23871 | C26: =+Données!$B$35 -> 22.183 | D26: =+B26*C26 -> 4286.6143 | E26: =+E14/13 -> 161.03226 | F26: =+'[22]marge brut'!$D$16 -> 8.9 | G26: =+E26*F26 -> 1433.1871
A27: Cacahuète | B27: =+B15/13 -> 193.23871 | C27: =+Données!$B$35 -> 22.183 | D27: =+B27*C27 -> 4286.6143 | E27: =+E15/13 -> 161.03226 | F27: =+'[22]marge brut'!$D$16 -> 8.9 | G27: =+E27*F27 -> 1433.1871
A28: Pois chiche | B28: =+B16/13 -> 193.23871 | C28: =+Données!$B$35 -> 22.183 | D28: =+B28*C28 -> 4286.6143 | E28: =+E16/13 -> 161.03226 | F28: =+'[22]marge brut'!$D$16 -> 8.9 | G28: =+E28*F28 -> 1433.1871
A29: noisette | B29: =+B17/13 -> 21.677419 | C29: =+Données!$B$35 -> 22.183 | D29: =+B29*C29 -> 480.87019 | E29: =+E17/13 -> 18.064516 | F29: =+'[22]marge brut'!$D$16 -> 8.9 | G29: =+E29*F29 -> 160.77419
A30: pistche | B30: =+B18/13 -> 21.677419 | C30: =+Données!$B$35 -> 22.183 | D30: =+B30*C30 -> 480.87019 | E30: =+E18/13 -> 18.064516 | F30: =+'[22]marge brut'!$D$16 -> 8.9 | G30: =+E30*F30 -> 160.77419
A31: acajou | B31: =+B19/13 -> 21.677419 | C31: =+Données!$B$35 -> 22.183 | D31: =+B31*C31 -> 480.87019 | E31: =+E19/13 -> 18.064516 | F31: =+'[22]marge brut'!$D$16 -> 8.9 | G31: =+E31*F31 -> 160.77419
A32: Amande | B32: =+B20/13 -> 21.677419 | C32: =+Données!$B$35 -> 22.183 | D32: =+B32*C32 -> 480.87019 | E32: =+E20/13 -> 18.064516 | F32: =+'[22]marge brut'!$D$16 -> 8.9 | G32: =+E32*F32 -> 160.77419
A33: Achat d'approvisionnement | B33: =SUM(B26:B32) -> 666.42581 | D33: =SUM(D26:D32) -> 14783.324 | E33: =SUM(E26:E32) -> 555.35484 | G33: =SUM(G26:G32) -> 4942.6581

Sheet TVA
B1: 2016 | E1: 2017 | H1: 2018 | K1: 2019 | N1: 2020
B2: HT | C2: TVA | D2: TTC | E2: HT | F2: TVA | G2: TTC | H2: HT | I2: TVA | J2: TTC | K2: HT | L2: TVA | M2: TTC | N2: HT | O2: TVA | P2: TTC
A3: Vente | B3: =+'Chiffre d''affaire'!I10 -> 1742256 | C3: =+B3*0.06 -> 104535.36 | D3: =+B3+C3 -> 1846791.4 | E3: =+'Chiffre d''affaire'!L10 -> 2003594.4 | F3: =+E3*0.06 -> 120215.66 | G3: =+E3+F3 -> 2123810.1 | H3: =+'Chiffre d''affaire'!N10 -> 2304133.6 | I3: =+H3*0.06 -> 138248.01 | J3: =+H3+I3 -> 2442381.6 | K3: =+'Chiffre d''affaire'!P10 -> 2649753.6 | L3: =+K3*0.06 -> 158985.22 | M3: =+K3+L3 -> 2808738.8 | N3: =+'Chiffre d''affaire'!R10 -> 3047216.6 | O3: =+N3*0.06 -> 182833 | P3: =+N3+O3 -> 3230049.6
A4: Achat MP | B4: =SUM(B5:B6) -> 945414.21 | C4: =SUM(C5:C6) -> -155966.1 | D4: =SUM(D5:D6) -> 1101380.3 | E4: =SUM(E5:E6) -> 978897.63 | F4: =SUM(F5:F6) -> -161489.9 | G4: =SUM(G5:G6) -> 1140387.5 | H4: =SUM(H5:H6) -> 1134759.7 | I4: =SUM(I5:I6) -> -187202.65 | ... P4: =SUM(P5:P6) -> 1747360.4
A5: Mais | B5: =+'Ach prévisionnel'!D3 -> 118403.8 | C5: =+(B5*0.06)*-1 -> -7104.2279 | D5: =+B5-C5 -> 125508.03 | E5: =+'Ach prévisionnel'!I3 -> 122597.27 | F5: =+(E5*0.06)*-1 -> -7355.836 | G5: =+E5-F5 -> 129953.1 | H5: =+'Ach prévisionnel'!N3 -> 142117.45 | I5: =+(H5*0.06)*-1 -> -8527.0469 | J5: =+H5-I5 -> 150644.5 | K5: =+'Ach prévisionnel'!S3 -> 163340.85 | L5: =+(K5*0.06)*-1 -> -9800.451 | M5: =+K5-L5 -> 173141.3 | N5: =+'Ach prévisionnel'!X3 -> 187849.83 | O5: =+(N5*0.06)*-1 -> -11270.99 | P5: =+N5-O5 -> 199120.82
A6: Autres | B6: =+SUM('Ach prévisionnel'!D4:D9) -> 827010.42 | C6: =+(B6*0.18)*-1 -> -148861.87 | D6: =+B6-C6 -> 975872.29 | E6: =+SUM('Ach prévisionnel'!I4:I9) -> 856300.37 | F6: =+(E6*0.18)*-1 -> -154134.07 | G6: =+E6-F6 -> 1010434.4 | H6: =+SUM('Ach prévisionnel'!N4:N9) -> 992642.22 | I6: =+(H6*0.18)*-1 -> -178675.6 | J6: =+H6-I6 -> 1171317.8 | K6: =+SUM('Ach prévisionnel'!S4:S9) -> 1140880.5 | L6: =+(K6*0.18)*-1 -> -205358.49 | M6: =+K6-L6 -> 1346239 | N6: =+SUM('Ach prévisionnel'!X4:X9) -> 1312067.4 | O6: =+(N6*0.18)*-1 -> -236172.13 | P6: =+N6-O6 -> 1548239.5
A7: Achat emballage | B7: =+'Consommations Q'!C39*Données!B17 -> 79415.742 | C7: =+(B7*0.18)*-1 -> -14294.834 | D7: =+B7-C7 -> 93710.575 | E7: =+'Ach prévisionnel'!I37 -> 82012.026 | F7: =+(E7*0.18)*-1 -> -14762.165 | G7: =+E7-F7 -> 96774.19 | H7: =+'Ach prévisionnel'!N37 -> 94313.83 | I7: =+(H7*0.18)*-1 -> -16976.489 | J7: =+H7-I7 -> 111290.32 | K7: =+'Ach prévisionnel'!S37 -> 108460.9 | L7: =+(K7*0.18)*-1 -> -19522.963 | M7: =+K7-L7 -> 127983.87 | N7: =+'Ach prévisionnel'!X37 -> 124730.04 | O7: =+(N7*0.18)*-1 -> -22451.407 | P7: =+N7-O7 -> 147181.45
A8: Achat Aromes | B8: =+'Consommations Q'!C26*Données!B35 -> 192183.21 | C8: =+(B8*0.18)*-1 -> -34592.977 | D8: =+B8-C8 -> 226776.19 | E8: =+'Ach prévisionnel'!I24 -> 198466.12 | F8: =+(E8*0.18)*-1 -> -35723.902 | G8: =+E8-F8 -> 234190.02 | H8: =+'Ach prévisionnel'!N24 -> 228236.04 | I8: =+(H8*0.18)*-1 -> -41082.487 | J8: =+H8-I8 -> 269318.53 | K8: =+'Ach prévisionnel'!S24 -> 262471.44 | L8: =+(K8*0.18)*-1 -> -47244.86 | M8: =+K8-L8 -> 309716.3 | N8: =+'Ach prévisionnel'!X24 -> 301842.16 | O8: =+(N8*0.18)*-1 -> -54331.589 | P8: =+N8-O8 -> 356173.75
A9: Consommables | B9: =+'Ach prévisionnel'!C47 -> 48396 | C9: =+(B9*0.18)*-1 -> -8711.28 | D9: =+B9-C9 -> 57107.28 | E9: =+'Ach prévisionnel'!D47 -> 55655.4 | F9: =+(E9*0.18)*-1 -> -10017.972 | G9: =+E9-F9 -> 65673.372 | H9: =+'Ach prévisionnel'!E47 -> 64003.71 | I9: =+(H9*0.18)*-1 -> -11520.668 | J9: =+H9-I9 -> 75524.378 | K9: =+'Ach prévisionnel'!F47 -> 73604.266 | L9: =+(K9*0.18)*-1 -> -13248.768 | M9: =+K9-L9 -> 86853.034 | N9: =+'Ach prévisionnel'!G47 -> 84644.906 | O9: =+(N9*0.18)*-1 -> -15236.083 | P9: =+N9-O9 -> 99880.99
A10: Achat Cartons | B10: =+'Achat carton'!F10 -> 21520 | C10: =+(B10*0.18)*-1 -> -3873.6 | D10: =+B10-C10 -> 25393.6 | E10: =+'Achat carton'!H10 -> 24748 | F10: =+(E10*0.18)*-1 -> -4454.64 | G10: =+E10-F10 -> 29202.64 | H10: =+'Achat carton'!J10 -> 28460.2 | I10: =+(H10*0.18)*-1 -> -5122.836 | J10: =+H10-I10 -> 33583.036 | K10: =+'Achat carton'!L10 -> 32729.23 | L10: =+(K10*0.18)*-1 -> -5891.2614 | M10: =+K10-L10 -> 38620.491 | N10: =+'Achat carton'!N10 -> 37638.614 | O10: =+(N10*0.18)*-1 -> -6774.9506 | P10: =+N10-O10 -> 44413.565
A11: Autres charges d'exploitation | B11: =+'Autres charges'!C16 -> 208679.5 | C11: =-'Autres charges'!J16 -> -31689.561 | D11: =+B11-C11 -> 240369.06 | E11: =+'Autres charges'!D16 -> 232216.25 | F11: =+(E11*0.18)*-1 -> -41798.926 | G11: =+E11-F11 -> 274015.18 | H11: =+'Autres charges'!E16 -> 259022.94 | I11: =+(H11*0.18)*-1 -> -46624.129 | J11: =+H11-I11 -> 305647.07 | K11: =+'Autres charges'!F16 -> 289863.04 | L11: =+(K11*0.18)*-1 -> -52175.346 | M11: =+K11-L11 -> 342038.38 | N11: =+'Autres charges'!G16 -> 324730.65 | O11: =+(N11*0.18)*-1 -> -58451.517 | P11: =+N11-O11 -> 383182.17
A12: Investissements | B12: =SUM(B13:B14) -> 389067.9 | C12: =SUM(C13:C14) -> -39587.094 | D12: =SUM(D13:D14) -> 428654.99 | F12: =SUM(F13:F14) -> 0 | G12: =SUM(G13:G14) -> 0 | I12: =SUM(I13:I14) -> 0 | J12: =SUM(J13:J14) -> 0 | L12: =SUM(L13:L14) -> 0 | M12: =SUM(M13:M14) -> 0 | O12: =SUM(O13:O14) -> 0 | P12: =SUM(P13:P14) -> 0
A13: Equipements importés | B13: =+Investissements!B6 -> 253709.4 | C13: =+(B13*0.06)*-1 -> -15222.564 | D13: =+B13-C13 -> 268931.96 | F13: =+(E13*0.06)*-1 -> 0 | G13: =+E13-F13 -> 0 | I13: =+(H13*0.06)*-1 -> 0 | J13: =+H13-I13 -> 0 | L13: =+(K13*0.06)*-1 -> 0 | M13: =+K13-L13 -> 0 | O13: =+(N13*0.06)*-1 -> 0 | P13: =+N13-O13 -> 0
A14: Autres équipements | B14: =+Investissements!B5+Investissements!B7+Investissements!B8 -> 135358.5 | C14: =+(B14*0.18)*-1 -> -24364.53 | D14: =+B14-C14 -> 159723.03 | F14: =+(E14*0.18)*-1 -> 0 | G14: =+E14-F14 -> 0 | I14: =+(H14*0.18)*-1 -> 0 | J14: =+H14-I14 -> 0 | L14: =+(K14*0.18)*-1 -> 0 | M14: =+K14-L14 -> 0 | O14: =+(N14*0.18)*-1 -> 0 | P14: =+N14-O14 -> 0
A15: Frais préliminaires | B15: =+Investissements!B10 -> 20500 | C15: =+(B15*0.18)*-1 -> -3690 | D15: =+B15-C15 -> 24190 | F15: =+(E15*0.18)*-1 -> 0 | G15: =+E15-F15 -> 0 | I15: =+(H15*0.18)*-1 -> 0 | J15: =+H15-I15 -> 0 | L15: =+(K15*0.18)*-1 -> 0 | M15: =+K15-L15 -> 0 | O15: =+(N15*0.18)*-1 -> 0 | P15: =+N15-O15 -> 0
A18: Solde de TVA | C18: =+C3+(C4+C7+C8++C9+C10+C12+C15+C11) -> -187870.09 | F18: =+F3+(F4+F7+F8++F9+F10+F12+F15+F11) -> -148031.84 | I18: =+I3+(I4+I7+I8++I9+I10+I12+I15+I11) -> -170281.24 | L18: =+L3+(L4+L7+L8++L9+L10+L12+L15+L11) -> -194256.92 | O18: =+O3+(O4+O7+O8++O9+O10+O12+O15+O11) -> -221855.67
A21: Achat fournisseurs | B21: solde fournisseurs 1 mois des achats
A22: =SUM(D4:D10) -> 2605748.3 | B22: =+A22/13 -> 200442.17

Sheet Achat carton
B1: 2016 | G1: 2017 | I1: 2018 | K1: 2019 | M1: 2020 | O1: 2021 | Q1: 2022
A2: Désignation de la rubrique | B2: QT produites en Kg | C2: QT - sachet | D2: Qt carton ( en Pcs) | E2: Prix Unit carton | F2: Montant des achats cartons | G2: QT produites en Kg | H2: Montant des achats cartons | I2: QT produites en Kg | J2: Montant des achats cartons | K2: QT produites en Kg | L2: Montant des achats cartons | M2: QT produites en Kg | N2: Montant des achats cartons | O2: QT produites en Kg | P2: Montant des achats cartons | Q2: QT produites en Kg | R2: Montant des achats cartons
A3: PF Mais | B3: =+'Chiffre d''affaire'!F3 -> 37440 | C3: =+B3*10 -> 374400 | D3: =+C3/36 -> 10400 | E3: =+Données!$B$20 -> 0.6 | F3: =+D3*E3 -> 6240 | G3: =+'Chiffre d''affaire'!K3/36 -> 11960 | H3: =+G3*$E$3 -> 7176 | I3: =+'Chiffre d''affaire'!M3/36 -> 13754 | J3: =+I3*$E$3 -> 8252.4 | K3: =+'Chiffre d''affaire'!O3/36 -> 15817.1 | L3: =+K3*$E$3 -> 9490.26 | M3: =+'Chiffre d''affaire'!Q3/36 -> 18189.665 | N3: =+M3*$E$3 -> 10913.799 | O3: =+'Chiffre d''affaire'!S3/36 -> 18189.665 | P3: =+O3*$E$3 -> 10913.799 | Q3: =+'Chiffre d''affaire'!U3/36 -> 18189.665 | R3: =+Q3*$E$3 -> 10913.799
A4: PF Cacahuète | B4: =+'Chiffre d''affaire'!F4 -> 37440 | C4: =+B4*10 -> 374400 | D4: =+C4/36 -> 10400 | E4: =+Données!$B$20 -> 0.6 | F4: =+D4*E4 -> 6240 | G4: =+'Chiffre d''affaire'!K4/36 -> 11960 | H4: =+G4*$E$3 -> 7176 | I4: =+'Chiffre d''affaire'!M4/36 -> 13754 | J4: =+I4*$E$3 -> 8252.4 | K4: =+'Chiffre d''affaire'!O4/36 -> 15817.1 | L4: =+K4*$E$3 -> 9490.26 | M4: =+'Chiffre d''affaire'!Q4/36 -> 18189.665 | N4: =+M4*$E$3 -> 10913.799 | O4: =+'Chiffre d''affaire'!S4/36 -> 18189.665 | P4: =+O4*$E$3 -> 10913.799 | Q4: =+'Chiffre d''affaire'!U4/36 -> 18189.665 | R4: =+Q4*$E$3 -> 10913.799
A5: PF Pois chiche | B5: =+'Chiffre d''affaire'!F5 -> 37440 | C5: =+B5*10 -> 374400 | D5: =+C5/36 -> 10400 | E5: =+Données!$B$20 -> 0.6 | F5: =+D5*E5 -> 6240 | G5: =+'Chiffre d''affaire'!K5/36 -> 11960 | H5: =+G5*$E$3 -> 7176 | I5: =+'Chiffre d''affaire'!M5/36 -> 13754 | J5: =+I5*$E$3 -> 8252.4 | K5: =+'Chiffre d''affaire'!O5/36 -> 15817.1 | L5: =+K5*$E$3 -> 9490.26 | M5: =+'Chiffre d''affaire'!Q5/36 -> 18189.665 | N5: =+M5*$E$3 -> 10913.799 | O5: =+'Chiffre d''affaire'!S5/36 -> 18189.665 | P5: =+O5*$E$3 -> 10913.799 | Q5: =+'Chiffre d''affaire'!U5/36 -> 18189.665 | R5: =+Q5*$E$3 -> 10913.799
A6: PF noisette | B6: =+'Chiffre d''affaire'!F6 -> 4200 | C6: =+B6*10 -> 42000 | D6: =+C6/36 -> 1166.6667 | E6: =+Données!$B$20 -> 0.6 | F6: =+D6*E6 -> 700 | G6: =+'Chiffre d''affaire'!K6/36 -> 1341.6667 | H6: =+G6*$E$3 -> 805 | I6: =+'Chiffre d''affaire'!M6/36 -> 1542.9167 | J6: =+I6*$E$3 -> 925.75 | K6: =+'Chiffre d''affaire'!O6/36 -> 1774.3542 | L6: =+K6*$E$3 -> 1064.6125 | M6: =+'Chiffre d''affaire'!Q6/36 -> 2040.5073 | N6: =+M6*$E$3 -> 1224.3044 | O6: =+'Chiffre d''affaire'!S6/36 -> 2040.5073 | P6: =+O6*$E$3 -> 1224.3044 | Q6: =+'Chiffre d''affaire'!U6/36 -> 2040.5073 | R6: =+Q6*$E$3 -> 1224.3044
A7: PF pistche | B7: =+'Chiffre d''affaire'!F7 -> 4200 | C7: =+B7*10 -> 42000 | D7: =+C7/36 -> 1166.6667 | E7: =+Données!$B$20 -> 0.6 | F7: =+D7*E7 -> 700 | G7: =+'Chiffre d''affaire'!K7/36 -> 1341.6667 | H7: =+G7*$E$3 -> 805 | I7: =+'Chiffre d''affaire'!M7/36 -> 1542.9167 | J7: =+I7*$E$3 -> 925.75 | K7: =+'Chiffre d''affaire'!O7/36 -> 1774.3542 | L7: =+K7*$E$3 -> 1064.6125 | M7: =+'Chiffre d''affaire'!Q7/36 -> 2040.5073 | N7: =+M7*$E$3 -> 1224.3044 | O7: =+'Chiffre d''affaire'!S7/36 -> 2040.5073 | P7: =+O7*$E$3 -> 1224.3044 | Q7: =+'Chiffre d''affaire'!U7/36 -> 2040.5073 | R7: =+Q7*$E$3 -> 1224.3044
A8: PF acajou | B8: =+'Chiffre d''affaire'!F8 -> 4200 | C8: =+B8*10 -> 42000 | D8: =+C8/36 -> 1166.6667 | E8: =+Données!$B$20 -> 0.6 | F8: =+D8*E8 -> 700 | G8: =+'Chiffre d''affaire'!K8/36 -> 1341.6667 | H8: =+G8*$E$3 -> 805 | I8: =+'Chiffre d''affaire'!M8/36 -> 1542.9167 | J8: =+I8*$E$3 -> 925.75 | K8: =+'Chiffre d''affaire'!O8/36 -> 1774.3542 | L8: =+K8*$E$3 -> 1064.6125 | M8: =+'Chiffre d''affaire'!Q8/36 -> 2040.5073 | N8: =+M8*$E$3 -> 1224.3044 | O8: =+'Chiffre d''affaire'!S8/36 -> 2040.5073 | P8: =+O8*$E$3 -> 1224.3044 | Q8: =+'Chiffre d''affaire'!U8/36 -> 2040.5073 | R8: =+Q8*$E$3 -> 1224.3044
A9: PF Amande | B9: =+'Chiffre d''affaire'!F9 -> 4200 | C9: =+B9*10 -> 42000 | D9: =+C9/36 -> 1166.6667 | E9: =+Données!$B$20 -> 0.6 | F9: =+D9*E9 -> 700 | G9: =+'Chiffre d''affaire'!K9/36 -> 1341.6667 | H9: =+G9*$E$3 -> 805 | I9: =+'Chiffre d''affaire'!M9/36 -> 1542.9167 | J9: =+I9*$E$3 -> 925.75 | K9: =+'Chiffre d''affaire'!O9/36 -> 1774.3542 | L9: =+K9*$E$3 -> 1064.6125 | M9: =+'Chiffre d''affaire'!Q9/36 -> 2040.5073 | N9: =+M9*$E$3 -> 1224.3044 | O9: =+'Chiffre d''affaire'!S9/36 -> 2040.5073 | P9: =+O9*$E$3 -> 1224.3044 | Q9: =+'Chiffre d''affaire'!U9/36 -> 2040.5073 | R9: =+Q9*$E$3 -> 1224.3044
B10: =SUM(B3:B9) -> 129120 | C10: =SUM(C3:C9) -> 1291200 | D10: =SUM(D3:D9) -> 35866.667 | E10: =SUM(E3:E9) -> 4.2 | F10: =SUM(F3:F9) -> 21520 | G10: =SUM(G3:G9) -> 41246.667 | H10: =SUM(H3:H9) -> 24748 | I10: =SUM(I3:I9) -> 47433.667 | ... R10: =SUM(R3:R9) -> 37638.614
H12: =+(H10-F10)/F10 -> 0.15 | J12: =+(J10-H10)/H10 -> 0.15 | L12: =+(L10-J10)/J10 -> 0.15 | N12: =+(N10-L10)/L10 -> 0.15 | P12: =+(P10-N10)/N10 -> 0 | R12: =+(R10-P10)/P10 -> 0

Sheet Autres charges
A2: Année | B2: Hypothèse retenue | C2: 2016 | D2: 2017 | E2: 2018 | F2: 2019 | G2: 2020 | H2: 2021 | I2: 2022 | J2: TVA
A3: Chiffre d'affaire | C3: =+'Ach prévisionnel'!C43 -> 1935840 | D3: =+'Ach prévisionnel'!D43 -> 2226216 | E3: =+'Ach prévisionnel'!E43 -> 2560148.4 | F3: =+'Ach prévisionnel'!F43 -> 2944170.7 | G3: =+'Ach prévisionnel'!G43 -> 3385796.3 | H3: =+'Ach prévisionnel'!H43 -> 3385796.3 | I3: =+'Ach prévisionnel'!I43 -> 3385796.3
A4: Frais de maintenance et d'entretien, lubrifiant | B4: 4% du cout d'invest | C4: =+(Investissements!$C$23+Investissements!$C$29)*4% -> 15902.716 | D4: =+(Investissements!$C$23+Investissements!$C$29)*4% -> 15902.716 | E4: =+(Investissements!$C$23+Investissements!$C$29)*4% -> 15902.716 | F4: =+(Investissements!$C$23+Investissements!$C$29)*4% -> 15902.716 | G4: =+(Investissements!$C$23+Investissements!$C$29)*4% -> 15902.716 | H4: =+(Investissements!$C$23+Investissements!$C$29)*4% -> 15902.716 | I4: =+(Investissements!$C$23+Investissements!$C$29)*4% -> 15902.716 | J4: =+C4*0.18 -> 2862.4889
A5: Frais de gestion courantes (poste/Telecommunication) | B5: 0,5% du chiffre d'affaire | C5: =+C3*0.005 -> 9679.2 | D5: =+D3*0.005 -> 11131.08 | E5: =+E3*0.005 -> 12800.742 | F5: =+F3*0.005 -> 14720.853 | G5: =+G3*0.005 -> 16928.981 | H5: =+H3*0.005 -> 16928.981 | I5: =+I3*0.005 -> 16928.981 | J5: =+C5*0.18 -> 1742.256
A6: Transport sur vente | B6: 3% du chiffre d'affaire | C6: =+C3*0.03 -> 58075.2 | D6: =+D3*0.03 -> 66786.48 | E6: =+E3*0.03 -> 76804.452 | F6: =+F3*0.03 -> 88325.12 | G6: =+G3*0.03 -> 101573.89 | H6: =+H3*0.03 -> 101573.89 | I6: =+I3*0.03 -> 101573.89 | J6: =+C6*0.12 -> 6969.024
A7: Dépenses publicitaire | B7: 3,5% du chiffre d'affaire | C7: =+C3*3.5% -> 67754.4 | D7: =+D3*3.5% -> 77917.56 | E7: =+E3*3.5% -> 89605.194 | F7: =+F3*3.5% -> 103045.97 | G7: =+G3*3.5% -> 118502.87 | H7: =+H3*3.5% -> 118502.87 | I7: =+I3*3.5% -> 118502.87 | J7: =+C7*0.18 -> 12195.792
A8: Loyer | B8: Augmentation 5% | C8: 25000 | D8: =+C8*1.05 -> 26250 | E8: =+D8*1.05 -> 27562.5 | F8: =+E8*1.05 -> 28940.625 | G8: =+F8*1.05 -> 30387.656 | H8: =+G8*1.05 -> 31907.039 | I8: =+H8*1.05 -> 33502.391 | J8: =+C8*0.18 -> 4500
A9: Honoraires (Audit, avocat etc) | B9: Forfait + augm de 5% | C9: 6000 | D9: =+C9*1.05 -> 6300 | E9: =+D9*1.05 -> 6615 | F9: =+E9*1.05 -> 6945.75 | G9: =+F9*1.05 -> 7293.0375 | H9: =+G9*1.05 -> 7657.6894 | I9: =+H9*1.05 -> 8040.5738 | J9: =+C9*0.12 -> 720
A10: Voyages et déplacement | B10: Forfait + augm de 5% | C10: 15000 | D10: =+C10*1.05 -> 15750 | E10: =+D10*1.05 -> 16537.5 | F10: =+E10*1.05 -> 17364.375 | G10: =+F10*1.05 -> 18232.594 | H10: =+G10*1.05 -> 19144.223 | I10: =+H10*1.05 -> 20101.435 | J10: =+C10*0.18 -> 2700
A12: Assurance (0,11% du chiffre d'affaire) | B12: Forfait + augm de 3% | C12: 4500 | D12: =+C12*1.03 -> 4635 | E12: =+D12*1.03 -> 4774.05 | F12: =+E12*1.03 -> 4917.2715 | G12: =+F12*1.03 -> 5064.7896 | H12: =+G12*1.03 -> 5216.7333 | I12: =+H12*1.03 -> 5373.2353
A13: TFP | C13: =+SALAIRE!C17*1% -> 1332 | D13: =+SALAIRE!D17*1% -> 1411.92 | E13: =+SALAIRE!E17*1% -> 1496.6352 | F13: =+SALAIRE!F17*1% -> 1729.3552 | G13: =+SALAIRE!G17*1% -> 1833.1165 | H13: =+SALAIRE!H17*1% -> 1833.1165 | I13: =+SALAIRE!I17*1% -> 1833.1165
A14: FOPROLOS | C14: =+C13 -> 1332 | D14: =+D13 -> 1411.92 | E14: =+E13 -> 1496.6352 | F14: =+F13 -> 1729.3552 | G14: =+G13 -> 1833.1165 | H14: =+H13 -> 1833.1165 | I14: =+I13 -> 1833.1165
A15: TCL | C15: =+C3*1.06*0.2% -> 4103.9808 | D15: =+D3*1.06*0.2% -> 4719.5779 | E15: =+E3*1.06*0.2% -> 5427.5146 | F15: =+F3*1.06*0.2% -> 6241.6418 | G15: =+G3*1.06*0.2% -> 7177.8881 | H15: =+H3*1.06*0.2% -> 7177.8881 | I15: =+I3*1.06*0.2% -> 7177.8881
A16: Total | C16: =SUM(C4:C15) -> 208679.5 | D16: =SUM(D4:D15) -> 232216.25 | E16: =SUM(E4:E15) -> 259022.94 | F16: =SUM(F4:F15) -> 289863.04 | G16: =SUM(G4:G15) -> 324730.65 | H16: =SUM(H4:H15) -> 327678.26 | I16: =SUM(I4:I15) -> 330770.21 | J16: =SUM(J4:J15) -> 31689.561
D18: =+(D16-C16)/C16 -> 0.11278903 | E18: =+(E16-D16)/D16 -> 0.11543845 | F18: =+(F16-E16)/E16 -> 0.11906319 | G18: =+(G16-F16)/F16 -> 0.12028997 | H18: =+(H16-G16)/G16 -> 0.009077086 | I18: =+(I16-H16)/H16 -> 0.0094359314
A19: Exonération de la TFP -FOPROLOS pendant 5 ans LF 2012
A22: Autres charges d'exploitation | B22: 2016 | C22: 2017 | D22: 2018 | E22: 2019 | F22: 2020 | G22: 2021 | H22: 2022
A23: Frais de marketing | B23: =+C7 -> 67754.4 | C23: =+D7 -> 77917.56 | D23: =+E7 -> 89605.194 | E23: =+F7 -> 103045.97 | F23: =+G7 -> 118502.87 | G23: =+H7 -> 118502.87 | H23: =+I7 -> 118502.87
A24: Transport sur vente | B24: =+C6 -> 58075.2 | C24: =+D6 -> 66786.48 | D24: =+E6 -> 76804.452 | E24: =+F6 -> 88325.12 | F24: =+G6 -> 101573.89 | G24: =+H6 -> 101573.89 | H24: =+I6 -> 101573.89
A25: Charges locatives | B25: =+C8 -> 25000 | C25: =+D8 -> 26250 | D25: =+E8 -> 27562.5 | E25: =+F8 -> 28940.625 | F25: =+G8 -> 30387.656 | G25: =+H8 -> 31907.039 | H25: =+I8 -> 33502.391
A26: Achat Cartons | B26: =+'Achat carton'!F10 -> 21520 | C26: =+'Achat carton'!H10 -> 24748 | D26: =+'Achat carton'!J10 -> 28460.2 | E26: =+'Achat carton'!L10 -> 32729.23 | F26: =+'Achat carton'!N10 -> 37638.614 | G26: =+'Achat carton'!O10 -> 62731.024 | H26: =+'Achat carton'!P10 -> 37638.614
A27: Frais de maintenance | B27: =+C4 -> 15902.716 | C27: =+D4 -> 15902.716 | D27: =+E4 -> 15902.716 | E27: =+F4 -> 15902.716 | F27: =+G4 -> 15902.716 | G27: =+H4 -> 15902.716 | H27: =+I4 -> 15902.716
A28: Voyages et déplacement | B28: =+C10 -> 15000 | C28: =+D10 -> 15750 | D28: =+E10 -> 16537.5 | E28: =+F10 -> 17364.375 | F28: =+G10 -> 18232.594 | G28: =+H10 -> 19144.223 | H28: =+I10 -> 20101.435
A29: Honoraires | B29: =+C9 -> 6000 | C29: =+D9 -> 6300 | D29: =+E9 -> 6615 | E29: =+F9 -> 6945.75 | F29: =+G9 -> 7293.0375 | G29: =+H9 -> 7657.6894 | H29: =+I9 -> 8040.5738
A30: TCL | B30: =+C15 -> 4103.9808 | C30: =+D15 -> 4719.5779 | D30: =+E15 -> 5427.5146 | E30: =+F15 -> 6241.6418 | F30: =+G15 -> 7177.8881 | G30: =+H15 -> 7177.8881 | H30: =+I15 -> 7177.8881
A31: Autres taxes | B31: =+C13+C14 -> 2664 | C31: =+D13+D14 -> 2823.84 | D31: =+E13+E14 -> 2993.2704 | E31: =+F13+F14 -> 3458.7105 | F31: =+G13+G14 -> 3666.2331 | G31: =+H13+H14 -> 3666.2331 | H31: =+I13+I14 -> 3666.2331
A32: Assurances | B32: =+C12 -> 4500 | C32: =+D12 -> 4635 | D32: =+E12 -> 4774.05 | E32: =+F12 -> 4917.2715 | F32: =+G12 -> 5064.7896 | G32: =+H12 -> 5216.7333 | H32: =+I12 -> 5373.2353
A33: Divers frais de gestion | B33: =+C5 -> 9679.2 | C33: =+D5 -> 11131.08 | D33: =+E5 -> 12800.742 | E33: =+F5 -> 14720.853 | F33: =+G5 -> 16928.981 | G33: =+H5 -> 16928.981 | H33: =+I5 -> 16928.981
A34: Total autres charges d'exploitation | B34: =SUM(B23:B33) -> 230199.5 | C34: =SUM(C23:C33) -> 256964.25 | D34: =SUM(D23:D33) -> 287483.14 | E34: =SUM(E23:E33) -> 322592.27 | F34: =SUM(F23:F33) -> 362369.27 | G34: =SUM(G23:G33) -> 390409.28 | H34: =SUM(H23:H33) -> 368408.82
B35: =+B34-C16-'Achat carton'!F10 -> 2.910383e-11 | C35: =+C34-D16-'Achat carton'!H10 -> 0 | D35: =+D34-E16-'Achat carton'!J10 -> 0 | E35: =+E34-F16-'Achat carton'!L10 -> 0 | F35: =+F34-G16-'Achat carton'!N10 -> -7.2759576e-11 | G35: =+G34-H16-'Achat carton'!O10 -> 0 | H35: =+H34-I16-'Achat carton'!P10 -> 0
A38: Désignation | B38: 2016 | C38: 2017 | D38: 2018 | E38: 2019 | F38: 2020 | G38: 2021 | H38: 2022
A39: Chiffre d'affaire | B39: =+C3 -> 1935840 | C39: =+D3 -> 2226216 | D39: =+E3 -> 2560148.4 | E39: =+F3 -> 2944170.7 | F39: =+G3 -> 3385796.3 | G39: =+H3 -> 3385796.3 | H39: =+I3 -> 3385796.3
A40: Transport sur vente | B40: =+B39*3% -> 58075.2 | C40: =+C39*3% -> 66786.48 | D40: =+D39*3% -> 76804.452 | E40: =+E39*3% -> 88325.12 | F40: =+F39*3% -> 101573.89 | G40: =+G39*3% -> 101573.89 | H40: =+H39*3% -> 101573.89
A42: Désignation | B42: 2016 | C42: 2017 | D42: 2018 | E42: 2019 | F42: 2020 | G42: 2021 | H42: 2022
A43: Cout des équipements | B43: =+Investissements!C29+Investissements!C23 -> 397567.9 | C43: =+B43 -> 397567.9 | D43: =+C43 -> 397567.9 | E43: =+D43 -> 397567.9 | F43: =+E43 -> 397567.9 | G43: =+F43 -> 397567.9 | H43: =+G43 -> 397567.9
A44: Frais d'entretien | B44: =+B43*0.04 -> 15902.716 | C44: =+C43*0.04 -> 15902.716 | D44: =+D43*0.04 -> 15902.716 | E44: =+E43*0.04 -> 15902.716 | F44: =+F43*0.04 -> 15902.716 | G44: =+G43*0.04 -> 15902.716 | H44: =+H43*0.04 -> 15902.716
A47: Désignation | B47: Hypothèse retenue
A48: Frais de maintenance et d'entretien, lubrifiant | B48: 4% du cout d'invest
A49: Frais de gestion courantes (poste/Telecommunication) | B49: 0,5% du chiffre d'affaire
A50: Transport sur vente | B50: 3% du chiffre d'affaire
A51: Dépenses publicitaire | B51: 3,5% du chiffre d'affaire
A52: Loyer | B52: Augmentation 5%
A53: Honoraires (Audit, avocat etc) | B53: Forfait + augm de 5%
A54: Voyages et déplacement | B54: Forfait + augm de 5%
A56: Assurance | B56: Forfait + augm de 3%
A57: TFP
A58: FOPROLOS
A59: TCL
A64: Autres charges d'exploitation | B64: 2016
A65: Voyages et déplacement | B65: 15000 | C65: Forfait+ Augmentation annuelle de 5%
A66: Honoraires | B66: 6000 | C66: Forfait+ Augmentation annuelle de 5%
A67: TCL | B67: 4104 | C67: 1% du chiffre d'affaires TTC
A68: Autres taxes | B68: 2664 | C68: TFP et FOPROLOS
A69: Assurances | B69: 4500 | C69: Forfait+ Augmentation annuele de 3%
A70: Divers frais de gestion | B70: 9679 | C70: 0,5% du chiffre d'affaires
A71: Total | B71: =SUM(B65:B70) -> 41947

Sheet SALAIRE
A2: Fonction | C2: Qualification | E2: 2016 | H2: 2017 | K2: 2018 | N2: 2019 | Q2: 2020 | T2: 2021 | W2: 2022
D3: Salaire brut | E3: Effectif | F3: Masse salariale | G3: % | H3: Effectif | I3: Masse salariale | J3: % | K3: Effectif | L3: Masse salariale | M3: % | N3: Effectif | O3: Masse salariale | P3: % | Q3: Effectif | R3: Masse salariale | S3: % | T3: Effectif | U3: Masse salariale | V3: % | W3: Effectif | X3: Masse salariale | Y3: %
A4: Gérant | B4: Non imputable | C4: Expérience exigée | D4: 2000 | E4: 1 | F4: =+D4*E4*12 -> 24000 | G4: =+F4/$F$12 -> 0.18018018 | H4: =+E4 -> 1 | I4: =+D4*1.06*H4*12 -> 25440 | J4: =+I4/$I$12 -> 0.18018018 | K4: =+E4 -> 1 | L4: =+D4*1.06*1.06*K4*12 -> 26966.4 | M4: =+L4/$L$12 -> 0.18018018 | N4: =+E4 -> 1 | O4: =+D4*1.06*1.06*1.06*N4*12 -> 28584.384 | P4: =+O4/$O$12 -> 0.16528926 | Q4: =+H4 -> 1 | R4: =+D4*1.06*1.06*1.06*1.06*Q4*12 -> 30299.447 | S4: =+R4/$R$12 -> 0.16528926 | T4: =+K4 -> 1 | U4: =+D4*1.06*1.06*1.06*1.06*T4*12 -> 30299.447 | V4: =+U4/$R$12 -> 0.16528926 | W4: =+N4 -> 1 | X4: =+D4*1.06*1.06*1.06*1.06*W4*12 -> 30299.447 | Y4: =+X4/$R$12 -> 0.16528926
A5: Responsables Commerciaux | B5: Imputable | D5: 1000 | E5: 2 | F5: =+D5*E5*12 -> 24000 | G5: =+F5/$F$12 -> 0.18018018 | H5: =+E5 -> 2 | I5: =+D5*1.06*H5*12 -> 25440 | J5: =+I5/$I$12 -> 0.18018018 | K5: =+E5 -> 2 | L5: =+D5*1.06*1.06*K5*12 -> 26966.4 | M5: =+L5/$L$12 -> 0.18018018 | N5: =+E5 -> 2 | O5: =+D5*1.06*1.06*1.06*N5*12 -> 28584.384 | P5: =+O5/$O$12 -> 0.16528926 | Q5: =+H5 -> 2 | R5: =+D5*1.06*1.06*1.06*1.06*Q5*12 -> 30299.447 | S5: =+R5/$R$12 -> 0.16528926 | T5: =+K5 -> 2 | U5: =+D5*1.06*1.06*1.06*1.06*T5*12 -> 30299.447 | V5: =+U5/$R$12 -> 0.16528926 | W5: =+N5 -> 2 | X5: =+D5*1.06*1.06*1.06*1.06*W5*12 -> 30299.447 | Y5: =+X5/$R$12 -> 0.16528926
A6: Directeur financier | B6: Non imputable | C6: Expérience exigée | D6: 1000 | E6: 1 | F6: =+D6*E6*12 -> 12000 | G6: =+F6/$F$12 -> 0.09009009 | H6: =+E6 -> 1 | I6: =+D6*1.06*H6*12 -> 12720 | J6: =+I6/$I$12 -> 0.09009009 | K6: =+E6 -> 1 | L6: =+D6*1.06*1.06*K6*12 -> 13483.2 | M6: =+L6/$L$12 -> 0.09009009 | N6: =+E6 -> 1 | O6: =+D6*1.06*1.06*1.06*N6*12 -> 14292.192 | P6: =+O6/$O$12 -> 0.082644628 | Q6: =+H6 -> 1 | R6: =+D6*1.06*1.06*1.06*1.06*Q6*12 -> 15149.724 | S6: =+R6/$R$12 -> 0.082644628 | T6: =+K6 -> 1 | U6: =+D6*1.06*1.06*1.06*1.06*T6*12 -> 15149.724 | V6: =+U6/$R$12 -> 0.082644628 | W6: =+N6 -> 1 | X6: =+D6*1.06*1.06*1.06*1.06*W6*12 -> 15149.724 | Y6: =+X6/$R$12 -> 0.082644628
A7: Administratif | B7: Non imputable | D7: 700 | E7: 1 | F7: =+D7*E7*12 -> 8400 | G7: =+F7/$F$12 -> 0.063063063 | H7: =+E7 -> 1 | I7: =+D7*1.06*H7*12 -> 8904 | J7: =+I7/$I$12 -> 0.063063063 | K7: =+E7 -> 1 | L7: =+D7*1.06*1.06*K7*12 -> 9438.24 | M7: =+L7/$L$12 -> 0.063063063 | N7: =+E7 -> 1 | O7: =+D7*1.06*1.06*1.06*N7*12 -> 10004.534 | P7: =+O7/$O$12 -> 0.05785124 | Q7: =+H7 -> 1 | R7: =+D7*1.06*1.06*1.06*1.06*Q7*12 -> 10604.806 | S7: =+R7/$R$12 -> 0.05785124 | T7: =+K7 -> 1 | U7: =+D7*1.06*1.06*1.06*1.06*T7*12 -> 10604.806 | V7: =+U7/$R$12 -> 0.05785124 | W7: =+N7 -> 1 | X7: =+D7*1.06*1.06*1.06*1.06*W7*12 -> 10604.806 | Y7: =+X7/$R$12 -> 0.05785124
A8: Gardien | B8: Non imputable | D8: 500 | E8: 1 | F8: =+D8*E8*12 -> 6000 | G8: =+F8/$F$12 -> 0.045045045 | H8: =+E8 -> 1 | I8: =+D8*1.06*H8*12 -> 6360 | J8: =+I8/$I$12 -> 0.045045045 | K8: =+E8 -> 1 | L8: =+D8*1.06*1.06*K8*12 -> 6741.6 | M8: =+L8/$L$12 -> 0.045045045 | N8: =+E8 -> 1 | O8: =+D8*1.06*1.06*1.06*N8*12 -> 7146.096 | P8: =+O8/$O$12 -> 0.041322314 | Q8: =+H8 -> 1 | R8: =+D8*1.06*1.06*1.06*1.06*Q8*12 -> 7574.8618 | S8: =+R8/$R$12 -> 0.041322314 | T8: =+K8 -> 1 | U8: =+D8*1.06*1.06*1.06*1.06*T8*12 -> 7574.8618 | V8: =+U8/$R$12 -> 0.041322314 | W8: =+N8 -> 1 | X8: =+D8*1.06*1.06*1.06*1.06*W8*12 -> 7574.8618 | Y8: =+X8/$R$12 -> 0.041322314
A9: Ouvriers | B9: Imputable | D9: 500 | E9: 6 | F9: =+D9*E9*12 -> 36000 | G9: =+F9/$F$12 -> 0.27027027 | H9: =+E9 -> 6 | I9: =+D9*1.06*H9*12 -> 38160 | J9: =+I9/$I$12 -> 0.27027027 | K9: =+E9 -> 6 | L9: =+D9*1.06*1.06*K9*12 -> 40449.6 | M9: =+L9/$L$12 -> 0.27027027 | N9: 8 | O9: =+D9*1.06*1.06*1.06*N9*12 -> 57168.768 | P9: =+O9/$O$12 -> 0.33057851 | Q9: 8 | R9: =+D9*1.06*1.06*1.06*1.06*Q9*12 -> 60598.894 | S9: =+R9/$R$12 -> 0.33057851 | T9: 8 | U9: =+D9*1.06*1.06*1.06*1.06*T9*12 -> 60598.894 | V9: =+U9/$R$12 -> 0.33057851 | W9: 8 | X9: =+D9*1.06*1.06*1.06*1.06*W9*12 -> 60598.894 | Y9: =+X9/$R$12 -> 0.33057851
A10: Chauffeur | B10: Imputable | D10: 600 | E10: 1 | F10: =+D10*E10*12 -> 7200 | G10: =+F10/$F$12 -> 0.054054054 | H10: =+E10 -> 1 | I10: =+D10*1.06*H10*12 -> 7632 | J10: =+I10/$I$12 -> 0.054054054 | K10: =+E10 -> 1 | L10: =+D10*1.06*1.06*K10*12 -> 8089.92 | M10: =+L10/$L$12 -> 0.054054054 | N10: 1 | O10: =+D10*1.06*1.06*1.06*N10*12 -> 8575.3152 | P10: =+O10/$O$12 -> 0.049586777 | Q10: 1 | R10: =+D10*1.06*1.06*1.06*1.06*Q10*12 -> 9089.8341 | S10: =+R10/$R$12 -> 0.049586777 | T10: 1 | U10: =+D10*1.06*1.06*1.06*1.06*T10*12 -> 9089.8341 | V10: =+U10/$R$12 -> 0.049586777 | W10: 1 | X10: =+D10*1.06*1.06*1.06*1.06*W10*12 -> 9089.8341 | Y10: =+X10/$R$12 -> 0.049586777
A11: Technicien | B11: Imputable | C11: Expérience exigée | D11: 650 | E11: 2 | F11: =+D11*E11*12 -> 15600 | G11: =+F11/$F$12 -> 0.11711712 | H11: =+E11 -> 2 | I11: =+D11*1.06*H11*12 -> 16536 | J11: =+I11/$I$12 -> 0.11711712 | K11: =+E11 -> 2 | L11: =+D11*1.06*1.06*K11*12 -> 17528.16 | M11: =+L11/$L$12 -> 0.11711712 | N11: =+E11 -> 2 | O11: =+D11*1.06*1.06*1.06*N11*12 -> 18579.85 | P11: =+O11/$O$12 -> 0.10743802 | Q11: =+H11 -> 2 | R11: =+D11*1.06*1.06*1.06*1.06*Q11*12 -> 19694.641 | S11: =+R11/$R$12 -> 0.10743802 | T11: =+K11 -> 2 | U11: =+D11*1.06*1.06*1.06*1.06*T11*12 -> 19694.641 | V11: =+U11/$R$12 -> 0.10743802 | W11: =+N11 -> 2 | X11: =+D11*1.06*1.06*1.06*1.06*W11*12 -> 19694.641 | Y11: =+X11/$R$12 -> 0.10743802
A12: Total | D12: =SUM(D4:D11) -> 6950 | E12: =SUM(E4:E11) -> 15 | F12: =SUM(F4:F11) -> 133200 | H12: =SUM(H4:H11) -> 15 | I12: =SUM(I4:I11) -> 141192 | K12: =SUM(K4:K11) -> 15 | L12: =SUM(L4:L11) -> 149663.52 | N12: =SUM(N4:N11) -> 17 | O12: =SUM(O4:O11) -> 172935.52 | Q12: =SUM(Q4:Q11) -> 17 | R12: =SUM(R4:R11) -> 183311.65 | T12: =SUM(T4:T11) -> 17 | U12: =SUM(U4:U11) -> 183311.65 | W12: =SUM(W4:W11) -> 17 | X12: =SUM(X4:X11) -> 183311.65
C14: Hypotèse d'évolution | I14: =+(I12-F12)/F12 -> 0.06 | L14: =+(L12-I12)/I12 -> 0.06 | O14: =+(O12-L12)/L12 -> 0.1554955 | R14: =+(R12-O12)/O12 -> 0.06 | U14: =+(U12-R12)/R12 -> 0 | X14: =+(X12-U12)/U12 -> 0
A16: Rubrique | C16: 2016 | D16: 2017 | E16: 2018 | F16: 2019 | G16: 2020 | H16: 2021 | I16: 2022
A17: Salaire brut annuel | C17: =+F12 -> 133200 | D17: =+I12 -> 141192 | E17: =+L12 -> 149663.52 | F17: =+O12 -> 172935.52 | G17: =+R12 -> 183311.65 | H17: =+U12 -> 183311.65 | I17: =+X12 -> 183311.65
A18: CNSS | C18: =+C17*(16.57%+2.4%) -> 25268.04 | D18: =+D17*(16.57%+2.4%) -> 26784.122 | E18: =+E17*(16.57%+2.4%) -> 28391.17 | F18: =+F17*(16.57%+2.4%) -> 32805.869 | G18: =+G17*(16.57%+2.4%) -> 34774.221 | H18: =+H17*(16.57%+2.4%) -> 34774.221 | I18: =+I17*(16.57%+2.4%) -> 34774.221
A19: TOTAL | C19: =SUM(C17:C18) -> 158468.04 | D19: =SUM(D17:D18) -> 167976.12 | E19: =SUM(E17:E18) -> 178054.69 | F19: =SUM(F17:F18) -> 205741.39 | G19: =SUM(G17:G18) -> 218085.88 | H19: =SUM(H17:H18) -> 218085.88 | I19: =SUM(I17:I18) -> 218085.88
A21: Imputable | C21: =+SUMIF(B:B,A21,G:G) -> 0.62162162 | D21: =+SUMIF(B:B,A21,J:J) -> 0.62162162 | E21: =+SUMIF(B:B,A21,M:M) -> 0.62162162 | F21: =+SUMIF(B:B,A21,P:P) -> 0.65289256 | G21: =+SUMIF(B:B,A21,S:S) -> 0.65289256 | H21: =+SUMIF(B:B,A21,V:V) -> 0.65289256 | I21: =+SUMIF(B:B,A21,Y:Y) -> 0.65289256
A22: Non imputable | C22: =+SUMIF(B:B,A22,G:G) -> 0.37837838 | D22: =+SUMIF(B:B,A22,J:J) -> 0.37837838 | E22: =+SUMIF(B:B,A22,M:M) -> 0.37837838 | F22: =+SUMIF(B:B,A22,P:P) -> 0.34710744 | G22: =+SUMIF(B:B,A22,S:S) -> 0.34710744 | H22: =+SUMIF(B:B,A22,V:V) -> 0.34710744 | I22: =+SUMIF(B:B,A22,Y:Y) -> 0.34710744
A25: Production annuelle | C25: =+'Consommations Q'!C11 -> 133285.16 | D25: =+'Consommations Q'!H11 -> 149112.77 | E25: =+'Consommations Q'!M11 -> 171479.69 | F25: =+'Consommations Q'!R11 -> 197201.64 | G25: =+'Consommations Q'!W11 -> 226781.89
A27: Main d'œuvre par Kg | C27: =+(C19*C21)/C25 -> 0.73907072 | D27: =+(D19*D21)/D25 -> 0.70025918 | E27: =+(E19*E21)/E25 -> 0.64545629 | F27: =+(F19*F21)/F25 -> 0.68116585 | G27: =+(G19*G21)/G25 -> 0.62785721
B29: 2016 | D29: 2017 | F29: 2018 | H29: 2019 | J29: 2020 | L29: 2021 | N29: 2022
A30: Fonctions | B30: Effectif | C30: Salaire Brut | D30: Effectif | E30: Salaire Brut | F30: Effectif | G30: Salaire Brut | H30: Effectif | I30: Salaire Brut | J30: Effectif | K30: Salaire Brut | L30: Effectif | M30: Salaire Brut | N30: Effectif | O30: Salaire Brut
A31: Gérant | B31: =+E4 -> 1 | C31: =+F4 -> 24000 | D31: =+H4 -> 1 | E31: =+I4 -> 25440 | F31: =+K4 -> 1 | G31: =+L4 -> 26966.4 | H31: =+N4 -> 1 | I31: =+O4 -> 28584.384 | J31: =+Q4 -> 1 | K31: =+R4 -> 30299.447 | L31: =+T4 -> 1 | M31: =+U4 -> 30299.447 | N31: =+W4 -> 1 | O31: =+X4 -> 30299.447
A32: Responsables Commerciaux | B32: =+E5 -> 2 | C32: =+F5 -> 24000 | D32: =+H5 -> 2 | E32: =+I5 -> 25440 | F32: =+K5 -> 2 | G32: =+L5 -> 26966.4 | H32: =+N5 -> 2 | I32: =+O5 -> 28584.384 | J32: =+Q5 -> 2 | K32: =+R5 -> 30299.447 | L32: =+T5 -> 2 | M32: =+U5 -> 30299.447 | N32: =+W5 -> 2 | O32: =+X5 -> 30299.447
A33: Directeur financier | B33: =+E6 -> 1 | C33: =+F6 -> 12000 | D33: =+H6 -> 1 | E33: =+I6 -> 12720 | F33: =+K6 -> 1 | G33: =+L6 -> 13483.2 | H33: =+N6 -> 1 | I33: =+O6 -> 14292.192 | J33: =+Q6 -> 1 | K33: =+R6 -> 15149.724 | L33: =+T6 -> 1 | M33: =+U6 -> 15149.724 | N33: =+W6 -> 1 | O33: =+X6 -> 15149.724
A34: Administratif | B34: =+E7 -> 1 | C34: =+F7 -> 8400 | D34: =+H7 -> 1 | E34: =+I7 -> 8904 | F34: =+K7 -> 1 | G34: =+L7 -> 9438.24 | H34: =+N7 -> 1 | I34: =+O7 -> 10004.534 | J34: =+Q7 -> 1 | K34: =+R7 -> 10604.806 | L34: =+T7 -> 1 | M34: =+U7 -> 10604.806 | N34: =+W7 -> 1 | O34: =+X7 -> 10604.806
A35: Gardien | B35: =+E8 -> 1 | C35: =+F8 -> 6000 | D35: =+H8 -> 1 | E35: =+I8 -> 6360 | F35: =+K8 -> 1 | G35: =+L8 -> 6741.6 | H35: =+N8 -> 1 | I35: =+O8 -> 7146.096 | J35: =+Q8 -> 1 | K35: =+R8 -> 7574.8618 | L35: =+T8 -> 1 | M35: =+U8 -> 7574.8618 | N35: =+W8 -> 1 | O35: =+X8 -> 7574.8618
A36: Ouvriers | B36: =+E9 -> 6 | C36: =+F9 -> 36000 | D36: =+H9 -> 6 | E36: =+I9 -> 38160 | F36: =+K9 -> 6 | G36: =+L9 -> 40449.6 | H36: =+N9 -> 8 | I36: =+O9 -> 57168.768 | J36: =+Q9 -> 8 | K36: =+R9 -> 60598.894 | L36: =+T9 -> 8 | M36: =+U9 -> 60598.894 | N36: =+W9 -> 8 | O36: =+X9 -> 60598.894
A37: Chauffeur | B37: =+E10 -> 1 | C37: =+F10 -> 7200 | D37: =+H10 -> 1 | E37: =+I10 -> 7632 | F37: =+K10 -> 1 | G37: =+L10 -> 8089.92 | H37: =+N10 -> 1 | I37: =+O10 -> 8575.3152 | J37: =+Q10 -> 1 | K37: =+R10 -> 9089.8341 | L37: =+T10 -> 1 | M37: =+U10 -> 9089.8341 | N37: =+W10 -> 1 | O37: =+X10 -> 9089.8341
A38: Technicien | B38: =+E11 -> 2 | C38: =+F11 -> 15600 | D38: =+H11 -> 2 | E38: =+I11 -> 16536 | F38: =+K11 -> 2 | G38: =+L11 -> 17528.16 | H38: =+N11 -> 2 | I38: =+O11 -> 18579.85 | J38: =+Q11 -> 2 | K38: =+R11 -> 19694.641 | L38: =+T11 -> 2 | M38: =+U11 -> 19694.641 | N38: =+W11 -> 2 | O38: =+X11 -> 19694.641
A39: Total | B39: =SUM(B31:B38) -> 15 | C39: =SUM(C31:C38) -> 133200 | D39: =SUM(D31:D38) -> 15 | E39: =SUM(E31:E38) -> 141192 | F39: =SUM(F31:F38) -> 15 | G39: =SUM(G31:G38) -> 149663.52 | H39: =SUM(H31:H38) -> 17 | I39: =SUM(I31:I38) -> 172935.52 | ... O39: =SUM(O31:O38) -> 183311.65
C40: =+C39-F12 -> 0 | E40: =+E39-I12 -> 0 | G40: =+G39-L12 -> 0 | I40: =+I39-O12 -> 0 | K40: =+K39-R12 -> 0 | M40: =+M39-U12 -> 0 | O40: =+O39-X12 -> 0

Sheet P&L
A1: ETAT DE RESULTAT
A2: Modèle autorisé
A3: (Exprimé en Dinars Tunisien)
C5: Exercice de 12 mois clos le 31 décembre
A6: Etat de résultat | C6: 2016 | D6: % Rev | E6: 2017 | F6: % Rev | G6: 2018 | H6: % Rev | I6: 2019 | J6: % Rev | K6: 2020 | L6: % Rev | M6: 2021 | N6: % Rev | O6: 2022 | P6: % Rev
A8: Produits d'exploitation
B10: Revenus | C10: =+'Chiffre d''affaire'!I10 -> 1742256 | E10: =+'Chiffre d''affaire'!L10 -> 2003594.4 | G10: =+'Chiffre d''affaire'!N10 -> 2304133.6 | I10: =+'Chiffre d''affaire'!P10 -> 2649753.6 | K10: =+'Chiffre d''affaire'!R10 -> 3047216.6 | M10: =+'Chiffre d''affaire'!T10 -> 3047216.6 | O10: =+'Chiffre d''affaire'!V10 -> 3047216.6
B11: Autres produits d'exploitation | I11: 0 | K11: 0 | M11: 0 | O11: 0
B12: Production immobilisée | I12: 0 | K12: 0 | M12: 0 | O12: 0
B14: Total des produits d'exploitation | C14: =SUM(C10:C13) -> 1742256 | E14: =SUM(E10:E13) -> 2003594.4 | G14: =SUM(G10:G13) -> 2304133.6 | I14: =SUM(I10:I13) -> 2649753.6 | K14: =SUM(K10:K13) -> 3047216.6 | M14: =SUM(M10:M13) -> 3047216.6 | O14: =SUM(O10:O13) -> 3047216.6
A16: Charges d'exploitation
B18: Variations des stocks produits finis & en-cours | C18: =-'Cout de production prévisionnel'!E12 -> 40538.501 | D18: =C18/$C$14 -> 0.023267821 | E18: =-'Cout de production prévisionnel'!I12 -> 6080.7751 | F18: =E18/$E$14 -> 0.0030349332 | G18: =-'Cout de production prévisionnel'!M12 -> 6992.8914 | H18: =G18/$G$14 -> 0.0030349332 | I18: =-'Cout de production prévisionnel'!Q12 -> 8041.8251 | J18: =I18/$I$14 -> 0.0030349332 | K18: =-'Cout de production prévisionnel'!U12 -> 9248.0989 | L18: =K18/$K$14 -> 0.0030349332 | M18: =-'Cout de production prévisionnel'!Y12 -> 0 | N18: =M18/$M$14 -> 0 | O18: =-'Cout de production prévisionnel'!AC12 -> 0 | P18: =O18/$O$14 -> 0
B19: Achats consommés | C19: =-'Ach prévisionnel'!B77 -> -1171792.8 | D19: =-C19/$C$14 -> 0.67257209 | E19: =-'Ach prévisionnel'!C77 -> -1312455.5 | F19: =-E19/$E$14 -> 0.65505051 | G19: =-'Ach prévisionnel'!D77 -> -1509323.9 | H19: =-G19/$G$14 -> 0.65505051 | I19: =-'Ach prévisionnel'!E77 -> -1735722.4 | J19: =-I19/$I$14 -> 0.65505051 | K19: =-'Ach prévisionnel'!F77 -> -1996080.8 | L19: =-K19/$K$14 -> 0.65505051 | M19: =-'Ach prévisionnel'!G77 -> -1988072 | N19: =-M19/$M$14 -> 0.65242227 | O19: =-'Ach prévisionnel'!H77 -> -1988072 | P19: =-O19/$O$14 -> 0.65242227
B20: Charges de personnel | C20: =-SALAIRE!C19 -> -158468.04 | D20: =-C20/$C$14 -> 0.090955657 | E20: =-SALAIRE!D19 -> -167976.12 | F20: =-E20/$E$14 -> 0.083837389 | G20: =-SALAIRE!E19 -> -178054.69 | H20: =-G20/$G$14 -> 0.077276202 | I20: =-SALAIRE!F19 -> -205741.39 | J20: =-I20/$I$14 -> 0.077645481 | K20: =-SALAIRE!G19 -> -218085.88 | L20: =-K20/$K$14 -> 0.071568878 | M20: =-SALAIRE!H19 -> -218085.88 | N20: =-M20/$M$14 -> 0.071568878 | O20: =-SALAIRE!I19 -> -218085.88 | P20: =-O20/$O$14 -> 0.071568878
B21: Dotations aux amortissements et aux provisions | C21: =-Investissements!F11 -> -55789.44 | D21: =-C21/$C$14 -> 0.032021379 | E21: =-Investissements!G11 -> -55789.44 | F21: =-E21/$E$14 -> 0.027844678 | G21: =-Investissements!H11 -> -55791.49 | H21: =-G21/$G$14 -> 0.024213653 | I21: =-Investissements!I11 -> -48956.79 | J21: =-I21/$I$14 -> 0.018475978 | K21: =-Investissements!J11 -> -48956.79 | L21: =-K21/$K$14 -> 0.016066068 | M21: =-Investissements!K11 -> -29556.79 | N21: =-M21/$M$14 -> 0.0096996025 | O21: =-Investissements!L11 -> -29556.79 | P21: =-O21/$O$14 -> 0.0096996025
B22: Autres charges d'exploitation | C22: =-'Autres charges'!B34 -> -230199.5 | D22: =-C22/$C$14 -> 0.13212725 | E22: =-'Autres charges'!C34 -> -256964.25 | F22: =-E22/$E$14 -> 0.12825163 | G22: =-'Autres charges'!D34 -> -287483.14 | H22: =-G22/$G$14 -> 0.12476844 | I22: =-'Autres charges'!E34 -> -322592.27 | J22: =-I22/$I$14 -> 0.12174425 | K22: =-'Autres charges'!F34 -> -362369.27 | L22: =-K22/$K$14 -> 0.11891812 | M22: =-'Autres charges'!G34 -> -390409.28 | N22: =-M22/$M$14 -> 0.12811996 | O22: =-'Autres charges'!H34 -> -368408.82 | P22: =-O22/$O$14 -> 0.12090011
B24: Total des charges d'exploitation | C24: =SUM(C18:C23) -> -1575711.2 | D24: =-C24/$C$14 -> 0.90440856 | E24: =SUM(E18:E23) -> -1787104.6 | F24: =-E24/$E$14 -> 0.89194928 | G24: =SUM(G18:G23) -> -2023660.3 | H24: =-G24/$G$14 -> 0.87827387 | I24: =SUM(I18:I23) -> -2304971.1 | J24: =-I24/$I$14 -> 0.86988129 | K24: =SUM(K18:K23) -> -2616244.6 | L24: =-K24/$K$14 -> 0.85856864 | M24: =SUM(M18:M23) -> -2626123.9 | N24: =-M24/$M$14 -> 0.86181072 | O24: =SUM(O18:O23) -> -2604123.5 | P24: =-O24/$O$14 -> 0.85459086
A26: Résultat d'exploitation | C26: =C14+C24 -> 166544.76 | D26: =C26/$C$14 -> 0.095591439 | E26: =E14+E24 -> 216489.83 | F26: =E26/$E$14 -> 0.10805072 | G26: =G14+G24 -> 280473.27 | H26: =G26/$G$14 -> 0.12172613 | I26: =I14+I24 -> 344782.53 | J26: =I26/$I$14 -> 0.13011871 | K26: =K14+K24 -> 430971.99 | L26: =K26/$K$14 -> 0.14143136 | M26: =M14+M24 -> 421092.68 | N26: =M26/$M$14 -> 0.13818928 | O26: =O14+O24 -> 443093.14 | P26: =O26/$O$14 -> 0.14540914
B28: Charges financières nettes | C28: =-Emprunt!L29 -> -34860 | D28: =-(C28/$C$14) -> 0.020008541 | E28: =-Emprunt!L30 -> -32681.25 | F28: =E28/$E$14 -> -0.01631131 | G28: =-Emprunt!L31 -> -26871.25 | H28: =G28/$G$14 -> -0.011662193 | I28: =-Emprunt!L32 -> -21061.25 | J28: =-I28/$I$14 -> 0.0079483806 | K28: =-Emprunt!L33 -> -15251.25 | L28: =-K28/$K$14 -> 0.0050049773 | M28: =-Emprunt!L34 -> -9441.25 | N28: =-M28/$M$14 -> 0.0030983193 | O28: =-Emprunt!L35 -> -3631.25 | P28: =-O28/$O$14 -> 0.0011916613
B29: Produits des placements | C29: 0 | D29: =C29/$C$14 -> 0 | F29: =E29/$E$14 -> 0 | H29: =G29/$G$14 -> 0 | J29: =-I29/$I$14 -> 0 | K29: 0 | L29: =-K29/$K$14 -> 0 | M29: 0 | N29: =-M29/$K$14 -> 0 | O29: 0 | P29: =-O29/$K$14 -> 0
B30: Autres gains ordinaires | C30: 0 | D30: =C30/$C$14 -> 0 | F30: =E30/$E$14 -> 0 | H30: =G30/$G$14 -> 0 | J30: =-I30/$I$14 -> 0 | K30: 0 | L30: =-K30/$K$14 -> 0 | M30: 0 | N30: =-M30/$K$14 -> 0 | O30: 0 | P30: =-O30/$K$14 -> 0
B31: Autres pertes ordinaires | C31: 0 | D31: =C31/$C$14 -> 0 | F31: =E31/$E$14 -> 0 | H31: =G31/$G$14 -> 0 | J31: =-I31/$I$14 -> 0 | K31: 0 | L31: =-K31/$K$14 -> 0 | M31: 0 | N31: =-M31/$K$14 -> 0 | O31: 0 | P31: =-O31/$K$14 -> 0
A33: Résultat des activités ordinaires avant impôt | C33: =SUM(C26:C31) -> 131684.76 | D33: =C33/$C$14 -> 0.075582898 | E33: =SUM(E26:E31) -> 183808.58 | F33: =E33/$E$14 -> 0.091739414 | G33: =SUM(G26:G31) -> 253602.02 | H33: =G33/$G$14 -> 0.11006394 | I33: =SUM(I26:I31) -> 323721.28 | J33: =I33/$I$14 -> 0.12217033 | K33: =SUM(K26:K31) -> 415720.74 | L33: =K33/$K$14 -> 0.13642638 | M33: =SUM(M26:M31) -> 411651.43 | N33: =M33/$M$14 -> 0.13509096 | O33: =SUM(O26:O31) -> 439461.89 | P33: =O33/$O$14 -> 0.14421748
B35: Impôt sur les bénéfices | C35: =-IF(C33<0,0,(C33*0.25)) -> -32921.189 | D35: =-C35/$C$14 -> 0.018895724 | E35: =-IF(E33<0,0,(E33*0.25)) -> -45952.144 | F35: =-E35/$E$14 -> 0.022934854 | G35: =-IF(G33<0,0,(G33*0.25)) -> -63400.505 | H35: =-G35/$G$14 -> 0.027515985 | I35: =-IF(I33<0,0,(I33*0.25)) -> -80930.32 | J35: =-I35/$I$14 -> 0.030542583 | K35: =-IF(K33<0,0,(K33*0.25)) -> -103930.19 | L35: =-K35/$K$14 -> 0.034106596 | M35: =-IF(M33<0,0,(M33*0.25)) -> -102912.86 | N35: =-M35/$M$14 -> 0.033772741 | O35: =-IF(O33<0,0,(O33*0.25)) -> -109865.47 | P35: =-O35/$O$14 -> 0.036054369
A37: Résultat des activités ordinaires après impôt | C37: =C33+C35 -> 98763.568 | D37: =C37/$C$14 -> 0.056687173 | E37: =E33+E35 -> 137856.43 | F37: =E37/$E$14 -> 0.068804561 | G37: =G33+G35 -> 190201.52 | H37: =G37/$G$14 -> 0.082547956 | I37: =I33+I35 -> 242790.96 | J37: =I37/I14 -> 0.09162775 | K37: =K33+K35 -> 311790.56 | L37: =K37/$K$14 -> 0.10231979 | M37: =M33+M35 -> 308738.58 | N37: =M37/$M$14 -> 0.10131822 | O37: =O33+O35 -> 329596.42 | P37: =O37/$O$14 -> 0.10816311
B38: Variation du BFR | D38: =C38/$C$14 -> 0
A39: Cash Flow | C39: =+(C37-C21)+C38 -> 154553.01 | E39: =+(E37-E21)+E38 -> 193645.87 | G39: =+(G37-G21)+G38 -> 245993.01 | I39: =+(I37-I21)+I38 -> 291747.75 | K39: =+(K37-K21)+K38 -> 360747.35 | M39: =+(M37-M21)+M38 -> 338295.37 | O39: =+(O37-O21)+O38 -> 359153.21
A40: Cash Flow cumulée | C40: =+C39 -> 154553.01 | E40: =+E39+C40 -> 348198.88 | G40: =+G39+E40 -> 594191.89 | I40: =+I39+G40 -> 885939.63 | K40: =+K39+I40 -> 1246687 | M40: =+M39+K40 -> 1584982.3 | O40: =+O39+M40 -> 1944135.6
A42: Remboursement Crédit LT | C42: 0 | E42: =-Emprunt!K30 -> -70000 | G42: =-Emprunt!K31 -> -70000 | I42: =-Emprunt!K32 -> -70000 | K42: =-Emprunt!K33 -> -70000 | M42: =-Emprunt!K34 -> -70000 | O42: =-Emprunt!K35 -> -70000
A43: Trésorerie cumulé | C43: =+C40+C42 -> 154553.01 | D43: =C43/$C$14 -> 0.088708553 | E43: =+E39+E42 -> 123645.87 | F43: =E43/$E$14 -> 0.061712027 | G43: =+G39+G42 -> 175993.01 | H43: =G43/$G$14 -> 0.076381425 | I43: =+I39+I42 -> 221747.75 | J43: =I43/$I$14 -> 0.083686177 | K43: =+K39+K42 -> 290747.35 | L43: =K43/$K$14 -> 0.095414072 | M43: =+M39+M42 -> 268295.37 | N43: =M43/$M$14 -> 0.088046043 | O43: =+O39+O42 -> 289153.21 | P43: =O43/$O$14 -> 0.094890927

Sheet ACTIFS
A1: BILAN
A2: (Exprimé en Dinars Tunisien)
D4: Solde arrêté au | F4: Solde arrêté au | H4: Solde arrêté au | J4: Solde arrêté au | L4: Solde arrêté au
A5: Actifs | C5: Notes | D5: 31 Déc. 2016 | F5: 31 Déc. 2017 | H5: 31 Déc. 2018 | J5: 31 Déc. 2019 | L5: 31 Déc. 2020
A7: Actifs non courants
B9: Immobilisations incorporelles | E9: =D9/$D$47 -> 0 | G9: =F9/$D$47 -> 0 | I9: =H9/$D$47 -> 0 | K9: =J9/$D$47 -> 0 | M9: =L9/$D$47 -> 0
B10: Moins : amortissements des immobilisations incorporelles | E10: =D10/$D$47 -> 0 | G10: =F10/$D$47 -> 0 | I10: =H10/$D$47 -> 0 | K10: =J10/$D$47 -> 0 | M10: =L10/$D$47 -> 0
B11: Immobilisations Incorporelles Nettes | D11: =SUM(D9:D10) -> 0 | E11: =D11/$D$47 -> 0 | F11: =SUM(F9:F10) -> 0 | G11: =F11/$D$47 -> 0 | H11: =SUM(H9:H10) -> 0 | I11: =H11/$D$47 -> 0 | J11: =SUM(J9:J10) -> 0 | K11: =J11/$D$47 -> 0 | L11: =SUM(L9:L10) -> 0 | M11: =L11/$D$47 -> 0
B13: Immobilisations corporelles | D13: =+SUMIF(BG!G:G,ACTIFS!B13,BG!E:E) -> 389067.9 | E13: =D13/$D$47 -> 0.43707826 | F13: =D13 -> 389067.9 | G13: =F13/$D$47 -> 0.43707826 | H13: =F13 -> 389067.9 | I13: =H13/$D$47 -> 0.43707826 | J13: =H13 -> 389067.9 | K13: =J13/$D$47 -> 0.43707826 | L13: =J13 -> 389067.9 | M13: =L13/$D$47 -> 0.43707826
B14: Moins : amortissements des immobilisations corporelles | D14: =+SUMIF(BG!G:G,ACTIFS!B14,BG!E:E) -> -48956.79 | E14: =D14/$D$47 -> -0.05499798 | F14: =+D14-SUM(Investissements!G5:G8) -> -97563.58 | G14: =F14/$D$47 -> -0.10960277 | H14: =+F14-SUM(Investissements!H5:H8) -> -146170.37 | I14: =H14/$D$47 -> -0.16420756 | J14: =+H14-SUM(Investissements!I5:I8) -> -194777.16 | K14: =J14/$D$47 -> -0.21881235 | L14: =+J14-SUM(Investissements!J5:J8) -> -243383.95 | M14: =L14/$D$47 -> -0.27341714
B15: Immobilisations Corporelles Nettes | C15: 1 | D15: =SUM(D13:D14) -> 340111.11 | E15: =D15/$D$47 -> 0.38208028 | F15: =SUM(F13:F14) -> 291504.32 | G15: =F15/$D$47 -> 0.32747549 | H15: =SUM(H13:H14) -> 242897.53 | I15: =H15/$D$47 -> 0.2728707 | J15: =SUM(J13:J14) -> 194290.74 | K15: =J15/$D$47 -> 0.21826591 | L15: =SUM(L13:L14) -> 145683.95 | M15: =L15/$D$47 -> 0.16366112
B17: Immobilisations financières | C17: 2 | D17: 0 | E17: =D17/$D$47 -> 0 | F17: 0 | G17: =F17/$D$47 -> 0 | H17: 0 | I17: =H17/$D$47 -> 0 | J17: 0 | K17: =J17/$D$47 -> 0 | L17: 0 | M17: =L17/$D$47 -> 0
B19: Total Actifs Immobilisés | D19: =D11+D15+D17 -> 340111.11 | E19: =D19/$D$47 -> 0.38208028 | F19: =F11+F15+F17 -> 291504.32 | G19: =F19/$D$47 -> 0.32747549 | H19: =H11+H15+H17 -> 242897.53 | I19: =H19/$D$47 -> 0.2728707 | J19: =J11+J15+J17 -> 194290.74 | K19: =J19/$D$47 -> 0.21826591 | L19: =L11+L15+L17 -> 145683.95 | M19: =L19/$D$47 -> 0.16366112
B21: Autres actifs non courants | D21: =+SUMIF(BG!G:G,ACTIFS!B21,BG!E:E) -> 13667.35 | E21: =D21/$D$47 -> 0.015353879 | F21: =+Investissements!B10-(Investissements!D10+Investissements!F10) -> 13667.35 | G21: =F21/$D$47 -> 0.015353879 | H21: =+Investissements!B10-SUM(Investissements!D10:G10) -> 6834.7 | I21: =H21/$D$47 -> 0.0076780911 | J21: 0 | K21: =J21/$D$47 -> 0 | L21: 0 | M21: =L21/$D$47 -> 0
A23: Total des actifs non courants | D23: =+D11+D15+D17+D21 -> 353778.46 | E23: =D23/$D$47 -> 0.39743416 | F23: =+F11+F15+F17+F21 -> 305171.67 | G23: =F23/$D$47 -> 0.34282937 | H23: =+H11+H15+H17+H21 -> 249732.23 | I23: =H23/$D$47 -> 0.28054879 | J23: =+J11+J15+J17+J21 -> 194290.74 | K23: =J23/$D$47 -> 0.21826591 | L23: =+L11+L15+L17+L21 -> 145683.95 | M23: =L23/$D$47 -> 0.16366112
A25: Actifs courants
B27: Stocks | C27: 3 | D27: =+SUMIF(BG!G:G,ACTIFS!B27,BG!E:E) -> 134154.9 | E27: =D27/$D$47 -> 0.1507094 | F27: =+#REF! -> #REF! | G27: =F27/$D$47 -> #REF! | H27: =+#REF! -> #REF! | I27: =H27/$D$47 -> #REF! | J27: =+#REF! -> #REF! | K27: =J27/$D$47 -> #REF! | L27: =+#REF! -> #REF! | M27: =L27/$D$47 -> #REF!
B28: Moins : provisions sur stocks | D28: 0 | E28: =D28/$D$47 -> 0 | F28: 0 | G28: =F28/$D$47 -> 0 | H28: 0 | I28: =H28/$D$47 -> 0 | J28: 0 | K28: =J28/$D$47 -> 0 | L28: 0 | M28: =L28/$D$47 -> 0
D29: =SUM(D27:D28) -> 134154.9 | E29: =D29/$D$47 -> 0.1507094 | F29: =SUM(F27:F28) -> #REF! | G29: =F29/$D$47 -> #REF! | H29: =SUM(H27:H28) -> #REF! | I29: =H29/$D$47 -> #REF! | J29: =SUM(J27:J28) -> #REF! | K29: =J29/$D$47 -> #REF! | L29: =SUM(L27:L28) -> #REF! | M29: =L29/$D$47 -> #REF!
B31: Clients et comptes rattachés | C31: 4 | D31: =+SUMIF(BG!G:G,ACTIFS!B31,BG!E:E) -> 51299.76 | E31: =D31/$D$47 -> 0.057630069 | F31: =+#REF! -> #REF! | G31: =F31/$D$47 -> #REF! | H31: =+#REF! -> #REF! | I31: =H31/$D$47 -> #REF! | J31: =+#REF! -> #REF! | K31: =J31/$D$47 -> #REF! | L31: =+#REF! -> #REF! | M31: =L31/$D$47 -> #REF! | O31: Stock | P31: =+D27 -> 134154.9
B32: Moins : provisions sur créances | D32: 0 | E32: =D32/$D$47 -> 0 | F32: 0 | G32: =F32/$D$47 -> 0 | H32: 0 | I32: =H32/$D$47 -> 0 | J32: 0 | K32: =J32/$D$47 -> 0 | L32: 0 | M32: =L32/$D$47 -> 0 | O32: client | P32: =+D31 -> 51299.76
D33: =SUM(D31:D32) -> 51299.76 | E33: =D33/$D$47 -> 0.057630069 | F33: =SUM(F31:F32) -> #REF! | G33: =F33/$D$47 -> #REF! | H33: =SUM(H31:H32) -> #REF! | I33: =H33/$D$47 -> #REF! | J33: =SUM(J31:J32) -> #REF! | K33: =J33/$D$47 -> #REF! | L33: =SUM(L31:L32) -> #REF! | M33: =L33/$D$47 -> #REF! | O33: AAC | P33: =+D35 -> 187870.09
O34: Feurs | P34: =-PASSIFS!D34 -> -176657.89
B35: Autres actifs courants | C35: 5 | D35: =+SUMIF(BG!G:G,ACTIFS!B35,BG!E:E) -> 187870.09 | E35: =D35/$D$47 -> 0.21105296 | F35: =+#REF! -> #REF! | G35: =F35/$D$47 -> #REF! | H35: =+#REF! -> #REF! | I35: =H35/$D$47 -> #REF! | J35: =+#REF! -> #REF! | K35: =J35/$D$47 -> #REF! | L35: =+#REF! -> #REF! | M35: =L35/$D$47 -> #REF! | O35: APC | P35: =-PASSIFS!D35 -> -14734.691
B36: Moins : provisions autres actifs courants | D36: 0 | E36: =D36/$D$47 -> 0 | F36: 0 | G36: =F36/$D$47 -> 0 | H36: 0 | I36: =H36/$D$47 -> 0 | J36: 0 | K36: =J36/$D$47 -> 0 | L36: 0 | M36: =L36/$D$47 -> 0
D37: =SUM(D35:D36) -> 187870.09 | E37: =D37/$D$47 -> 0.21105296 | F37: =SUM(F35:F36) -> #REF! | G37: =F37/$D$47 -> #REF! | H37: =SUM(H35:H36) -> #REF! | I37: =H37/$D$47 -> #REF! | J37: =SUM(J35:J36) -> #REF! | K37: =J37/$D$47 -> #REF! | L37: =SUM(L35:L36) -> #REF! | M37: =L37/$D$47 -> #REF!
B39: Placements et autres actifs financiers | D39: 0 | E39: =D39/$D$47 -> 0 | F39: 0 | G39: =F39/$D$47 -> 0 | H39: 0 | I39: =H39/$D$47 -> 0 | J39: 0 | K39: =J39/$D$47 -> 0 | L39: 0 | M39: =L39/$D$47 -> 0
B40: Moins : provisions autres actifs financiers | D40: 0 | E40: =D40/$D$47 -> 0 | F40: 0 | G40: =F40/$D$47 -> 0 | H40: 0 | I40: =H40/$D$47 -> 0 | J40: 0 | K40: =J40/$D$47 -> 0 | L40: 0 | M40: =L40/$D$47 -> 0
D41: =SUM(D39:D40) -> 0 | E41: =D41/$D$47 -> 0 | F41: =SUM(F39:F40) -> 0 | G41: =F41/$D$47 -> 0 | H41: =SUM(H39:H40) -> 0 | I41: =H41/$D$47 -> 0 | J41: =SUM(J39:J40) -> 0 | K41: =J41/$D$47 -> 0 | L41: =SUM(L39:L40) -> 0 | M41: =L41/$D$47 -> 0
B43: Liquidités et équivalents de liquidités | C43: 6 | D43: =+SUMIF(BG!G:G,ACTIFS!B43,BG!E:E) -> 163052.94 | E43: =D43/$D$47 -> 0.18317342 | F43: 0 | G43: =F43/$D$47 -> 0 | H43: =+SUMIF(BG!K:K,ACTIFS!F43,BG!I:I) -> 0 | I43: =H43/$D$47 -> 0 | J43: =+SUMIF(BG!M:M,ACTIFS!H43,BG!K:K) -> 0 | K43: =J43/$D$47 -> 0 | L43: =+SUMIF(BG!O:O,ACTIFS!J43,BG!M:M) -> 0 | M43: =L43/$D$47 -> 0
A45: Total des actifs courants | D45: =+D43+D37+D33+D29+D41 -> 536377.69 | E45: =D45/$D$47 -> 0.60256584 | F45: =+F43+F37+F33+F29+F41 -> #REF! | G45: =F45/$D$47 -> #REF! | H45: =+H43+H37+H33+H29+H41 -> #REF! | I45: =H45/$D$47 -> #REF! | J45: =+J43+J37+J33+J29+J41 -> #REF! | K45: =J45/$D$47 -> #REF! | L45: =+L43+L37+L33+L29+L41 -> #REF! | M45: =L45/$D$47 -> #REF!
A47: Total des actifs | D47: =+D45+D23 -> 890156.15 | E47: =D47/$D$47 -> 1 | F47: =+F45+F23 -> #REF! | G47: =F47/$D$47 -> #REF! | H47: =+H45+H23 -> #REF! | I47: =H47/$D$47 -> #REF! | J47: =+J45+J23 -> #REF! | K47: =J47/$D$47 -> #REF! | L47: =+L45+L23 -> #REF! | M47: =L47/$D$47 -> #REF!
B49: Check | D49: =D47-PASSIFS!D42 -> 0 | F49: =F47-PASSIFS!F42 -> #REF! | H49: =H47-PASSIFS!H42 -> #REF! | J49: =J47-PASSIFS!J42 -> #REF! | L49: =L47-PASSIFS!L42 -> #REF!

Sheet PASSIFS
A1: BILAN
A2: (Exprimé en Dinars Tunisien)
D4: Solde arrêté au | F4: Solde arrêté au | H4: Solde arrêté au | J4: Solde arrêté au | L4: Solde arrêté au
A5: Capitaux propres et passifs | C5: Notes | D5: 31 Déc. 2016 | F5: 31 Déc. 2016 | H5: 31 Déc. 2016 | J5: 31 Déc. 2016 | L5: 31 Déc. 2016
A7: Capitaux propres
B9: Capital social | D9: =-SUMIF(BG!G:G,PASSIFS!B9,BG!E:E) -> 180000 | E9: =D9/$D$42 -> 0.20221171 | F9: =+D9 -> 180000 | G9: =F9/$D$42 -> 0.20221171 | H9: =+F9 -> 180000 | I9: =H9/$D$42 -> 0.20221171 | J9: =+H9 -> 180000 | K9: =J9/$D$42 -> 0.20221171 | L9: =+J9 -> 180000 | M9: =L9/$D$42 -> 0.20221171
B10: Réserves légales | E10: =D10/$D$42 -> 0 | G10: =F10/$D$42 -> 0 | I10: =H10/$D$42 -> 0 | K10: =J10/$D$42 -> 0 | M10: =L10/$D$42 -> 0
B11: Résultats reportés | E11: =D11/$D$42 -> 0 | F11: =+D19 -> 98763.568 | G11: =F11/$D$42 -> 0.11095083 | H11: =+F11+F19 -> 236620 | I11: =H11/$D$42 -> 0.26581853 | J11: =+H11+H19 -> 426821.52 | K11: =J11/$D$42 -> 0.47949061 | L11: =+J11+J19 -> 669612.47 | M11: =L11/$D$42 -> 0.75224159
B12: Modifications comptables | E12: =D12/$D$42 -> 0 | G12: =F12/$D$42 -> 0 | I12: =H12/$D$42 -> 0 | K12: =J12/$D$42 -> 0 | M12: =L12/$D$42 -> 0
B13: Autres capitaux propres | E13: =D13/$D$42 -> 0 | G13: =F13/$D$42 -> 0 | I13: =H13/$D$42 -> 0 | K13: =J13/$D$42 -> 0 | M13: =L13/$D$42 -> 0
B14: Réserves spéciales de réévaluation | E14: =D14/$D$42 -> 0 | G14: =F14/$D$42 -> 0 | I14: =H14/$D$42 -> 0 | K14: =J14/$D$42 -> 0 | M14: =L14/$D$42 -> 0
B15: Subventions d'investissement | E15: =D15/$D$42 -> 0 | G15: =F15/$D$42 -> 0 | I15: =H15/$D$42 -> 0 | K15: =J15/$D$42 -> 0 | M15: =L15/$D$42 -> 0
A17: Total des capitaux propres avant résulat | D17: =SUM(D9:D16) -> 180000 | E17: =D17/$D$42 -> 0.20221171 | F17: =SUM(F9:F16) -> 278763.57 | G17: =F17/$D$42 -> 0.31316255 | H17: =SUM(H9:H16) -> 416620 | I17: =H17/$D$42 -> 0.46803024 | J17: =SUM(J9:J16) -> 606821.52 | K17: =J17/$D$42 -> 0.68170232 | L17: =SUM(L9:L16) -> 849612.47 | M17: =L17/$D$42 -> 0.9544533
B19: Résultat de l'exercice | D19: =+'P&L'!C37 -> 98763.568 | E19: =D19/$D$42 -> 0.11095083 | F19: =+'P&L'!E37 -> 137856.43 | G19: =F19/$D$42 -> 0.1548677 | H19: =+'P&L'!G37 -> 190201.52 | I19: =H19/$D$42 -> 0.21367208 | J19: =+'P&L'!I37 -> 242790.96 | K19: =J19/$D$42 -> 0.27275098 | L19: =+'P&L'!K37 -> 311790.56 | M19: =L19/$D$42 -> 0.35026501
A21: Total des capitaux propres avant affectation | C21: 7 | D21: =D19+D17 -> 278763.57 | E21: =D21/$D$42 -> 0.31316255 | F21: =F19+F17 -> 416620 | G21: =F21/$D$42 -> 0.46803024 | H21: =H19+H17 -> 606821.52 | I21: =H21/$D$42 -> 0.68170232 | J21: =J19+J17 -> 849612.47 | K21: =J21/$D$42 -> 0.9544533 | L21: =L19+L17 -> 1161403 | M21: =L21/$D$42 -> 1.3047183
A23: Passifs
A25: Passifs non courants
B27: Provisions pour risques et charges | E27: =D27/$D$42 -> 0 | G27: =F27/$D$42 -> 0 | I27: =H27/$D$42 -> 0 | K27: =J27/$D$42 -> 0 | M27: =L27/$D$42 -> 0
B28: Emprunts et dettes assimilées | C28: 8 | D28: =-SUMIF(BG!G:G,PASSIFS!B28,BG!E:E) -> 420000 | E28: =D28/$D$42 -> 0.47182733 | F28: =+D28+'P&L'!E42 -> 350000 | G28: =F28/$D$42 -> 0.39318944 | H28: =+F28+'P&L'!G42 -> 280000 | I28: =H28/$D$42 -> 0.31455155 | J28: =+H28+'P&L'!I42 -> 210000 | K28: =J28/$D$42 -> 0.23591367 | L28: =+J28+'P&L'!K42 -> 140000 | M28: =L28/$D$42 -> 0.15727578
A30: Total des passifs non courants | D30: =SUM(D27:D29) -> 420000 | E30: =D30/$D$42 -> 0.47182733 | F30: =SUM(F27:F29) -> 350000 | G30: =F30/$D$42 -> 0.39318944 | H30: =SUM(H27:H29) -> 280000 | I30: =H30/$D$42 -> 0.31455155 | J30: =SUM(J27:J29) -> 210000 | K30: =J30/$D$42 -> 0.23591367 | L30: =SUM(L27:L29) -> 140000 | M30: =L30/$D$42 -> 0.15727578
A32: Passifs courants
B34: Fournisseurs et comptes rattachés | C34: 9 | D34: =-SUMIF(BG!G:G,PASSIFS!B34,BG!E:E) -> 176657.89 | E34: =D34/$D$42 -> 0.19845719 | F34: =-#REF! -> #REF! | G34: =F34/$D$42 -> #REF! | H34: =-#REF! -> #REF! | I34: =H34/$D$42 -> #REF! | J34: =-#REF! -> #REF! | K34: =J34/$D$42 -> #REF! | L34: =-#REF! -> #REF! | M34: =L34/$D$42 -> #REF!
B35: Autres passifs courants | C35: 10 | D35: =-SUMIF(BG!G:G,PASSIFS!B35,BG!E:E) -> 14734.691 | E35: =D35/$D$42 -> 0.016552929 | F35: =-#REF! -> #REF! | G35: =F35/$D$42 -> #REF! | H35: =-#REF! -> #REF! | I35: =H35/$D$42 -> #REF! | J35: =-#REF! -> #REF! | K35: =J35/$D$42 -> #REF! | L35: =-#REF! -> #REF! | M35: =L35/$D$42 -> #REF!
B36: Concours bancaires et autres passifs financiers | C36: 11 | E36: =D36/$D$42 -> 0 | G36: =F36/$D$42 -> 0 | I36: =H36/$D$42 -> 0 | K36: =J36/$D$42 -> 0 | M36: =L36/$D$42 -> 0
A38: Total des passifs courants | D38: =SUM(D34:D37) -> 191392.58 | E38: =D38/$D$42 -> 0.21501012 | F38: =SUM(F34:F37) -> #REF! | G38: =F38/$D$42 -> #REF! | H38: =SUM(H34:H37) -> #REF! | I38: =H38/$D$42 -> #REF! | J38: =SUM(J34:J37) -> #REF! | K38: =J38/$D$42 -> #REF! | L38: =SUM(L34:L37) -> #REF! | M38: =L38/$D$42 -> #REF!
A40: Total des passifs | D40: =D38+D30 -> 611392.58 | E40: =D40/$D$42 -> 0.68683745 | F40: =F38+F30 -> #REF! | G40: =F40/$D$42 -> #REF! | H40: =H38+H30 -> #REF! | I40: =H40/$D$42 -> #REF! | J40: =J38+J30 -> #REF! | K40: =J40/$D$42 -> #REF! | L40: =L38+L30 -> #REF! | M40: =L40/$D$42 -> #REF!
A42: Total des capitaux propres et passifs | D42: =D40+D21 -> 890156.15 | E42: =D42/$D$42 -> 1 | F42: =F40+F21 -> #REF! | G42: =F42/$D$42 -> #REF! | H42: =H40+H21 -> #REF! | I42: =H42/$D$42 -> #REF! | J42: =J40+J21 -> #REF! | K42: =J42/$D$42 -> #REF! | L42: =L40+L21 -> #REF! | M42: =L42/$D$42 -> #REF!
B44: Check | D44: =D42-ACTIFS!D47 -> 0 | F44: =F42-ACTIFS!F47 -> #REF! | H44: =H42-ACTIFS!H47 -> #REF! | J44: =J42-ACTIFS!J47 -> #REF! | L44: =L42-ACTIFS!L47 -> #REF!

Sheet BG
A2: Compte | B2: Libéllé | C2: Débit | D2: Crédit | E2: Solde | G2: Affectation | I2: Hypothèse
B3: Banque | C3: 180000 | E3: =+C3-D3 -> 180000 | F3: BS | G3: Liquidités et équivalents de liquidités | H3: A
B4: capital | D4: 180000 | E4: =+C4-D4 -> -180000 | F4: BS | G4: Capital social | H4: CP
B5: Banque | C5: =+D6 -> 420000 | E5: =+C5-D5 -> 420000 | F5: BS | G5: Liquidités et équivalents de liquidités | H5: A
B6: emprunt | D6: 420000 | E6: =+C6-D6 -> -420000 | F6: BS | G6: Emprunts et dettes assimilées | H6: P
B7: emprunt | C7: 0 | E7: =+C7-D7 -> 0 | F7: BS | G7: Emprunts et dettes assimilées | H7: P
B8: Banque | D8: 0 | E8: =+C8-D8 -> 0 | F8: BS | G8: Liquidités et équivalents de liquidités | H8: A
B9: interet | C9: =+Emprunt!L29 -> 34860 | E9: =+C9-D9 -> 34860 | F9: PL
B10: Banque | D10: =+C9 -> 34860 | E10: =+C10-D10 -> -34860 | F10: BS | G10: Liquidités et équivalents de liquidités | H10: A
B11: clients | C11: =+D12+D13 -> 1846791.4 | E11: =+C11-D11 -> 1846791.4 | F11: BS | G11: Clients et comptes rattachés | H11: A
B12: vente | D12: =+'Chiffre d''affaire'!I10 -> 1742256 | E12: =+C12-D12 -> -1742256 | F12: PL
B13: TVA/VTE | D13: =+D12*0.06 -> 104535.36 | E13: =+C13-D13 -> -104535.36 | F13: BS | G13: Autres passifs courants | H13: P
B14: Banque | C14: =+(D16)*0.985 -> 1768559.2 | E14: =+C14-D14 -> 1768559.2 | F14: BS | G14: Liquidités et équivalents de liquidités | H14: A
B15: retenue à la source | C15: =+D16-C14 -> 26932.374 | E15: =+C15-D15 -> 26932.374 | F15: BS | G15: Autres actifs courants | H15: A
B16: clients | D16: =+C11/360*350 -> 1795491.6 | E16: =+C16-D16 -> -1795491.6 | F16: BS | G16: Clients et comptes rattachés | H16: A | I16: Hyp : DRCC 10 J
B17: Achat MP | C17: =+'Ach prévisionnel'!D10+('Consommations Q'!C26*Données!B35)+('Consommations Q'!C39*Données!B17) -> 1217013.2 | E17: =+C17-D17 -> 1217013.2 | F17: PL
B18: TVA/ACHAT | C18: =-TVA!C4-TVA!C7-TVA!C8 -> 204853.91 | E18: =+C18-D18 -> 204853.91 | F18: BS | G18: Autres actifs courants | H18: A
B19: fournisseur | D19: =+C17+C18 -> 1421867.1 | E19: =+C19-D19 -> -1421867.1 | F19: BS | G19: Fournisseurs et comptes rattachés | H19: P
B20: Stock PF | C20: =+D21 -> 40538.501 | E20: =+C20-D20 -> 40538.501 | F20: BS | G20: Stocks | H20: A
B21: Variation de stock PF | D21: =+'Cout de production prévisionnel'!E10 -> 40538.501 | E21: =+C21-D21 -> -40538.501 | F21: PL
B22: Stock MP | C22: =+'Ach prévisionnel'!F10+'Ach prévisionnel'!F24+'Ach prévisionnel'!F37 -> 93616.397 | E22: =+C22-D22 -> 93616.397 | F22: BS | G22: Stocks | H22: A
B23: Variation de stock MP | D23: =+C22 -> 93616.397 | E23: =+C23-D23 -> -93616.397 | F23: PL
B24: fournisseur | C24: =+D19/13*11.5 -> 1257805.5 | E24: =+C24-D24 -> 1257805.5 | F24: BS | G24: Fournisseurs et comptes rattachés | H24: P | I24: Hyp : DRDF 45 jours
B25: Banque | D25: =+C24-D26 -> 1238938.4 | E25: =+C25-D25 -> -1238938.4 | F25: BS | G25: Liquidités et équivalents de liquidités | H25: A
B26: retenue à la source/acht | D26: =+C24*0.015 -> 18867.082 | E26: =+C26-D26 -> -18867.082 | F26: BS | G26: Autres passifs courants | H26: P
B27: retenue à la source/acht | C27: =+D26/12*11 -> 17294.826 | E27: =+C27-D27 -> 17294.826 | F27: BS | G27: Autres passifs courants | H27: P
B28: Banque | D28: =+C27 -> 17294.826 | E28: =+C28-D28 -> -17294.826 | F28: BS | G28: Liquidités et équivalents de liquidités | H28: A
B29: Autres approv | C29: =+'Ach prévisionnel'!C47 -> 48396 | E29: =+C29-D29 -> 48396 | F29: PL
B30: TVA/ACHAT | C30: =-TVA!C9 -> 8711.28 | E30: =+C30-D30 -> 8711.28 | F30: BS | G30: Autres actifs courants | H30: A
B31: fournisseur | D31: =+(C29+C30-(D32+D33)) -> 1522.8608 | E31: =+C31-D31 -> -1522.8608 | F31: BS | G31: Fournisseurs et comptes rattachés | H31: p
B32: Banque | D32: =+(C29+C30)/12*11.5 -> 54727.81 | E32: =+C32-D32 -> -54727.81 | F32: BS | G32: Liquidités et équivalents de liquidités | H32: A | I32: Hyp règelment à 15 jours
